Workbook
Name CARGOS: [1]cargos_atlantico!$B$8:$B$33
Name EIXOS: [1]cargos_atlantico!$H$8:$H$14

Sheet total
E1: =SUBTOTAL(9,E4:E33) -> 146612.78 | F1: =SUBTOTAL(9,F4:F33) -> #VALUE! | G1: =SUBTOTAL(9,G4:G33) -> #VALUE! | H1: =SUBTOTAL(9,H4:H33) -> #VALUE! | I1: =SUBTOTAL(9,I4:I33) -> 4514.33 | J1: =SUBTOTAL(9,J4:J33) -> 640.0223 | K1: =SUBTOTAL(9,K4:K33) -> 3874.3077 | L1: =SUBTOTAL(9,L4:L33) -> 15150 | ... BP1: =SUBTOTAL(9,BP4:BP33) -> 0
B2: Mat | C2: Matrícula | D2: Nome | E2: Salário | F2: Unimed | I2: Uniodonto | L2: Caju | O2: Seguro de Vida | R2: Sistel | U2: Claro | V2: Auxílio Creche | W2: Reembolso Func | X2: Transporte | AA2: Pensão Alimentícia | AB2: Gratificação | AC2: Auxílio Pós Graduação | AD2: Auxílio HO | AE2: ASO | AF2: Auxílio Funeral | AG2: Indicação Premiada | AH2: Assistência Saúde | AK2: Auxílio Transporte | AL2: Inglês Tim | AO2: Zenklub | AQ2: Zenklub | AR2: Bradesco Saúde | AU2: Bradesco Dental | AX2: Ascan | AY2: Comissão | AZ2: Academy | BA2: Diária de Viagem | BB2: Caju Extra | BE2: Open English | BH2: Gympass | BI2: Agiel | BJ2: Caju Intermitentes | BM2: Diferença Sistel | BO2: Auxílio HO - Intermitente | BP2: Creche - Intermitente
F3: Fatura | G3: Desconto | H3: Custo | I3: Fatura | J3: Desconto | K3: Custo | L3: Fatura | M3: Desconto | N3: Custo | O3: Fatura | P3: Desconto | Q3: Custo | R3: Folha | S3: Empresti | T3: Custo | V3: Custo | X3: Fatura | Y3: Desconto | Z3: Custo | AA3: Desconto | AB3: Custo | AH3: Fatura | AI3: Desconto | AJ3: Custo | AL3: Fatura | AM3: Desconto | AN3: Custo | AO3: Fatura | AP3: Desconto | AQ3: Custo | AR3: Fatura | AS3: Desconto | AT3: Custo | AU3: Fatura | AV3: Desconto | AW3: Custo | BB3: Fatura | BC3: Desconto | BD3: Custo | BE3: Fatura | BF3: Desconto | BG3: Custo | BH3: Custo | BI3: Custo | BJ3: Fatura | BK3: Desconto | BL3: Custo | BM3: Folha | BN3: Custo
B4: 1 | C4: =VLOOKUP(B4,salario!$A$3:$C$195,2,0) -> ATIVO | D4: =VLOOKUP(B4,salario!$A$3:$C$195,3,0) -> Colaborador 1 | E4: =IFERROR(VLOOKUP(B4,salario!$A$3:$K$854,11,0), "0") -> 5826.03 | F4: =SUMIF([2]unimed!$AL:$AL,B4,[2]unimed!$AJ:$AJ) -> #VALUE! | G4: =SUMIF([2]unimed!$AL:$AL,B4,[2]unimed!$AQ:$AQ) -> #VALUE! | H4: =SUMIF([2]unimed!$AL:$AL,B4,[2]unimed!$AP:$AP) -> #VALUE! | I4: =IFERROR(VLOOKUP(B4,uniodonto!$B$3:$F$339,5,0),0) -> 84.38 | J4: =IF(E4>=0,IF(AND(E4>tabelas!$C$4,E4<=tabelas!$C$5),I4*tabelas!$E$4,IF(AND(E4>=tabelas!$C$5,E4<=tabelas!$C$6),I4*tabelas!$E$5,IF(AND(E4>=tabelas!$C$6,E4<=tabelas!$C$7),I4*tabelas!$E$6,IF(AND(E4>0,E4>tabelas!$C$7),I4*tabelas!$E$7,0))))) -> 12.657 | K4: =I4-J4 -> 71.723 | L4: =SUMIF(caju!$A$4:$A$562,total!B4,caju!$C$4:$C$2900) -> 500 | M4: =IF(E4>=0,IF(AND(E4>tabelas!$C$11,E4<=tabelas!$C$12),L4*tabelas!$E$11,IF(AND(E4>=tabelas!$C$12,E4<=tabelas!$C$13),L4*tabelas!$E$12,IF(AND(E4>=tabelas!$C$13,E4<=tabelas!$C$14),L4*tabelas!$E$13,IF(AND(E4>0,E4>tabelas!$C$14),L4*tabelas!$E$14,0))))) -> 30 | N4: =L4-M4 -> 470 | O4: =IFERROR(VLOOKUP(B4,segurodevida!$B$4:$E$588,4,0),0) -> 18.614166 | P4: =O4/2 -> 9.3070829 | Q4: =O4-P4 -> 9.3070829 | V4: =IFERROR(VLOOKUP(B4,#REF!,3,0),0) -> 0 | W4: =SUMIF(#REF!,total!B4,#REF!) -> #REF! | X4: =IFERROR(VLOOKUP(B4,#REF!,4,0),0) -> 0 | Y4: =IFERROR(VLOOKUP(B4,#REF!,5,0),0) -> 0 | Z4: =IFERROR(X4-Y4,0) -> 0 | AA4: =IFERROR(VLOOKUP(B4,#REF!,3,0),0) -> 0 | AB4: =IFERROR(VLOOKUP(B4,#REF!,3,0),0) -> 0 | AC4: =IFERROR(VLOOKUP(B4,#REF!,5,0),0) -> 0 | AD4: 275 | AE4: =IFERROR(VLOOKUP(B4,#REF!,3,0),0) -> 0 | AF4: =IFERROR(VLOOKUP(B4,#REF!,3,0),0) -> 0 | AG4: =IFERROR(VLOOKUP(B4,#REF!,3,0),0) -> 0 | AK4: =IFERROR(VLOOKUP(B4,#REF!,3,0),0) -> 0 | AL4: =IFERROR(VLOOKUP(B4,ingles!$A$2:$C$673,3,0),"-") -> 165 | AM4: =ROUNDUP(IFERROR(AL4*39.39%,"0"),1) -> 65 | AN4: =IFERROR(AL4-AM4,"-") -> 100 | AO4: =SUMIFS(zenklub!I:I,zenklub!A:A,total!B4) -> 90.566667 | AP4: =SUMIF(zenklub!$A$49:$A$106,total!B4,zenklub!$I$49:$I$106) -> 23.9 | AQ4: =AO4-AP4 -> 66.666667 | AR4: =SUMIF([3]bradesco!$C:$C,B4,[3]bradesco!$M:$M) -> #VALUE! | AS4: =SUMIF([3]bradesco!$C:$C,B4,[3]bradesco!$V:$V) -> #VALUE! | AT4: =IFERROR(SUMIF([3]bradesco!$C:$C,B4,[3]bradesco!$Y:$Y),0) -> 0 | AU4: =SUMIF([4]bradesco!$C:$C,B4,[4]bradesco!$M:$M) -> #VALUE! | AV4: =SUMIF([4]bradesco!$C:$C,B4,[4]bradesco!$V:$V) -> #VALUE! | AW4: =AU4-AV4 -> #VALUE! | AX4: =IFERROR(VLOOKUP(B4,#REF!,3,0),0) -> 0 | AY4: =IFERROR(VLOOKUP(B4,#REF!,3,0),0) -> 0 | AZ4: =IFERROR(VLOOKUP(B4,#REF!,3,0),0) -> 0 | BA4: 0 | BB4: =IFERROR(VLOOKUP(B4,#REF!,3,0),0) -> 0 | BC4: =IF(E4>=0,IF(AND(E4>tabelas!$C$11,E4<=tabelas!$C$12),BB4*tabelas!$E$11,IF(AND(E4>=tabelas!$C$12,E4<=tabelas!$C$13),BB4*tabelas!$E$12,IF(AND(E4>=tabelas!$C$13,E4<=tabelas!$C$14),BB4*tabelas!$E$13,IF(AND(E4>0,E4>tabelas!$C$14),BB4*tabelas!$E$14,0))))) -> 0 | BD4: =BB4-BC4 -> 0 | BE4: =SUMIF(open_english!A:A,total!B4,open_english!C:C) -> 138.88889 | BF4: =SUMIF(open_english!A:A,total!B4,open_english!D:D) -> 96.56 | BG4: =SUMIF(open_english!A:A,total!B4,open_english!E:E) -> 42.328889 | BH4: =IFERROR(VLOOKUP(B4,gympass!$A$2:$F$527,6,0),"-") -> 166.66667 | BI4: =IFERROR(VLOOKUP(B4,#REF!,4,0),"-") -> - | BJ4: =IFERROR(VLOOKUP(B4,#REF!,3,0),0) -> 0 | BK4: =IF(E4>=0,IF(AND(E4>tabelas!$C$11,E4<=tabelas!$C$12),BJ4*tabelas!$E$11,IF(AND(E4>=tabelas!$C$12,E4<=tabelas!$C$13),BJ4*tabelas!$E$12,IF(AND(E4>=tabelas!$C$13,E4<=tabelas!$C$14),BJ4*tabelas!$E$13,IF(AND(E4>0,E4>tabelas!$C$14),BJ4*tabelas!$E$14,0))))) -> 0 | BL4: =BJ4-BK4 -> 0 | BM4: =IFERROR(INDEX(dif_sistel!L:L,MATCH(total!B4,dif_sistel!D:D,0)),0)+IFERROR(INDEX(dif_sistel!N:N,MATCH(total!B4,dif_sistel!D:D,0)),0) -> 0 | BN4: =IFERROR(VLOOKUP(B4,dif_sistel!$D$3:$X$257,21,0),0) -> 0 | BO4: =IFERROR(SUMIF(#REF!,total!B4,#REF!),"0") -> 0 | BP4: =IFERROR(SUMIF(#REF!,total!B4,#REF!),"0") -> 0
B5: 2 | C5: =VLOOKUP(B5,salario!$A$3:$C$195,2,0) -> ATIVO | D5: =VLOOKUP(B5,salario!$A$3:$C$195,3,0) -> Colaborador 2 | E5: =IFERROR(VLOOKUP(B5,salario!$A$3:$K$854,11,0), "0") -> 4332.22 | F5: =SUMIF([2]unimed!$AL:$AL,B5,[2]unimed!$AJ:$AJ) -> #VALUE! | G5: =SUMIF([2]unimed!$AL:$AL,B5,[2]unimed!$AQ:$AQ) -> #VALUE! | H5: =SUMIF([2]unimed!$AL:$AL,B5,[2]unimed!$AP:$AP) -> #VALUE! | I5: =IFERROR(VLOOKUP(B5,uniodonto!$B$3:$F$339,5,0),0) -> 210.95 | J5: =IF(E5>=0,IF(AND(E5>tabelas!$C$4,E5<=tabelas!$C$5),I5*tabelas!$E$4,IF(AND(E5>=tabelas!$C$5,E5<=tabelas!$C$6),I5*tabelas!$E$5,IF(AND(E5>=tabelas!$C$6,E5<=tabelas!$C$7),I5*tabelas!$E$6,IF(AND(E5>0,E5>tabelas!$C$7),I5*tabelas!$E$7,0))))) -> 31.6425 | K5: =I5-J5 -> 179.3075 | L5: =SUMIF(caju!$A$4:$A$562,total!B5,caju!$C$4:$C$2900) -> 500 | M5: =IF(E5>=0,IF(AND(E5>tabelas!$C$11,E5<=tabelas!$C$12),L5*tabelas!$E$11,IF(AND(E5>=tabelas!$C$12,E5<=tabelas!$C$13),L5*tabelas!$E$12,IF(AND(E5>=tabelas!$C$13,E5<=tabelas!$C$14),L5*tabelas!$E$13,IF(AND(E5>0,E5>tabelas!$C$14),L5*tabelas!$E$14,0))))) -> 30 | N5: =L5-M5 -> 470 | O5: =IFERROR(VLOOKUP(B5,segurodevida!$B$4:$E$588,4,0),0) -> 13.841443 | P5: =O5/2 -> 6.9207215 | Q5: =O5-P5 -> 6.9207215 | V5: =IFERROR(VLOOKUP(B5,#REF!,3,0),0) -> 0 | W5: =SUMIF(#REF!,total!B5,#REF!) -> #REF! | X5: =IFERROR(VLOOKUP(B5,#REF!,4,0),0) -> 0 | Y5: =IFERROR(VLOOKUP(B5,#REF!,5,0),0) -> 0 | Z5: =IFERROR(X5-Y5,0) -> 0 | AA5: =IFERROR(VLOOKUP(B5,#REF!,3,0),0) -> 0 | AB5: =IFERROR(VLOOKUP(B5,#REF!,3,0),0) -> 0 | AC5: =IFERROR(VLOOKUP(B5,#REF!,5,0),0) -> 0 | AD5: 275 | AE5: =IFERROR(VLOOKUP(B5,#REF!,3,0),0) -> 0 | AF5: =IFERROR(VLOOKUP(B5,#REF!,3,0),0) -> 0 | AG5: =IFERROR(VLOOKUP(B5,#REF!,3,0),0) -> 0 | AK5: =IFERROR(VLOOKUP(B5,#REF!,3,0),0) -> 0 | AL5: =IFERROR(VLOOKUP(B5,ingles!$A$2:$C$673,3,0),"-") -> 165 | AM5: =ROUNDUP(IFERROR(AL5*39.39%,"0"),1) -> 65 | AN5: =IFERROR(AL5-AM5,"-") -> 100 | AO5: =SUMIFS(zenklub!I:I,zenklub!A:A,total!B5) -> 90.566667 | AP5: =SUMIF(zenklub!$A$49:$A$106,total!B5,zenklub!$I$49:$I$106) -> 23.9 | AQ5: =AO5-AP5 -> 66.666667 | AR5: =SUMIF([3]bradesco!$C:$C,B5,[3]bradesco!$M:$M) -> #VALUE! | AS5: =SUMIF([3]bradesco!$C:$C,B5,[3]bradesco!$V:$V) -> #VALUE! | AT5: =IFERROR(SUMIF([3]bradesco!$C:$C,B5,[3]bradesco!$Y:$Y),0) -> 0 | AU5: =SUMIF([4]bradesco!$C:$C,B5,[4]bradesco!$M:$M) -> #VALUE! | AV5: =SUMIF([4]bradesco!$C:$C,B5,[4]bradesco!$V:$V) -> #VALUE! | AW5: =AU5-AV5 -> #VALUE! | AX5: =IFERROR(VLOOKUP(B5,#REF!,3,0),0) -> 0 | AY5: =IFERROR(VLOOKUP(B5,#REF!,3,0),0) -> 0 | AZ5: =IFERROR(VLOOKUP(B5,#REF!,3,0),0) -> 0 | BA5: 0 | BB5: =IFERROR(VLOOKUP(B5,#REF!,3,0),0) -> 0 | BC5: =IF(E5>=0,IF(AND(E5>tabelas!$C$11,E5<=tabelas!$C$12),BB5*tabelas!$E$11,IF(AND(E5>=tabelas!$C$12,E5<=tabelas!$C$13),BB5*tabelas!$E$12,IF(AND(E5>=tabelas!$C$13,E5<=tabelas!$C$14),BB5*tabelas!$E$13,IF(AND(E5>0,E5>tabelas!$C$14),BB5*tabelas!$E$14,0))))) -> 0 | BD5: =BB5-BC5 -> 0 | BE5: =SUMIF(open_english!A:A,total!B5,open_english!C:C) -> 138.88889 | BF5: =SUMIF(open_english!A:A,total!B5,open_english!D:D) -> 96.56 | BG5: =SUMIF(open_english!A:A,total!B5,open_english!E:E) -> 42.328889 | BH5: =IFERROR(VLOOKUP(B5,gympass!$A$2:$F$527,6,0),"-") -> 166.66667 | BI5: =IFERROR(VLOOKUP(B5,#REF!,4,0),"-") -> - | BJ5: =IFERROR(VLOOKUP(B5,#REF!,3,0),0) -> 0 | BK5: =IF(E5>=0,IF(AND(E5>tabelas!$C$11,E5<=tabelas!$C$12),BJ5*tabelas!$E$11,IF(AND(E5>=tabelas!$C$12,E5<=tabelas!$C$13),BJ5*tabelas!$E$12,IF(AND(E5>=tabelas!$C$13,E5<=tabelas!$C$14),BJ5*tabelas!$E$13,IF(AND(E5>0,E5>tabelas!$C$14),BJ5*tabelas!$E$14,0))))) -> 0 | BL5: =BJ5-BK5 -> 0 | BM5: =IFERROR(INDEX(dif_sistel!L:L,MATCH(total!B5,dif_sistel!D:D,0)),0)+IFERROR(INDEX(dif_sistel!N:N,MATCH(total!B5,dif_sistel!D:D,0)),0) -> 0 | BN5: =IFERROR(VLOOKUP(B5,dif_sistel!$D$3:$X$257,21,0),0) -> 0 | BO5: =IFERROR(SUMIF(#REF!,total!B5,#REF!),"0") -> 0 | BP5: =IFERROR(SUMIF(#REF!,total!B5,#REF!),"0") -> 0
B6: 3 | C6: =VLOOKUP(B6,salario!$A$3:$C$195,2,0) -> ATIVO | D6: =VLOOKUP(B6,salario!$A$3:$C$195,3,0) -> Colaborador 3 | E6: =IFERROR(VLOOKUP(B6,salario!$A$3:$K$854,11,0), "0") -> 4714.12 | F6: =SUMIF([2]unimed!$AL:$AL,B6,[2]unimed!$AJ:$AJ) -> #VALUE! | G6: =SUMIF([2]unimed!$AL:$AL,B6,[2]unimed!$AQ:$AQ) -> #VALUE! | H6: =SUMIF([2]unimed!$AL:$AL,B6,[2]unimed!$AP:$AP) -> #VALUE! | I6: =IFERROR(VLOOKUP(B6,uniodonto!$B$3:$F$339,5,0),0) -> 253.14 | J6: =IF(E6>=0,IF(AND(E6>tabelas!$C$4,E6<=tabelas!$C$5),I6*tabelas!$E$4,IF(AND(E6>=tabelas!$C$5,E6<=tabelas!$C$6),I6*tabelas!$E$5,IF(AND(E6>=tabelas!$C$6,E6<=tabelas!$C$7),I6*tabelas!$E$6,IF(AND(E6>0,E6>tabelas!$C$7),I6*tabelas!$E$7,0))))) -> 37.971 | K6: =I6-J6 -> 215.169 | L6: =SUMIF(caju!$A$4:$A$562,total!B6,caju!$C$4:$C$2900) -> 500 | M6: =IF(E6>=0,IF(AND(E6>tabelas!$C$11,E6<=tabelas!$C$12),L6*tabelas!$E$11,IF(AND(E6>=tabelas!$C$12,E6<=tabelas!$C$13),L6*tabelas!$E$12,IF(AND(E6>=tabelas!$C$13,E6<=tabelas!$C$14),L6*tabelas!$E$13,IF(AND(E6>0,E6>tabelas!$C$14),L6*tabelas!$E$14,0))))) -> 30 | N6: =L6-M6 -> 470 | O6: =IFERROR(VLOOKUP(B6,segurodevida!$B$4:$E$588,4,0),0) -> 15.061613 | P6: =O6/2 -> 7.5308067 | Q6: =O6-P6 -> 7.5308067 | V6: =IFERROR(VLOOKUP(B6,#REF!,3,0),0) -> 0 | W6: =SUMIF(#REF!,total!B6,#REF!) -> #REF! | X6: =IFERROR(VLOOKUP(B6,#REF!,4,0),0) -> 0 | Y6: =IFERROR(VLOOKUP(B6,#REF!,5,0),0) -> 0 | Z6: =IFERROR(X6-Y6,0) -> 0 | AA6: =IFERROR(VLOOKUP(B6,#REF!,3,0),0) -> 0 | AB6: =IFERROR(VLOOKUP(B6,#REF!,3,0),0) -> 0 | AC6: =IFERROR(VLOOKUP(B6,#REF!,5,0),0) -> 0 | AD6: 275 | AE6: =IFERROR(VLOOKUP(B6,#REF!,3,0),0) -> 0 | AF6: =IFERROR(VLOOKUP(B6,#REF!,3,0),0) -> 0 | AG6: =IFERROR(VLOOKUP(B6,#REF!,3,0),0) -> 0 | AK6: =IFERROR(VLOOKUP(B6,#REF!,3,0),0) -> 0 | AL6: =IFERROR(VLOOKUP(B6,ingles!$A$2:$C$673,3,0),"-") -> 165 | AM6: =ROUNDUP(IFERROR(AL6*39.39%,"0"),1) -> 65 | AN6: =IFERROR(AL6-AM6,"-") -> 100 | AO6: =SUMIFS(zenklub!I:I,zenklub!A:A,total!B6) -> 90.566667 | AP6: =SUMIF(zenklub!$A$49:$A$106,total!B6,zenklub!$I$49:$I$106) -> 23.9 | AQ6: =AO6-AP6 -> 66.666667 | AR6: =SUMIF([3]bradesco!$C:$C,B6,[3]bradesco!$M:$M) -> #VALUE! | AS6: =SUMIF([3]bradesco!$C:$C,B6,[3]bradesco!$V:$V) -> #VALUE! | AT6: =IFERROR(SUMIF([3]bradesco!$C:$C,B6,[3]bradesco!$Y:$Y),0) -> 0 | AU6: =SUMIF([4]bradesco!$C:$C,B6,[4]bradesco!$M:$M) -> #VALUE! | AV6: =SUMIF([4]bradesco!$C:$C,B6,[4]bradesco!$V:$V) -> #VALUE! | AW6: =AU6-AV6 -> #VALUE! | AX6: =IFERROR(VLOOKUP(B6,#REF!,3,0),0) -> 0 | AY6: =IFERROR(VLOOKUP(B6,#REF!,3,0),0) -> 0 | AZ6: =IFERROR(VLOOKUP(B6,#REF!,3,0),0) -> 0 | BA6: 0 | BB6: =IFERROR(VLOOKUP(B6,#REF!,3,0),0) -> 0 | BC6: =IF(E6>=0,IF(AND(E6>tabelas!$C$11,E6<=tabelas!$C$12),BB6*tabelas!$E$11,IF(AND(E6>=tabelas!$C$12,E6<=tabelas!$C$13),BB6*tabelas!$E$12,IF(AND(E6>=tabelas!$C$13,E6<=tabelas!$C$14),BB6*tabelas!$E$13,IF(AND(E6>0,E6>tabelas!$C$14),BB6*tabelas!$E$14,0))))) -> 0 | BD6: =BB6-BC6 -> 0 | BE6: =SUMIF(open_english!A:A,total!B6,open_english!C:C) -> 138.88889 | BF6: =SUMIF(open_english!A:A,total!B6,open_english!D:D) -> 96.56 | BG6: =SUMIF(open_english!A:A,total!B6,open_english!E:E) -> 42.328889 | BH6: =IFERROR(VLOOKUP(B6,gympass!$A$2:$F$527,6,0),"-") -> 166.66667 | BI6: =IFERROR(VLOOKUP(B6,#REF!,4,0),"-") -> - | BJ6: =IFERROR(VLOOKUP(B6,#REF!,3,0),0) -> 0 | BK6: =IF(E6>=0,IF(AND(E6>tabelas!$C$11,E6<=tabelas!$C$12),BJ6*tabelas!$E$11,IF(AND(E6>=tabelas!$C$12,E6<=tabelas!$C$13),BJ6*tabelas!$E$12,IF(AND(E6>=tabelas!$C$13,E6<=tabelas!$C$14),BJ6*tabelas!$E$13,IF(AND(E6>0,E6>tabelas!$C$14),BJ6*tabelas!$E$14,0))))) -> 0 | BL6: =BJ6-BK6 -> 0 | BM6: =IFERROR(INDEX(dif_sistel!L:L,MATCH(total!B6,dif_sistel!D:D,0)),0)+IFERROR(INDEX(dif_sistel!N:N,MATCH(total!B6,dif_sistel!D:D,0)),0) -> 0 | BN6: =IFERROR(VLOOKUP(B6,dif_sistel!$D$3:$X$257,21,0),0) -> 0 | BO6: =IFERROR(SUMIF(#REF!,total!B6,#REF!),"0") -> 0 | BP6: =IFERROR(SUMIF(#REF!,total!B6,#REF!),"0") -> 0
B7: 4 | C7: =VLOOKUP(B7,salario!$A$3:$C$195,2,0) -> ATIVO | D7: =VLOOKUP(B7,salario!$A$3:$C$195,3,0) -> Colaborador 4 | E7: =IFERROR(VLOOKUP(B7,salario!$A$3:$K$854,11,0), "0") -> 7685.13 | F7: =SUMIF([2]unimed!$AL:$AL,B7,[2]unimed!$AJ:$AJ) -> #VALUE! | G7: =SUMIF([2]unimed!$AL:$AL,B7,[2]unimed!$AQ:$AQ) -> #VALUE! | H7: =SUMIF([2]unimed!$AL:$AL,B7,[2]unimed!$AP:$AP) -> #VALUE! | I7: =IFERROR(VLOOKUP(B7,uniodonto!$B$3:$F$339,5,0),0) -> 42.19 | J7: =IF(E7>=0,IF(AND(E7>tabelas!$C$4,E7<=tabelas!$C$5),I7*tabelas!$E$4,IF(AND(E7>=tabelas!$C$5,E7<=tabelas!$C$6),I7*tabelas!$E$5,IF(AND(E7>=tabelas!$C$6,E7<=tabelas!$C$7),I7*tabelas!$E$6,IF(AND(E7>0,E7>tabelas!$C$7),I7*tabelas!$E$7,0))))) -> 9.7037 | K7: =I7-J7 -> 32.4863 | L7: =SUMIF(caju!$A$4:$A$562,total!B7,caju!$C$4:$C$2900) -> 500 | M7: =IF(E7>=0,IF(AND(E7>tabelas!$C$11,E7<=tabelas!$C$12),L7*tabelas!$E$11,IF(AND(E7>=tabelas!$C$12,E7<=tabelas!$C$13),L7*tabelas!$E$12,IF(AND(E7>=tabelas!$C$13,E7<=tabelas!$C$14),L7*tabelas!$E$13,IF(AND(E7>0,E7>tabelas!$C$14),L7*tabelas!$E$14,0))))) -> 50 | N7: =L7-M7 -> 450 | O7: =IFERROR(VLOOKUP(B7,segurodevida!$B$4:$E$588,4,0),0) -> 24.55399 | P7: =O7/2 -> 12.276995 | Q7: =O7-P7 -> 12.276995 | V7: =IFERROR(VLOOKUP(B7,#REF!,3,0),0) -> 0 | W7: =SUMIF(#REF!,total!B7,#REF!) -> #REF! | X7: =IFERROR(VLOOKUP(B7,#REF!,4,0),0) -> 0 | Y7: =IFERROR(VLOOKUP(B7,#REF!,5,0),0) -> 0 | Z7: =IFERROR(X7-Y7,0) -> 0 | AA7: =IFERROR(VLOOKUP(B7,#REF!,3,0),0) -> 0 | AB7: =IFERROR(VLOOKUP(B7,#REF!,3,0),0) -> 0 | AC7: =IFERROR(VLOOKUP(B7,#REF!,5,0),0) -> 0 | AD7: 275 | AE7: =IFERROR(VLOOKUP(B7,#REF!,3,0),0) -> 0 | AF7: =IFERROR(VLOOKUP(B7,#REF!,3,0),0) -> 0 | AG7: =IFERROR(VLOOKUP(B7,#REF!,3,0),0) -> 0 | AK7: =IFERROR(VLOOKUP(B7,#REF!,3,0),0) -> 0 | AL7: =IFERROR(VLOOKUP(B7,ingles!$A$2:$C$673,3,0),"-") -> 165 | AM7: =ROUNDUP(IFERROR(AL7*39.39%,"0"),1) -> 65 | AN7: =IFERROR(AL7-AM7,"-") -> 100 | AO7: =SUMIFS(zenklub!I:I,zenklub!A:A,total!B7) -> 90.566667 | AP7: =SUMIF(zenklub!$A$49:$A$106,total!B7,zenklub!$I$49:$I$106) -> 23.9 | AQ7: =AO7-AP7 -> 66.666667 | AR7: =SUMIF([3]bradesco!$C:$C,B7,[3]bradesco!$M:$M) -> #VALUE! | AS7: =SUMIF([3]bradesco!$C:$C,B7,[3]bradesco!$V:$V) -> #VALUE! | AT7: =IFERROR(SUMIF([3]bradesco!$C:$C,B7,[3]bradesco!$Y:$Y),0) -> 0 | AU7: =SUMIF([4]bradesco!$C:$C,B7,[4]bradesco!$M:$M) -> #VALUE! | AV7: =SUMIF([4]bradesco!$C:$C,B7,[4]bradesco!$V:$V) -> #VALUE! | AW7: =AU7-AV7 -> #VALUE! | AX7: =IFERROR(VLOOKUP(B7,#REF!,3,0),0) -> 0 | AY7: =IFERROR(VLOOKUP(B7,#REF!,3,0),0) -> 0 | AZ7: =IFERROR(VLOOKUP(B7,#REF!,3,0),0) -> 0 | BA7: 0 | BB7: =IFERROR(VLOOKUP(B7,#REF!,3,0),0) -> 0 | BC7: =IF(E7>=0,IF(AND(E7>tabelas!$C$11,E7<=tabelas!$C$12),BB7*tabelas!$E$11,IF(AND(E7>=tabelas!$C$12,E7<=tabelas!$C$13),BB7*tabelas!$E$12,IF(AND(E7>=tabelas!$C$13,E7<=tabelas!$C$14),BB7*tabelas!$E$13,IF(AND(E7>0,E7>tabelas!$C$14),BB7*tabelas!$E$14,0))))) -> 0 | BD7: =BB7-BC7 -> 0 | BE7: =SUMIF(open_english!A:A,total!B7,open_english!C:C) -> 138.88889 | BF7: =SUMIF(open_english!A:A,total!B7,open_english!D:D) -> 96.56 | BG7: =SUMIF(open_english!A:A,total!B7,open_english!E:E) -> 42.328889 | BH7: =IFERROR(VLOOKUP(B7,gympass!$A$2:$F$527,6,0),"-") -> 166.66667 | BI7: =IFERROR(VLOOKUP(B7,#REF!,4,0),"-") -> - | BJ7: =IFERROR(VLOOKUP(B7,#REF!,3,0),0) -> 0 | BK7: =IF(E7>=0,IF(AND(E7>tabelas!$C$11,E7<=tabelas!$C$12),BJ7*tabelas!$E$11,IF(AND(E7>=tabelas!$C$12,E7<=tabelas!$C$13),BJ7*tabelas!$E$12,IF(AND(E7>=tabelas!$C$13,E7<=tabelas!$C$14),BJ7*tabelas!$E$13,IF(AND(E7>0,E7>tabelas!$C$14),BJ7*tabelas!$E$14,0))))) -> 0 | BL7: =BJ7-BK7 -> 0 | BM7: =IFERROR(INDEX(dif_sistel!L:L,MATCH(total!B7,dif_sistel!D:D,0)),0)+IFERROR(INDEX(dif_sistel!N:N,MATCH(total!B7,dif_sistel!D:D,0)),0) -> 0 | BN7: =IFERROR(VLOOKUP(B7,dif_sistel!$D$3:$X$257,21,0),0) -> 0 | BO7: =IFERROR(SUMIF(#REF!,total!B7,#REF!),"0") -> 0 | BP7: =IFERROR(SUMIF(#REF!,total!B7,#REF!),"0") -> 0
B8: 5 | C8: =VLOOKUP(B8,salario!$A$3:$C$195,2,0) -> ATIVO | D8: =VLOOKUP(B8,salario!$A$3:$C$195,3,0) -> Colaborador 5 | E8: =IFERROR(VLOOKUP(B8,salario!$A$3:$K$854,11,0), "0") -> 3652.6 | F8: =SUMIF([2]unimed!$AL:$AL,B8,[2]unimed!$AJ:$AJ) -> #VALUE! | G8: =SUMIF([2]unimed!$AL:$AL,B8,[2]unimed!$AQ:$AQ) -> #VALUE! | H8: =SUMIF([2]unimed!$AL:$AL,B8,[2]unimed!$AP:$AP) -> #VALUE! | I8: =IFERROR(VLOOKUP(B8,uniodonto!$B$3:$F$339,5,0),0) -> 253.14 | J8: =IF(E8>=0,IF(AND(E8>tabelas!$C$4,E8<=tabelas!$C$5),I8*tabelas!$E$4,IF(AND(E8>=tabelas!$C$5,E8<=tabelas!$C$6),I8*tabelas!$E$5,IF(AND(E8>=tabelas!$C$6,E8<=tabelas!$C$7),I8*tabelas!$E$6,IF(AND(E8>0,E8>tabelas!$C$7),I8*tabelas!$E$7,0))))) -> 17.7198 | K8: =I8-J8 -> 235.4202 | L8: =SUMIF(caju!$A$4:$A$562,total!B8,caju!$C$4:$C$2900) -> 500 | M8: =IF(E8>=0,IF(AND(E8>tabelas!$C$11,E8<=tabelas!$C$12),L8*tabelas!$E$11,IF(AND(E8>=tabelas!$C$12,E8<=tabelas!$C$13),L8*tabelas!$E$12,IF(AND(E8>=tabelas!$C$13,E8<=tabelas!$C$14),L8*tabelas!$E$13,IF(AND(E8>0,E8>tabelas!$C$14),L8*tabelas!$E$14,0))))) -> 10 | N8: =L8-M8 -> 490 | O8: =IFERROR(VLOOKUP(B8,segurodevida!$B$4:$E$588,4,0),0) -> 11.670057 | P8: =O8/2 -> 5.8350285 | Q8: =O8-P8 -> 5.8350285 | V8: =IFERROR(VLOOKUP(B8,#REF!,3,0),0) -> 0 | W8: =SUMIF(#REF!,total!B8,#REF!) -> #REF! | X8: =IFERROR(VLOOKUP(B8,#REF!,4,0),0) -> 0 | Y8: =IFERROR(VLOOKUP(B8,#REF!,5,0),0) -> 0 | Z8: =IFERROR(X8-Y8,0) -> 0 | AA8: =IFERROR(VLOOKUP(B8,#REF!,3,0),0) -> 0 | AB8: =IFERROR(VLOOKUP(B8,#REF!,3,0),0) -> 0 | AC8: =IFERROR(VLOOKUP(B8,#REF!,5,0),0) -> 0 | AD8: 275 | AE8: =IFERROR(VLOOKUP(B8,#REF!,3,0),0) -> 0 | AF8: =IFERROR(VLOOKUP(B8,#REF!,3,0),0) -> 0 | AG8: =IFERROR(VLOOKUP(B8,#REF!,3,0),0) -> 0 | AK8: =IFERROR(VLOOKUP(B8,#REF!,3,0),0) -> 0 | AL8: =IFERROR(VLOOKUP(B8,ingles!$A$2:$C$673,3,0),"-") -> 165 | AM8: =ROUNDUP(IFERROR(AL8*39.39%,"0"),1) -> 65 | AN8: =IFERROR(AL8-AM8,"-") -> 100 | AO8: =SUMIFS(zenklub!I:I,zenklub!A:A,total!B8) -> 90.566667 | AP8: =SUMIF(zenklub!$A$49:$A$106,total!B8,zenklub!$I$49:$I$106) -> 23.9 | AQ8: =AO8-AP8 -> 66.666667 | AR8: =SUMIF([3]bradesco!$C:$C,B8,[3]bradesco!$M:$M) -> #VALUE! | AS8: =SUMIF([3]bradesco!$C:$C,B8,[3]bradesco!$V:$V) -> #VALUE! | AT8: =IFERROR(SUMIF([3]bradesco!$C:$C,B8,[3]bradesco!$Y:$Y),0) -> 0 | AU8: =SUMIF([4]bradesco!$C:$C,B8,[4]bradesco!$M:$M) -> #VALUE! | AV8: =SUMIF([4]bradesco!$C:$C,B8,[4]bradesco!$V:$V) -> #VALUE! | AW8: =AU8-AV8 -> #VALUE! | AX8: =IFERROR(VLOOKUP(B8,#REF!,3,0),0) -> 0 | AY8: =IFERROR(VLOOKUP(B8,#REF!,3,0),0) -> 0 | AZ8: =IFERROR(VLOOKUP(B8,#REF!,3,0),0) -> 0 | BA8: 0 | BB8: =IFERROR(VLOOKUP(B8,#REF!,3,0),0) -> 0 | BC8: =IF(E8>=0,IF(AND(E8>tabelas!$C$11,E8<=tabelas!$C$12),BB8*tabelas!$E$11,IF(AND(E8>=tabelas!$C$12,E8<=tabelas!$C$13),BB8*tabelas!$E$12,IF(AND(E8>=tabelas!$C$13,E8<=tabelas!$C$14),BB8*tabelas!$E$13,IF(AND(E8>0,E8>tabelas!$C$14),BB8*tabelas!$E$14,0))))) -> 0 | BD8: =BB8-BC8 -> 0 | BE8: =SUMIF(open_english!A:A,total!B8,open_english!C:C) -> 138.88889 | BF8: =SUMIF(open_english!A:A,total!B8,open_english!D:D) -> 96.56 | BG8: =SUMIF(open_english!A:A,total!B8,open_english!E:E) -> 42.328889 | BH8: =IFERROR(VLOOKUP(B8,gympass!$A$2:$F$527,6,0),"-") -> 166.66667 | BI8: =IFERROR(VLOOKUP(B8,#REF!,4,0),"-") -> - | BJ8: =IFERROR(VLOOKUP(B8,#REF!,3,0),0) -> 0 | BK8: =IF(E8>=0,IF(AND(E8>tabelas!$C$11,E8<=tabelas!$C$12),BJ8*tabelas!$E$11,IF(AND(E8>=tabelas!$C$12,E8<=tabelas!$C$13),BJ8*tabelas!$E$12,IF(AND(E8>=tabelas!$C$13,E8<=tabelas!$C$14),BJ8*tabelas!$E$13,IF(AND(E8>0,E8>tabelas!$C$14),BJ8*tabelas!$E$14,0))))) -> 0 | BL8: =BJ8-BK8 -> 0 | BM8: =IFERROR(INDEX(dif_sistel!L:L,MATCH(total!B8,dif_sistel!D:D,0)),0)+IFERROR(INDEX(dif_sistel!N:N,MATCH(total!B8,dif_sistel!D:D,0)),0) -> 0 | BN8: =IFERROR(VLOOKUP(B8,dif_sistel!$D$3:$X$257,21,0),0) -> 0 | BO8: =IFERROR(SUMIF(#REF!,total!B8,#REF!),"0") -> 0 | BP8: =IFERROR(SUMIF(#REF!,total!B8,#REF!),"0") -> 0
B9: 6 | C9: =VLOOKUP(B9,salario!$A$3:$C$195,2,0) -> ATIVO | D9: =VLOOKUP(B9,salario!$A$3:$C$195,3,0) -> Colaborador 6 | E9: =IFERROR(VLOOKUP(B9,salario!$A$3:$K$854,11,0), "0") -> 7943.86 | F9: =SUMIF([2]unimed!$AL:$AL,B9,[2]unimed!$AJ:$AJ) -> #VALUE! | G9: =SUMIF([2]unimed!$AL:$AL,B9,[2]unimed!$AQ:$AQ) -> #VALUE! | H9: =SUMIF([2]unimed!$AL:$AL,B9,[2]unimed!$AP:$AP) -> #VALUE! | I9: =IFERROR(VLOOKUP(B9,uniodonto!$B$3:$F$339,5,0),0) -> 168.76 | J9: =IF(E9>=0,IF(AND(E9>tabelas!$C$4,E9<=tabelas!$C$5),I9*tabelas!$E$4,IF(AND(E9>=tabelas!$C$5,E9<=tabelas!$C$6),I9*tabelas!$E$5,IF(AND(E9>=tabelas!$C$6,E9<=tabelas!$C$7),I9*tabelas!$E$6,IF(AND(E9>0,E9>tabelas!$C$7),I9*tabelas!$E$7,0))))) -> 38.8148 | K9: =I9-J9 -> 129.9452 | L9: =SUMIF(caju!$A$4:$A$562,total!B9,caju!$C$4:$C$2900) -> 500 | M9: =IF(E9>=0,IF(AND(E9>tabelas!$C$11,E9<=tabelas!$C$12),L9*tabelas!$E$11,IF(AND(E9>=tabelas!$C$12,E9<=tabelas!$C$13),L9*tabelas!$E$12,IF(AND(E9>=tabelas!$C$13,E9<=tabelas!$C$14),L9*tabelas!$E$13,IF(AND(E9>0,E9>tabelas!$C$14),L9*tabelas!$E$14,0))))) -> 50 | N9: =L9-M9 -> 450 | O9: =IFERROR(VLOOKUP(B9,segurodevida!$B$4:$E$588,4,0),0) -> 25.380633 | P9: =O9/2 -> 12.690316 | Q9: =O9-P9 -> 12.690316 | V9: =IFERROR(VLOOKUP(B9,#REF!,3,0),0) -> 0 | W9: =SUMIF(#REF!,total!B9,#REF!) -> #REF! | X9: =IFERROR(VLOOKUP(B9,#REF!,4,0),0) -> 0 | Y9: =IFERROR(VLOOKUP(B9,#REF!,5,0),0) -> 0 | Z9: =IFERROR(X9-Y9,0) -> 0 | AA9: =IFERROR(VLOOKUP(B9,#REF!,3,0),0) -> 0 | AB9: =IFERROR(VLOOKUP(B9,#REF!,3,0),0) -> 0 | AC9: =IFERROR(VLOOKUP(B9,#REF!,5,0),0) -> 0 | AD9: 275 | AE9: =IFERROR(VLOOKUP(B9,#REF!,3,0),0) -> 0 | AF9: =IFERROR(VLOOKUP(B9,#REF!,3,0),0) -> 0 | AG9: =IFERROR(VLOOKUP(B9,#REF!,3,0),0) -> 0 | AK9: =IFERROR(VLOOKUP(B9,#REF!,3,0),0) -> 0 | AL9: =IFERROR(VLOOKUP(B9,ingles!$A$2:$C$673,3,0),"-") -> 165 | AM9: =ROUNDUP(IFERROR(AL9*39.39%,"0"),1) -> 65 | AN9: =IFERROR(AL9-AM9,"-") -> 100 | AO9: =SUMIFS(zenklub!I:I,zenklub!A:A,total!B9) -> 90.566667 | AP9: =SUMIF(zenklub!$A$49:$A$106,total!B9,zenklub!$I$49:$I$106) -> 23.9 | AQ9: =AO9-AP9 -> 66.666667 | AR9: =SUMIF([3]bradesco!$C:$C,B9,[3]bradesco!$M:$M) -> #VALUE! | AS9: =SUMIF([3]bradesco!$C:$C,B9,[3]bradesco!$V:$V) -> #VALUE! | AT9: =IFERROR(SUMIF([3]bradesco!$C:$C,B9,[3]bradesco!$Y:$Y),0) -> 0 | AU9: =SUMIF([4]bradesco!$C:$C,B9,[4]bradesco!$M:$M) -> #VALUE! | AV9: =SUMIF([4]bradesco!$C:$C,B9,[4]bradesco!$V:$V) -> #VALUE! | AW9: =AU9-AV9 -> #VALUE! | AX9: =IFERROR(VLOOKUP(B9,#REF!,3,0),0) -> 0 | AY9: =IFERROR(VLOOKUP(B9,#REF!,3,0),0) -> 0 | AZ9: =IFERROR(VLOOKUP(B9,#REF!,3,0),0) -> 0 | BA9: 0 | BB9: =IFERROR(VLOOKUP(B9,#REF!,3,0),0) -> 0 | BC9: =IF(E9>=0,IF(AND(E9>tabelas!$C$11,E9<=tabelas!$C$12),BB9*tabelas!$E$11,IF(AND(E9>=tabelas!$C$12,E9<=tabelas!$C$13),BB9*tabelas!$E$12,IF(AND(E9>=tabelas!$C$13,E9<=tabelas!$C$14),BB9*tabelas!$E$13,IF(AND(E9>0,E9>tabelas!$C$14),BB9*tabelas!$E$14,0))))) -> 0 | BD9: =BB9-BC9 -> 0 | BE9: =SUMIF(open_english!A:A,total!B9,open_english!C:C) -> 138.88889 | BF9: =SUMIF(open_english!A:A,total!B9,open_english!D:D) -> 96.56 | BG9: =SUMIF(open_english!A:A,total!B9,open_english!E:E) -> 42.328889 | BH9: =IFERROR(VLOOKUP(B9,gympass!$A$2:$F$527,6,0),"-") -> 166.66667 | BI9: =IFERROR(VLOOKUP(B9,#REF!,4,0),"-") -> - | BJ9: =IFERROR(VLOOKUP(B9,#REF!,3,0),0) -> 0 | BK9: =IF(E9>=0,IF(AND(E9>tabelas!$C$11,E9<=tabelas!$C$12),BJ9*tabelas!$E$11,IF(AND(E9>=tabelas!$C$12,E9<=tabelas!$C$13),BJ9*tabelas!$E$12,IF(AND(E9>=tabelas!$C$13,E9<=tabelas!$C$14),BJ9*tabelas!$E$13,IF(AND(E9>0,E9>tabelas!$C$14),BJ9*tabelas!$E$14,0))))) -> 0 | BL9: =BJ9-BK9 -> 0 | BM9: =IFERROR(INDEX(dif_sistel!L:L,MATCH(total!B9,dif_sistel!D:D,0)),0)+IFERROR(INDEX(dif_sistel!N:N,MATCH(total!B9,dif_sistel!D:D,0)),0) -> 0 | BN9: =IFERROR(VLOOKUP(B9,dif_sistel!$D$3:$X$257,21,0),0) -> 0 | BO9: =IFERROR(SUMIF(#REF!,total!B9,#REF!),"0") -> 0 | BP9: =IFERROR(SUMIF(#REF!,total!B9,#REF!),"0") -> 0
B10: 7 | C10: =VLOOKUP(B10,salario!$A$3:$C$195,2,0) -> ATIVO | D10: =VLOOKUP(B10,salario!$A$3:$C$195,3,0) -> Colaborador 7 | E10: =IFERROR(VLOOKUP(B10,salario!$A$3:$K$854,11,0), "0") -> 7131.14 | F10: =SUMIF([2]unimed!$AL:$AL,B10,[2]unimed!$AJ:$AJ) -> #VALUE! | G10: =SUMIF([2]unimed!$AL:$AL,B10,[2]unimed!$AQ:$AQ) -> #VALUE! | H10: =SUMIF([2]unimed!$AL:$AL,B10,[2]unimed!$AP:$AP) -> #VALUE! | I10: =IFERROR(VLOOKUP(B10,uniodonto!$B$3:$F$339,5,0),0) -> 168.76 | J10: =IF(E10>=0,IF(AND(E10>tabelas!$C$4,E10<=tabelas!$C$5),I10*tabelas!$E$4,IF(AND(E10>=tabelas!$C$5,E10<=tabelas!$C$6),I10*tabelas!$E$5,IF(AND(E10>=tabelas!$C$6,E10<=tabelas!$C$7),I10*tabelas!$E$6,IF(AND(E10>0,E10>tabelas!$C$7),I10*tabelas!$E$7,0))))) -> 25.314 | K10: =I10-J10 -> 143.446 | L10: =SUMIF(caju!$A$4:$A$562,total!B10,caju!$C$4:$C$2900) -> 500 | M10: =IF(E10>=0,IF(AND(E10>tabelas!$C$11,E10<=tabelas!$C$12),L10*tabelas!$E$11,IF(AND(E10>=tabelas!$C$12,E10<=tabelas!$C$13),L10*tabelas!$E$12,IF(AND(E10>=tabelas!$C$13,E10<=tabelas!$C$14),L10*tabelas!$E$13,IF(AND(E10>0,E10>tabelas!$C$14),L10*tabelas!$E$14,0))))) -> 30 | N10: =L10-M10 -> 470 | O10: =IFERROR(VLOOKUP(B10,segurodevida!$B$4:$E$588,4,0),0) -> 22.783992 | P10: =O10/2 -> 11.391996 | Q10: =O10-P10 -> 11.391996 | V10: =IFERROR(VLOOKUP(B10,#REF!,3,0),0) -> 0 | W10: =SUMIF(#REF!,total!B10,#REF!) -> #REF! | X10: =IFERROR(VLOOKUP(B10,#REF!,4,0),0) -> 0 | Y10: =IFERROR(VLOOKUP(B10,#REF!,5,0),0) -> 0 | Z10: =IFERROR(X10-Y10,0) -> 0 | AA10: =IFERROR(VLOOKUP(B10,#REF!,3,0),0) -> 0 | AB10: =IFERROR(VLOOKUP(B10,#REF!,3,0),0) -> 0 | AC10: =IFERROR(VLOOKUP(B10,#REF!,5,0),0) -> 0 | AD10: 275 | AE10: =IFERROR(VLOOKUP(B10,#REF!,3,0),0) -> 0 | AF10: =IFERROR(VLOOKUP(B10,#REF!,3,0),0) -> 0 | AG10: =IFERROR(VLOOKUP(B10,#REF!,3,0),0) -> 0 | AK10: =IFERROR(VLOOKUP(B10,#REF!,3,0),0) -> 0 | AL10: =IFERROR(VLOOKUP(B10,ingles!$A$2:$C$673,3,0),"-") -> 165 | AM10: =ROUNDUP(IFERROR(AL10*39.39%,"0"),1) -> 65 | AN10: =IFERROR(AL10-AM10,"-") -> 100 | AO10: =SUMIFS(zenklub!I:I,zenklub!A:A,total!B10) -> 90.566667 | AP10: =SUMIF(zenklub!$A$49:$A$106,total!B10,zenklub!$I$49:$I$106) -> 23.9 | AQ10: =AO10-AP10 -> 66.666667 | AR10: =SUMIF([3]bradesco!$C:$C,B10,[3]bradesco!$M:$M) -> #VALUE! | AS10: =SUMIF([3]bradesco!$C:$C,B10,[3]bradesco!$V:$V) -> #VALUE! | AT10: =IFERROR(SUMIF([3]bradesco!$C:$C,B10,[3]bradesco!$Y:$Y),0) -> 0 | AU10: =SUMIF([4]bradesco!$C:$C,B10,[4]bradesco!$M:$M) -> #VALUE! | AV10: =SUMIF([4]bradesco!$C:$C,B10,[4]bradesco!$V:$V) -> #VALUE! | AW10: =AU10-AV10 -> #VALUE! | AX10: =IFERROR(VLOOKUP(B10,#REF!,3,0),0) -> 0 | AY10: =IFERROR(VLOOKUP(B10,#REF!,3,0),0) -> 0 | AZ10: =IFERROR(VLOOKUP(B10,#REF!,3,0),0) -> 0 | BA10: 0 | BB10: =IFERROR(VLOOKUP(B10,#REF!,3,0),0) -> 0 | BC10: =IF(E10>=0,IF(AND(E10>tabelas!$C$11,E10<=tabelas!$C$12),BB10*tabelas!$E$11,IF(AND(E10>=tabelas!$C$12,E10<=tabelas!$C$13),BB10*tabelas!$E$12,IF(AND(E10>=tabelas!$C$13,E10<=tabelas!$C$14),BB10*tabelas!$E$13,IF(AND(E10>0,E10>tabelas!$C$14),BB10*tabelas!$E$14,0))))) -> 0 | BD10: =BB10-BC10 -> 0 | BE10: =SUMIF(open_english!A:A,total!B10,open_english!C:C) -> 138.88889 | BF10: =SUMIF(open_english!A:A,total!B10,open_english!D:D) -> 96.56 | BG10: =SUMIF(open_english!A:A,total!B10,open_english!E:E) -> 42.328889 | BH10: =IFERROR(VLOOKUP(B10,gympass!$A$2:$F$527,6,0),"-") -> 166.66667 | BI10: =IFERROR(VLOOKUP(B10,#REF!,4,0),"-") -> - | BJ10: =IFERROR(VLOOKUP(B10,#REF!,3,0),0) -> 0 | BK10: =IF(E10>=0,IF(AND(E10>tabelas!$C$11,E10<=tabelas!$C$12),BJ10*tabelas!$E$11,IF(AND(E10>=tabelas!$C$12,E10<=tabelas!$C$13),BJ10*tabelas!$E$12,IF(AND(E10>=tabelas!$C$13,E10<=tabelas!$C$14),BJ10*tabelas!$E$13,IF(AND(E10>0,E10>tabelas!$C$14),BJ10*tabelas!$E$14,0))))) -> 0 | BL10: =BJ10-BK10 -> 0 | BM10: =IFERROR(INDEX(dif_sistel!L:L,MATCH(total!B10,dif_sistel!D:D,0)),0)+IFERROR(INDEX(dif_sistel!N:N,MATCH(total!B10,dif_sistel!D:D,0)),0) -> 0 | BN10: =IFERROR(VLOOKUP(B10,dif_sistel!$D$3:$X$257,21,0),0) -> 0 | BO10: =IFERROR(SUMIF(#REF!,total!B10,#REF!),"0") -> 0 | BP10: =IFERROR(SUMIF(#REF!,total!B10,#REF!),"0") -> 0
B11: 8 | C11: =VLOOKUP(B11,salario!$A$3:$C$195,2,0) -> ATIVO | D11: =VLOOKUP(B11,salario!$A$3:$C$195,3,0) -> Colaborador 8 | E11: =IFERROR(VLOOKUP(B11,salario!$A$3:$K$854,11,0), "0") -> 5245.5 | F11: =SUMIF([2]unimed!$AL:$AL,B11,[2]unimed!$AJ:$AJ) -> #VALUE! | G11: =SUMIF([2]unimed!$AL:$AL,B11,[2]unimed!$AQ:$AQ) -> #VALUE! | H11: =SUMIF([2]unimed!$AL:$AL,B11,[2]unimed!$AP:$AP) -> #VALUE! | I11: =IFERROR(VLOOKUP(B11,uniodonto!$B$3:$F$339,5,0),0) -> 168.76 | J11: =IF(E11>=0,IF(AND(E11>tabelas!$C$4,E11<=tabelas!$C$5),I11*tabelas!$E$4,IF(AND(E11>=tabelas!$C$5,E11<=tabelas!$C$6),I11*tabelas!$E$5,IF(AND(E11>=tabelas!$C$6,E11<=tabelas!$C$7),I11*tabelas!$E$6,IF(AND(E11>0,E11>tabelas!$C$7),I11*tabelas!$E$7,0))))) -> 25.314 | K11: =I11-J11 -> 143.446 | L11: =SUMIF(caju!$A$4:$A$562,total!B11,caju!$C$4:$C$2900) -> 500 | M11: =IF(E11>=0,IF(AND(E11>tabelas!$C$11,E11<=tabelas!$C$12),L11*tabelas!$E$11,IF(AND(E11>=tabelas!$C$12,E11<=tabelas!$C$13),L11*tabelas!$E$12,IF(AND(E11>=tabelas!$C$13,E11<=tabelas!$C$14),L11*tabelas!$E$13,IF(AND(E11>0,E11>tabelas!$C$14),L11*tabelas!$E$14,0))))) -> 30 | N11: =L11-M11 -> 470 | O11: =IFERROR(VLOOKUP(B11,segurodevida!$B$4:$E$588,4,0),0) -> 16.759373 | P11: =O11/2 -> 8.3796863 | Q11: =O11-P11 -> 8.3796863 | V11: =IFERROR(VLOOKUP(B11,#REF!,3,0),0) -> 0 | W11: =SUMIF(#REF!,total!B11,#REF!) -> #REF! | X11: =IFERROR(VLOOKUP(B11,#REF!,4,0),0) -> 0 | Y11: =IFERROR(VLOOKUP(B11,#REF!,5,0),0) -> 0 | Z11: =IFERROR(X11-Y11,0) -> 0 | AA11: =IFERROR(VLOOKUP(B11,#REF!,3,0),0) -> 0 | AB11: =IFERROR(VLOOKUP(B11,#REF!,3,0),0) -> 0 | AC11: =IFERROR(VLOOKUP(B11,#REF!,5,0),0) -> 0 | AD11: 275 | AE11: =IFERROR(VLOOKUP(B11,#REF!,3,0),0) -> 0 | AF11: =IFERROR(VLOOKUP(B11,#REF!,3,0),0) -> 0 | AG11: =IFERROR(VLOOKUP(B11,#REF!,3,0),0) -> 0 | AK11: =IFERROR(VLOOKUP(B11,#REF!,3,0),0) -> 0 | AL11: =IFERROR(VLOOKUP(B11,ingles!$A$2:$C$673,3,0),"-") -> 165 | AM11: =ROUNDUP(IFERROR(AL11*39.39%,"0"),1) -> 65 | AN11: =IFERROR(AL11-AM11,"-") -> 100 | AO11: =SUMIFS(zenklub!I:I,zenklub!A:A,total!B11) -> 90.566667 | AP11: =SUMIF(zenklub!$A$49:$A$106,total!B11,zenklub!$I$49:$I$106) -> 23.9 | AQ11: =AO11-AP11 -> 66.666667 | AR11: =SUMIF([3]bradesco!$C:$C,B11,[3]bradesco!$M:$M) -> #VALUE! | AS11: =SUMIF([3]bradesco!$C:$C,B11,[3]bradesco!$V:$V) -> #VALUE! | AT11: =IFERROR(SUMIF([3]bradesco!$C:$C,B11,[3]bradesco!$Y:$Y),0) -> 0 | AU11: =SUMIF([4]bradesco!$C:$C,B11,[4]bradesco!$M:$M) -> #VALUE! | AV11: =SUMIF([4]bradesco!$C:$C,B11,[4]bradesco!$V:$V) -> #VALUE! | AW11: =AU11-AV11 -> #VALUE! | AX11: =IFERROR(VLOOKUP(B11,#REF!,3,0),0) -> 0 | AY11: =IFERROR(VLOOKUP(B11,#REF!,3,0),0) -> 0 | AZ11: =IFERROR(VLOOKUP(B11,#REF!,3,0),0) -> 0 | BA11: 0 | BB11: =IFERROR(VLOOKUP(B11,#REF!,3,0),0) -> 0 | BC11: =IF(E11>=0,IF(AND(E11>tabelas!$C$11,E11<=tabelas!$C$12),BB11*tabelas!$E$11,IF(AND(E11>=tabelas!$C$12,E11<=tabelas!$C$13),BB11*tabelas!$E$12,IF(AND(E11>=tabelas!$C$13,E11<=tabelas!$C$14),BB11*tabelas!$E$13,IF(AND(E11>0,E11>tabelas!$C$14),BB11*tabelas!$E$14,0))))) -> 0 | BD11: =BB11-BC11 -> 0 | BE11: =SUMIF(open_english!A:A,total!B11,open_english!C:C) -> 138.88889 | BF11: =SUMIF(open_english!A:A,total!B11,open_english!D:D) -> 96.56 | BG11: =SUMIF(open_english!A:A,total!B11,open_english!E:E) -> 42.328889 | BH11: =IFERROR(VLOOKUP(B11,gympass!$A$2:$F$527,6,0),"-") -> 166.66667 | BI11: =IFERROR(VLOOKUP(B11,#REF!,4,0),"-") -> - | BJ11: =IFERROR(VLOOKUP(B11,#REF!,3,0),0) -> 0 | BK11: =IF(E11>=0,IF(AND(E11>tabelas!$C$11,E11<=tabelas!$C$12),BJ11*tabelas!$E$11,IF(AND(E11>=tabelas!$C$12,E11<=tabelas!$C$13),BJ11*tabelas!$E$12,IF(AND(E11>=tabelas!$C$13,E11<=tabelas!$C$14),BJ11*tabelas!$E$13,IF(AND(E11>0,E11>tabelas!$C$14),BJ11*tabelas!$E$14,0))))) -> 0 | BL11: =BJ11-BK11 -> 0 | BM11: =IFERROR(INDEX(dif_sistel!L:L,MATCH(total!B11,dif_sistel!D:D,0)),0)+IFERROR(INDEX(dif_sistel!N:N,MATCH(total!B11,dif_sistel!D:D,0)),0) -> 0 | BN11: =IFERROR(VLOOKUP(B11,dif_sistel!$D$3:$X$257,21,0),0) -> 0 | BO11: =IFERROR(SUMIF(#REF!,total!B11,#REF!),"0") -> 0 | BP11: =IFERROR(SUMIF(#REF!,total!B11,#REF!),"0") -> 0
B12: 9 | C12: =VLOOKUP(B12,salario!$A$3:$C$195,2,0) -> ATIVO | D12: =VLOOKUP(B12,salario!$A$3:$C$195,3,0) -> Colaborador 9 | E12: =IFERROR(VLOOKUP(B12,salario!$A$3:$K$854,11,0), "0") -> 4229.32 | F12: =SUMIF([2]unimed!$AL:$AL,B12,[2]unimed!$AJ:$AJ) -> #VALUE! | G12: =SUMIF([2]unimed!$AL:$AL,B12,[2]unimed!$AQ:$AQ) -> #VALUE! | H12: =SUMIF([2]unimed!$AL:$AL,B12,[2]unimed!$AP:$AP) -> #VALUE! | I12: =IFERROR(VLOOKUP(B12,uniodonto!$B$3:$F$339,5,0),0) -> 126.57 | J12: =IF(E12>=0,IF(AND(E12>tabelas!$C$4,E12<=tabelas!$C$5),I12*tabelas!$E$4,IF(AND(E12>=tabelas!$C$5,E12<=tabelas!$C$6),I12*tabelas!$E$5,IF(AND(E12>=tabelas!$C$6,E12<=tabelas!$C$7),I12*tabelas!$E$6,IF(AND(E12>0,E12>tabelas!$C$7),I12*tabelas!$E$7,0))))) -> 18.9855 | K12: =I12-J12 -> 107.5845 | L12: =SUMIF(caju!$A$4:$A$562,total!B12,caju!$C$4:$C$2900) -> 500 | M12: =IF(E12>=0,IF(AND(E12>tabelas!$C$11,E12<=tabelas!$C$12),L12*tabelas!$E$11,IF(AND(E12>=tabelas!$C$12,E12<=tabelas!$C$13),L12*tabelas!$E$12,IF(AND(E12>=tabelas!$C$13,E12<=tabelas!$C$14),L12*tabelas!$E$13,IF(AND(E12>0,E12>tabelas!$C$14),L12*tabelas!$E$14,0))))) -> 30 | N12: =L12-M12 -> 470 | O12: =IFERROR(VLOOKUP(B12,segurodevida!$B$4:$E$588,4,0),0) -> 13.512677 | P12: =O12/2 -> 6.7563387 | Q12: =O12-P12 -> 6.7563387 | V12: =IFERROR(VLOOKUP(B12,#REF!,3,0),0) -> 0 | W12: =SUMIF(#REF!,total!B12,#REF!) -> #REF! | X12: =IFERROR(VLOOKUP(B12,#REF!,4,0),0) -> 0 | Y12: =IFERROR(VLOOKUP(B12,#REF!,5,0),0) -> 0 | Z12: =IFERROR(X12-Y12,0) -> 0 | AA12: =IFERROR(VLOOKUP(B12,#REF!,3,0),0) -> 0 | AB12: =IFERROR(VLOOKUP(B12,#REF!,3,0),0) -> 0 | AC12: =IFERROR(VLOOKUP(B12,#REF!,5,0),0) -> 0 | AD12: 275 | AE12: =IFERROR(VLOOKUP(B12,#REF!,3,0),0) -> 0 | AF12: =IFERROR(VLOOKUP(B12,#REF!,3,0),0) -> 0 | AG12: =IFERROR(VLOOKUP(B12,#REF!,3,0),0) -> 0 | AK12: =IFERROR(VLOOKUP(B12,#REF!,3,0),0) -> 0 | AL12: =IFERROR(VLOOKUP(B12,ingles!$A$2:$C$673,3,0),"-") -> - | AM12: =ROUNDUP(IFERROR(AL12*39.39%,"0"),1) -> 0 | AN12: =IFERROR(AL12-AM12,"-") -> - | AO12: =SUMIFS(zenklub!I:I,zenklub!A:A,total!B12) -> 90.566667 | AP12: =SUMIF(zenklub!$A$49:$A$106,total!B12,zenklub!$I$49:$I$106) -> 23.9 | AQ12: =AO12-AP12 -> 66.666667 | AR12: =SUMIF([3]bradesco!$C:$C,B12,[3]bradesco!$M:$M) -> #VALUE! | AS12: =SUMIF([3]bradesco!$C:$C,B12,[3]bradesco!$V:$V) -> #VALUE! | AT12: =IFERROR(SUMIF([3]bradesco!$C:$C,B12,[3]bradesco!$Y:$Y),0) -> 0 | AU12: =SUMIF([4]bradesco!$C:$C,B12,[4]bradesco!$M:$M) -> #VALUE! | AV12: =SUMIF([4]bradesco!$C:$C,B12,[4]bradesco!$V:$V) -> #VALUE! | AW12: =AU12-AV12 -> #VALUE! | AX12: =IFERROR(VLOOKUP(B12,#REF!,3,0),0) -> 0 | AY12: =IFERROR(VLOOKUP(B12,#REF!,3,0),0) -> 0 | AZ12: =IFERROR(VLOOKUP(B12,#REF!,3,0),0) -> 0 | BA12: 0 | BB12: =IFERROR(VLOOKUP(B12,#REF!,3,0),0) -> 0 | BC12: =IF(E12>=0,IF(AND(E12>tabelas!$C$11,E12<=tabelas!$C$12),BB12*tabelas!$E$11,IF(AND(E12>=tabelas!$C$12,E12<=tabelas!$C$13),BB12*tabelas!$E$12,IF(AND(E12>=tabelas!$C$13,E12<=tabelas!$C$14),BB12*tabelas!$E$13,IF(AND(E12>0,E12>tabelas!$C$14),BB12*tabelas!$E$14,0))))) -> 0 | BD12: =BB12-BC12 -> 0 | BE12: =SUMIF(open_english!A:A,total!B12,open_english!C:C) -> 138.88889 | BF12: =SUMIF(open_english!A:A,total!B12,open_english!D:D) -> 96.56 | BG12: =SUMIF(open_english!A:A,total!B12,open_english!E:E) -> 42.328889 | BH12: =IFERROR(VLOOKUP(B12,gympass!$A$2:$F$527,6,0),"-") -> 166.66667 | BI12: =IFERROR(VLOOKUP(B12,#REF!,4,0),"-") -> - | BJ12: =IFERROR(VLOOKUP(B12,#REF!,3,0),0) -> 0 | BK12: =IF(E12>=0,IF(AND(E12>tabelas!$C$11,E12<=tabelas!$C$12),BJ12*tabelas!$E$11,IF(AND(E12>=tabelas!$C$12,E12<=tabelas!$C$13),BJ12*tabelas!$E$12,IF(AND(E12>=tabelas!$C$13,E12<=tabelas!$C$14),BJ12*tabelas!$E$13,IF(AND(E12>0,E12>tabelas!$C$14),BJ12*tabelas!$E$14,0))))) -> 0 | BL12: =BJ12-BK12 -> 0 | BM12: =IFERROR(INDEX(dif_sistel!L:L,MATCH(total!B12,dif_sistel!D:D,0)),0)+IFERROR(INDEX(dif_sistel!N:N,MATCH(total!B12,dif_sistel!D:D,0)),0) -> 0 | BN12: =IFERROR(VLOOKUP(B12,dif_sistel!$D$3:$X$257,21,0),0) -> 0 | BO12: =IFERROR(SUMIF(#REF!,total!B12,#REF!),"0") -> 0 | BP12: =IFERROR(SUMIF(#REF!,total!B12,#REF!),"0") -> 0
B13: 10 | C13: =VLOOKUP(B13,salario!$A$3:$C$195,2,0) -> ATIVO | D13: =VLOOKUP(B13,salario!$A$3:$C$195,3,0) -> Colaborador 10 | E13: =IFERROR(VLOOKUP(B13,salario!$A$3:$K$854,11,0), "0") -> 2404.84 | F13: =SUMIF([2]unimed!$AL:$AL,B13,[2]unimed!$AJ:$AJ) -> #VALUE! | G13: =SUMIF([2]unimed!$AL:$AL,B13,[2]unimed!$AQ:$AQ) -> #VALUE! | H13: =SUMIF([2]unimed!$AL:$AL,B13,[2]unimed!$AP:$AP) -> #VALUE! | I13: =IFERROR(VLOOKUP(B13,uniodonto!$B$3:$F$339,5,0),0) -> 126.57 | J13: =IF(E13>=0,IF(AND(E13>tabelas!$C$4,E13<=tabelas!$C$5),I13*tabelas!$E$4,IF(AND(E13>=tabelas!$C$5,E13<=tabelas!$C$6),I13*tabelas!$E$5,IF(AND(E13>=tabelas!$C$6,E13<=tabelas!$C$7),I13*tabelas!$E$6,IF(AND(E13>0,E13>tabelas!$C$7),I13*tabelas!$E$7,0))))) -> 8.8599 | K13: =I13-J13 -> 117.7101 | L13: =SUMIF(caju!$A$4:$A$562,total!B13,caju!$C$4:$C$2900) -> 500 | M13: =IF(E13>=0,IF(AND(E13>tabelas!$C$11,E13<=tabelas!$C$12),L13*tabelas!$E$11,IF(AND(E13>=tabelas!$C$12,E13<=tabelas!$C$13),L13*tabelas!$E$12,IF(AND(E13>=tabelas!$C$13,E13<=tabelas!$C$14),L13*tabelas!$E$13,IF(AND(E13>0,E13>tabelas!$C$14),L13*tabelas!$E$14,0))))) -> 10 | N13: =L13-M13 -> 490 | O13: =IFERROR(VLOOKUP(B13,segurodevida!$B$4:$E$588,4,0),0) -> 7.6834638 | P13: =O13/2 -> 3.8417319 | Q13: =O13-P13 -> 3.8417319 | V13: =IFERROR(VLOOKUP(B13,#REF!,3,0),0) -> 0 | W13: =SUMIF(#REF!,total!B13,#REF!) -> #REF! | X13: =IFERROR(VLOOKUP(B13,#REF!,4,0),0) -> 0 | Y13: =IFERROR(VLOOKUP(B13,#REF!,5,0),0) -> 0 | Z13: =IFERROR(X13-Y13,0) -> 0 | AA13: =IFERROR(VLOOKUP(B13,#REF!,3,0),0) -> 0 | AB13: =IFERROR(VLOOKUP(B13,#REF!,3,0),0) -> 0 | AC13: =IFERROR(VLOOKUP(B13,#REF!,5,0),0) -> 0 | AD13: 275 | AE13: =IFERROR(VLOOKUP(B13,#REF!,3,0),0) -> 0 | AF13: =IFERROR(VLOOKUP(B13,#REF!,3,0),0) -> 0 | AG13: =IFERROR(VLOOKUP(B13,#REF!,3,0),0) -> 0 | AK13: =IFERROR(VLOOKUP(B13,#REF!,3,0),0) -> 0 | AL13: =IFERROR(VLOOKUP(B13,ingles!$A$2:$C$673,3,0),"-") -> - | AM13: =ROUNDUP(IFERROR(AL13*39.39%,"0"),1) -> 0 | AN13: =IFERROR(AL13-AM13,"-") -> - | AO13: =SUMIFS(zenklub!I:I,zenklub!A:A,total!B13) -> 90.566667 | AP13: =SUMIF(zenklub!$A$49:$A$106,total!B13,zenklub!$I$49:$I$106) -> 23.9 | AQ13: =AO13-AP13 -> 66.666667 | AR13: =SUMIF([3]bradesco!$C:$C,B13,[3]bradesco!$M:$M) -> #VALUE! | AS13: =SUMIF([3]bradesco!$C:$C,B13,[3]bradesco!$V:$V) -> #VALUE! | AT13: =IFERROR(SUMIF([3]bradesco!$C:$C,B13,[3]bradesco!$Y:$Y),0) -> 0 | AU13: =SUMIF([4]bradesco!$C:$C,B13,[4]bradesco!$M:$M) -> #VALUE! | AV13: =SUMIF([4]bradesco!$C:$C,B13,[4]bradesco!$V:$V) -> #VALUE! | AW13: =AU13-AV13 -> #VALUE! | AX13: =IFERROR(VLOOKUP(B13,#REF!,3,0),0) -> 0 | AY13: =IFERROR(VLOOKUP(B13,#REF!,3,0),0) -> 0 | AZ13: =IFERROR(VLOOKUP(B13,#REF!,3,0),0) -> 0 | BA13: 0 | BB13: =IFERROR(VLOOKUP(B13,#REF!,3,0),0) -> 0 | BC13: =IF(E13>=0,IF(AND(E13>tabelas!$C$11,E13<=tabelas!$C$12),BB13*tabelas!$E$11,IF(AND(E13>=tabelas!$C$12,E13<=tabelas!$C$13),BB13*tabelas!$E$12,IF(AND(E13>=tabelas!$C$13,E13<=tabelas!$C$14),BB13*tabelas!$E$13,IF(AND(E13>0,E13>tabelas!$C$14),BB13*tabelas!$E$14,0))))) -> 0 | BD13: =BB13-BC13 -> 0 | BE13: =SUMIF(open_english!A:A,total!B13,open_english!C:C) -> 138.88889 | BF13: =SUMIF(open_english!A:A,total!B13,open_english!D:D) -> 96.56 | BG13: =SUMIF(open_english!A:A,total!B13,open_english!E:E) -> 42.328889 | BH13: =IFERROR(VLOOKUP(B13,gympass!$A$2:$F$527,6,0),"-") -> 166.66667 | BI13: =IFERROR(VLOOKUP(B13,#REF!,4,0),"-") -> - | BJ13: =IFERROR(VLOOKUP(B13,#REF!,3,0),0) -> 0 | BK13: =IF(E13>=0,IF(AND(E13>tabelas!$C$11,E13<=tabelas!$C$12),BJ13*tabelas!$E$11,IF(AND(E13>=tabelas!$C$12,E13<=tabelas!$C$13),BJ13*tabelas!$E$12,IF(AND(E13>=tabelas!$C$13,E13<=tabelas!$C$14),BJ13*tabelas!$E$13,IF(AND(E13>0,E13>tabelas!$C$14),BJ13*tabelas!$E$14,0))))) -> 0 | BL13: =BJ13-BK13 -> 0 | BM13: =IFERROR(INDEX(dif_sistel!L:L,MATCH(total!B13,dif_sistel!D:D,0)),0)+IFERROR(INDEX(dif_sistel!N:N,MATCH(total!B13,dif_sistel!D:D,0)),0) -> 0 | BN13: =IFERROR(VLOOKUP(B13,dif_sistel!$D$3:$X$257,21,0),0) -> 0 | BO13: =IFERROR(SUMIF(#REF!,total!B13,#REF!),"0") -> 0 | BP13: =IFERROR(SUMIF(#REF!,total!B13,#REF!),"0") -> 0
B14: 11 | C14: =VLOOKUP(B14,salario!$A$3:$C$195,2,0) -> ATIVO | D14: =VLOOKUP(B14,salario!$A$3:$C$195,3,0) -> Colaborador 11 | E14: =IFERROR(VLOOKUP(B14,salario!$A$3:$K$854,11,0), "0") -> 2335.03 | F14: =SUMIF([2]unimed!$AL:$AL,B14,[2]unimed!$AJ:$AJ) -> #VALUE! | G14: =SUMIF([2]unimed!$AL:$AL,B14,[2]unimed!$AQ:$AQ) -> #VALUE! | H14: =SUMIF([2]unimed!$AL:$AL,B14,[2]unimed!$AP:$AP) -> #VALUE! | I14: =IFERROR(VLOOKUP(B14,uniodonto!$B$3:$F$339,5,0),0) -> 126.57 | J14: =IF(E14>=0,IF(AND(E14>tabelas!$C$4,E14<=tabelas!$C$5),I14*tabelas!$E$4,IF(AND(E14>=tabelas!$C$5,E14<=tabelas!$C$6),I14*tabelas!$E$5,IF(AND(E14>=tabelas!$C$6,E14<=tabelas!$C$7),I14*tabelas!$E$6,IF(AND(E14>0,E14>tabelas!$C$7),I14*tabelas!$E$7,0))))) -> 8.8599 | K14: =I14-J14 -> 117.7101 | L14: =SUMIF(caju!$A$4:$A$562,total!B14,caju!$C$4:$C$2900) -> 500 | M14: =IF(E14>=0,IF(AND(E14>tabelas!$C$11,E14<=tabelas!$C$12),L14*tabelas!$E$11,IF(AND(E14>=tabelas!$C$12,E14<=tabelas!$C$13),L14*tabelas!$E$12,IF(AND(E14>=tabelas!$C$13,E14<=tabelas!$C$14),L14*tabelas!$E$13,IF(AND(E14>0,E14>tabelas!$C$14),L14*tabelas!$E$14,0))))) -> 10 | N14: =L14-M14 -> 490 | O14: =IFERROR(VLOOKUP(B14,segurodevida!$B$4:$E$588,4,0),0) -> 7.4604209 | P14: =O14/2 -> 3.7302104 | Q14: =O14-P14 -> 3.7302104 | V14: =IFERROR(VLOOKUP(B14,#REF!,3,0),0) -> 0 | W14: =SUMIF(#REF!,total!B14,#REF!) -> #REF! | X14: =IFERROR(VLOOKUP(B14,#REF!,4,0),0) -> 0 | Y14: =IFERROR(VLOOKUP(B14,#REF!,5,0),0) -> 0 | Z14: =IFERROR(X14-Y14,0) -> 0 | AA14: =IFERROR(VLOOKUP(B14,#REF!,3,0),0) -> 0 | AB14: =IFERROR(VLOOKUP(B14,#REF!,3,0),0) -> 0 | AC14: =IFERROR(VLOOKUP(B14,#REF!,5,0),0) -> 0 | AD14: 275 | AE14: =IFERROR(VLOOKUP(B14,#REF!,3,0),0) -> 0 | AF14: =IFERROR(VLOOKUP(B14,#REF!,3,0),0) -> 0 | AG14: =IFERROR(VLOOKUP(B14,#REF!,3,0),0) -> 0 | AK14: =IFERROR(VLOOKUP(B14,#REF!,3,0),0) -> 0 | AL14: =IFERROR(VLOOKUP(B14,ingles!$A$2:$C$673,3,0),"-") -> - | AM14: =ROUNDUP(IFERROR(AL14*39.39%,"0"),1) -> 0 | AN14: =IFERROR(AL14-AM14,"-") -> - | AO14: =SUMIFS(zenklub!I:I,zenklub!A:A,total!B14) -> 90.566667 | AP14: =SUMIF(zenklub!$A$49:$A$106,total!B14,zenklub!$I$49:$I$106) -> 23.9 | AQ14: =AO14-AP14 -> 66.666667 | AR14: =SUMIF([3]bradesco!$C:$C,B14,[3]bradesco!$M:$M) -> #VALUE! | AS14: =SUMIF([3]bradesco!$C:$C,B14,[3]bradesco!$V:$V) -> #VALUE! | AT14: =IFERROR(SUMIF([3]bradesco!$C:$C,B14,[3]bradesco!$Y:$Y),0) -> 0 | AU14: =SUMIF([4]bradesco!$C:$C,B14,[4]bradesco!$M:$M) -> #VALUE! | AV14: =SUMIF([4]bradesco!$C:$C,B14,[4]bradesco!$V:$V) -> #VALUE! | AW14: =AU14-AV14 -> #VALUE! | AX14: =IFERROR(VLOOKUP(B14,#REF!,3,0),0) -> 0 | AY14: =IFERROR(VLOOKUP(B14,#REF!,3,0),0) -> 0 | AZ14: =IFERROR(VLOOKUP(B14,#REF!,3,0),0) -> 0 | BA14: 0 | BB14: =IFERROR(VLOOKUP(B14,#REF!,3,0),0) -> 0 | BC14: =IF(E14>=0,IF(AND(E14>tabelas!$C$11,E14<=tabelas!$C$12),BB14*tabelas!$E$11,IF(AND(E14>=tabelas!$C$12,E14<=tabelas!$C$13),BB14*tabelas!$E$12,IF(AND(E14>=tabelas!$C$13,E14<=tabelas!$C$14),BB14*tabelas!$E$13,IF(AND(E14>0,E14>tabelas!$C$14),BB14*tabelas!$E$14,0))))) -> 0 | BD14: =BB14-BC14 -> 0 | BE14: =SUMIF(open_english!A:A,total!B14,open_english!C:C) -> 138.88889 | BF14: =SUMIF(open_english!A:A,total!B14,open_english!D:D) -> 96.56 | BG14: =SUMIF(open_english!A:A,total!B14,open_english!E:E) -> 42.328889 | BH14: =IFERROR(VLOOKUP(B14,gympass!$A$2:$F$527,6,0),"-") -> 166.66667 | BI14: =IFERROR(VLOOKUP(B14,#REF!,4,0),"-") -> - | BJ14: =IFERROR(VLOOKUP(B14,#REF!,3,0),0) -> 0 | BK14: =IF(E14>=0,IF(AND(E14>tabelas!$C$11,E14<=tabelas!$C$12),BJ14*tabelas!$E$11,IF(AND(E14>=tabelas!$C$12,E14<=tabelas!$C$13),BJ14*tabelas!$E$12,IF(AND(E14>=tabelas!$C$13,E14<=tabelas!$C$14),BJ14*tabelas!$E$13,IF(AND(E14>0,E14>tabelas!$C$14),BJ14*tabelas!$E$14,0))))) -> 0 | BL14: =BJ14-BK14 -> 0 | BM14: =IFERROR(INDEX(dif_sistel!L:L,MATCH(total!B14,dif_sistel!D:D,0)),0)+IFERROR(INDEX(dif_sistel!N:N,MATCH(total!B14,dif_sistel!D:D,0)),0) -> 0 | BN14: =IFERROR(VLOOKUP(B14,dif_sistel!$D$3:$X$257,21,0),0) -> 0 | BO14: =IFERROR(SUMIF(#REF!,total!B14,#REF!),"0") -> 0 | BP14: =IFERROR(SUMIF(#REF!,total!B14,#REF!),"0") -> 0
B15: 12 | C15: =VLOOKUP(B15,salario!$A$3:$C$195,2,0) -> ATIVO | D15: =VLOOKUP(B15,salario!$A$3:$C$195,3,0) -> Colaborador 12 | E15: =IFERROR(VLOOKUP(B15,salario!$A$3:$K$854,11,0), "0") -> 3290.79 | F15: =SUMIF([2]unimed!$AL:$AL,B15,[2]unimed!$AJ:$AJ) -> #VALUE! | G15: =SUMIF([2]unimed!$AL:$AL,B15,[2]unimed!$AQ:$AQ) -> #VALUE! | H15: =SUMIF([2]unimed!$AL:$AL,B15,[2]unimed!$AP:$AP) -> #VALUE! | I15: =IFERROR(VLOOKUP(B15,uniodonto!$B$3:$F$339,5,0),0) -> 42.19 | J15: =IF(E15>=0,IF(AND(E15>tabelas!$C$4,E15<=tabelas!$C$5),I15*tabelas!$E$4,IF(AND(E15>=tabelas!$C$5,E15<=tabelas!$C$6),I15*tabelas!$E$5,IF(AND(E15>=tabelas!$C$6,E15<=tabelas!$C$7),I15*tabelas!$E$6,IF(AND(E15>0,E15>tabelas!$C$7),I15*tabelas!$E$7,0))))) -> 2.9533 | K15: =I15-J15 -> 39.2367 | L15: =SUMIF(caju!$A$4:$A$562,total!B15,caju!$C$4:$C$2900) -> 500 | M15: =IF(E15>=0,IF(AND(E15>tabelas!$C$11,E15<=tabelas!$C$12),L15*tabelas!$E$11,IF(AND(E15>=tabelas!$C$12,E15<=tabelas!$C$13),L15*tabelas!$E$12,IF(AND(E15>=tabelas!$C$13,E15<=tabelas!$C$14),L15*tabelas!$E$13,IF(AND(E15>0,E15>tabelas!$C$14),L15*tabelas!$E$14,0))))) -> 10 | N15: =L15-M15 -> 490 | O15: =IFERROR(VLOOKUP(B15,segurodevida!$B$4:$E$588,4,0),0) -> 10.514074 | P15: =O15/2 -> 5.257037 | Q15: =O15-P15 -> 5.257037 | V15: =IFERROR(VLOOKUP(B15,#REF!,3,0),0) -> 0 | W15: =SUMIF(#REF!,total!B15,#REF!) -> #REF! | X15: =IFERROR(VLOOKUP(B15,#REF!,4,0),0) -> 0 | Y15: =IFERROR(VLOOKUP(B15,#REF!,5,0),0) -> 0 | Z15: =IFERROR(X15-Y15,0) -> 0 | AA15: =IFERROR(VLOOKUP(B15,#REF!,3,0),0) -> 0 | AB15: =IFERROR(VLOOKUP(B15,#REF!,3,0),0) -> 0 | AC15: =IFERROR(VLOOKUP(B15,#REF!,5,0),0) -> 0 | AD15: 275 | AE15: =IFERROR(VLOOKUP(B15,#REF!,3,0),0) -> 0 | AF15: =IFERROR(VLOOKUP(B15,#REF!,3,0),0) -> 0 | AG15: =IFERROR(VLOOKUP(B15,#REF!,3,0),0) -> 0 | AK15: =IFERROR(VLOOKUP(B15,#REF!,3,0),0) -> 0 | AL15: =IFERROR(VLOOKUP(B15,ingles!$A$2:$C$673,3,0),"-") -> - | AM15: =ROUNDUP(IFERROR(AL15*39.39%,"0"),1) -> 0 | AN15: =IFERROR(AL15-AM15,"-") -> - | AO15: =SUMIFS(zenklub!I:I,zenklub!A:A,total!B15) -> 90.566667 | AP15: =SUMIF(zenklub!$A$49:$A$106,total!B15,zenklub!$I$49:$I$106) -> 23.9 | AQ15: =AO15-AP15 -> 66.666667 | AR15: =SUMIF([3]bradesco!$C:$C,B15,[3]bradesco!$M:$M) -> #VALUE! | AS15: =SUMIF([3]bradesco!$C:$C,B15,[3]bradesco!$V:$V) -> #VALUE! | AT15: =IFERROR(SUMIF([3]bradesco!$C:$C,B15,[3]bradesco!$Y:$Y),0) -> 0 | AU15: =SUMIF([4]bradesco!$C:$C,B15,[4]bradesco!$M:$M) -> #VALUE! | AV15: =SUMIF([4]bradesco!$C:$C,B15,[4]bradesco!$V:$V) -> #VALUE! | AW15: =AU15-AV15 -> #VALUE! | AX15: =IFERROR(VLOOKUP(B15,#REF!,3,0),0) -> 0 | AY15: =IFERROR(VLOOKUP(B15,#REF!,3,0),0) -> 0 | AZ15: =IFERROR(VLOOKUP(B15,#REF!,3,0),0) -> 0 | BA15: 0 | BB15: =IFERROR(VLOOKUP(B15,#REF!,3,0),0) -> 0 | BC15: =IF(E15>=0,IF(AND(E15>tabelas!$C$11,E15<=tabelas!$C$12),BB15*tabelas!$E$11,IF(AND(E15>=tabelas!$C$12,E15<=tabelas!$C$13),BB15*tabelas!$E$12,IF(AND(E15>=tabelas!$C$13,E15<=tabelas!$C$14),BB15*tabelas!$E$13,IF(AND(E15>0,E15>tabelas!$C$14),BB15*tabelas!$E$14,0))))) -> 0 | BD15: =BB15-BC15 -> 0 | BE15: =SUMIF(open_english!A:A,total!B15,open_english!C:C) -> 138.88889 | BF15: =SUMIF(open_english!A:A,total!B15,open_english!D:D) -> 96.56 | BG15: =SUMIF(open_english!A:A,total!B15,open_english!E:E) -> 42.328889 | BH15: =IFERROR(VLOOKUP(B15,gympass!$A$2:$F$527,6,0),"-") -> 166.66667 | BI15: =IFERROR(VLOOKUP(B15,#REF!,4,0),"-") -> - | BJ15: =IFERROR(VLOOKUP(B15,#REF!,3,0),0) -> 0 | BK15: =IF(E15>=0,IF(AND(E15>tabelas!$C$11,E15<=tabelas!$C$12),BJ15*tabelas!$E$11,IF(AND(E15>=tabelas!$C$12,E15<=tabelas!$C$13),BJ15*tabelas!$E$12,IF(AND(E15>=tabelas!$C$13,E15<=tabelas!$C$14),BJ15*tabelas!$E$13,IF(AND(E15>0,E15>tabelas!$C$14),BJ15*tabelas!$E$14,0))))) -> 0 | BL15: =BJ15-BK15 -> 0 | BM15: =IFERROR(INDEX(dif_sistel!L:L,MATCH(total!B15,dif_sistel!D:D,0)),0)+IFERROR(INDEX(dif_sistel!N:N,MATCH(total!B15,dif_sistel!D:D,0)),0) -> 0 | BN15: =IFERROR(VLOOKUP(B15,dif_sistel!$D$3:$X$257,21,0),0) -> 0 | BO15: =IFERROR(SUMIF(#REF!,total!B15,#REF!),"0") -> 0 | BP15: =IFERROR(SUMIF(#REF!,total!B15,#REF!),"0") -> 0
B16: 13 | C16: =VLOOKUP(B16,salario!$A$3:$C$195,2,0) -> ATIVO | D16: =VLOOKUP(B16,salario!$A$3:$C$195,3,0) -> Colaborador 13 | E16: =IFERROR(VLOOKUP(B16,salario!$A$3:$K$854,11,0), "0") -> 1102.16 | F16: =SUMIF([2]unimed!$AL:$AL,B16,[2]unimed!$AJ:$AJ) -> #VALUE! | G16: =SUMIF([2]unimed!$AL:$AL,B16,[2]unimed!$AQ:$AQ) -> #VALUE! | H16: =SUMIF([2]unimed!$AL:$AL,B16,[2]unimed!$AP:$AP) -> #VALUE! | I16: =IFERROR(VLOOKUP(B16,uniodonto!$B$3:$F$339,5,0),0) -> 210.95 | J16: =IF(E16>=0,IF(AND(E16>tabelas!$C$4,E16<=tabelas!$C$5),I16*tabelas!$E$4,IF(AND(E16>=tabelas!$C$5,E16<=tabelas!$C$6),I16*tabelas!$E$5,IF(AND(E16>=tabelas!$C$6,E16<=tabelas!$C$7),I16*tabelas!$E$6,IF(AND(E16>0,E16>tabelas!$C$7),I16*tabelas!$E$7,0))))) -> 14.7665 | K16: =I16-J16 -> 196.1835 | L16: =SUMIF(caju!$A$4:$A$562,total!B16,caju!$C$4:$C$2900) -> 500 | M16: =IF(E16>=0,IF(AND(E16>tabelas!$C$11,E16<=tabelas!$C$12),L16*tabelas!$E$11,IF(AND(E16>=tabelas!$C$12,E16<=tabelas!$C$13),L16*tabelas!$E$12,IF(AND(E16>=tabelas!$C$13,E16<=tabelas!$C$14),L16*tabelas!$E$13,IF(AND(E16>0,E16>tabelas!$C$14),L16*tabelas!$E$14,0))))) -> 10 | N16: =L16-M16 -> 490 | O16: =IFERROR(VLOOKUP(B16,segurodevida!$B$4:$E$588,4,0),0) -> 3.5214012 | P16: =O16/2 -> 1.7607006 | Q16: =O16-P16 -> 1.7607006 | V16: =IFERROR(VLOOKUP(B16,#REF!,3,0),0) -> 0 | W16: =SUMIF(#REF!,total!B16,#REF!) -> #REF! | X16: =IFERROR(VLOOKUP(B16,#REF!,4,0),0) -> 0 | Y16: =IFERROR(VLOOKUP(B16,#REF!,5,0),0) -> 0 | Z16: =IFERROR(X16-Y16,0) -> 0 | AA16: =IFERROR(VLOOKUP(B16,#REF!,3,0),0) -> 0 | AB16: =IFERROR(VLOOKUP(B16,#REF!,3,0),0) -> 0 | AC16: =IFERROR(VLOOKUP(B16,#REF!,5,0),0) -> 0 | AD16: 275 | AE16: =IFERROR(VLOOKUP(B16,#REF!,3,0),0) -> 0 | AF16: =IFERROR(VLOOKUP(B16,#REF!,3,0),0) -> 0 | AG16: =IFERROR(VLOOKUP(B16,#REF!,3,0),0) -> 0 | AK16: =IFERROR(VLOOKUP(B16,#REF!,3,0),0) -> 0 | AL16: =IFERROR(VLOOKUP(B16,ingles!$A$2:$C$673,3,0),"-") -> 165 | AM16: =ROUNDUP(IFERROR(AL16*39.39%,"0"),1) -> 65 | AN16: =IFERROR(AL16-AM16,"-") -> 100 | AO16: =SUMIFS(zenklub!I:I,zenklub!A:A,total!B16) -> 90.566667 | AP16: =SUMIF(zenklub!$A$49:$A$106,total!B16,zenklub!$I$49:$I$106) -> 23.9 | AQ16: =AO16-AP16 -> 66.666667 | AR16: =SUMIF([3]bradesco!$C:$C,B16,[3]bradesco!$M:$M) -> #VALUE! | AS16: =SUMIF([3]bradesco!$C:$C,B16,[3]bradesco!$V:$V) -> #VALUE! | AT16: =IFERROR(SUMIF([3]bradesco!$C:$C,B16,[3]bradesco!$Y:$Y),0) -> 0 | AU16: =SUMIF([4]bradesco!$C:$C,B16,[4]bradesco!$M:$M) -> #VALUE! | AV16: =SUMIF([4]bradesco!$C:$C,B16,[4]bradesco!$V:$V) -> #VALUE! | AW16: =AU16-AV16 -> #VALUE! | AX16: =IFERROR(VLOOKUP(B16,#REF!,3,0),0) -> 0 | AY16: =IFERROR(VLOOKUP(B16,#REF!,3,0),0) -> 0 | AZ16: =IFERROR(VLOOKUP(B16,#REF!,3,0),0) -> 0 | BA16: 0 | BB16: =IFERROR(VLOOKUP(B16,#REF!,3,0),0) -> 0 | BC16: =IF(E16>=0,IF(AND(E16>tabelas!$C$11,E16<=tabelas!$C$12),BB16*tabelas!$E$11,IF(AND(E16>=tabelas!$C$12,E16<=tabelas!$C$13),BB16*tabelas!$E$12,IF(AND(E16>=tabelas!$C$13,E16<=tabelas!$C$14),BB16*tabelas!$E$13,IF(AND(E16>0,E16>tabelas!$C$14),BB16*tabelas!$E$14,0))))) -> 0 | BD16: =BB16-BC16 -> 0 | BE16: =SUMIF(open_english!A:A,total!B16,open_english!C:C) -> 138.88889 | BF16: =SUMIF(open_english!A:A,total!B16,open_english!D:D) -> 96.56 | BG16: =SUMIF(open_english!A:A,total!B16,open_english!E:E) -> 42.328889 | BH16: =IFERROR(VLOOKUP(B16,gympass!$A$2:$F$527,6,0),"-") -> 166.66667 | BI16: =IFERROR(VLOOKUP(B16,#REF!,4,0),"-") -> - | BJ16: =IFERROR(VLOOKUP(B16,#REF!,3,0),0) -> 0 | BK16: =IF(E16>=0,IF(AND(E16>tabelas!$C$11,E16<=tabelas!$C$12),BJ16*tabelas!$E$11,IF(AND(E16>=tabelas!$C$12,E16<=tabelas!$C$13),BJ16*tabelas!$E$12,IF(AND(E16>=tabelas!$C$13,E16<=tabelas!$C$14),BJ16*tabelas!$E$13,IF(AND(E16>0,E16>tabelas!$C$14),BJ16*tabelas!$E$14,0))))) -> 0 | BL16: =BJ16-BK16 -> 0 | BM16: =IFERROR(INDEX(dif_sistel!L:L,MATCH(total!B16,dif_sistel!D:D,0)),0)+IFERROR(INDEX(dif_sistel!N:N,MATCH(total!B16,dif_sistel!D:D,0)),0)+dif_sistel!R9 -> 0 | BN16: =IFERROR(VLOOKUP(B16,dif_sistel!$D$3:$X$257,21,0),0) -> 0 | BO16: =IFERROR(SUMIF(#REF!,total!B16,#REF!),"0") -> 0 | BP16: =IFERROR(SUMIF(#REF!,total!B16,#REF!),"0") -> 0
B17: 14 | C17: =VLOOKUP(B17,salario!$A$3:$C$195,2,0) -> ATIVO | D17: =VLOOKUP(B17,salario!$A$3:$C$195,3,0) -> Colaborador 14 | E17: =IFERROR(VLOOKUP(B17,salario!$A$3:$K$854,11,0), "0") -> 5617.18 | F17: =SUMIF([2]unimed!$AL:$AL,B17,[2]unimed!$AJ:$AJ) -> #VALUE! | G17: =SUMIF([2]unimed!$AL:$AL,B17,[2]unimed!$AQ:$AQ) -> #VALUE! | H17: =SUMIF([2]unimed!$AL:$AL,B17,[2]unimed!$AP:$AP) -> #VALUE! | I17: =IFERROR(VLOOKUP(B17,uniodonto!$B$3:$F$339,5,0),0) -> 210.95 | J17: =IF(E17>=0,IF(AND(E17>tabelas!$C$4,E17<=tabelas!$C$5),I17*tabelas!$E$4,IF(AND(E17>=tabelas!$C$5,E17<=tabelas!$C$6),I17*tabelas!$E$5,IF(AND(E17>=tabelas!$C$6,E17<=tabelas!$C$7),I17*tabelas!$E$6,IF(AND(E17>0,E17>tabelas!$C$7),I17*tabelas!$E$7,0))))) -> 31.6425 | K17: =I17-J17 -> 179.3075 | L17: =SUMIF(caju!$A$4:$A$562,total!B17,caju!$C$4:$C$2900) -> 550 | M17: =IF(E17>=0,IF(AND(E17>tabelas!$C$11,E17<=tabelas!$C$12),L17*tabelas!$E$11,IF(AND(E17>=tabelas!$C$12,E17<=tabelas!$C$13),L17*tabelas!$E$12,IF(AND(E17>=tabelas!$C$13,E17<=tabelas!$C$14),L17*tabelas!$E$13,IF(AND(E17>0,E17>tabelas!$C$14),L17*tabelas!$E$14,0))))) -> 33 | N17: =L17-M17 -> 517 | O17: =IFERROR(VLOOKUP(B17,segurodevida!$B$4:$E$588,4,0),0) -> 17.94689 | P17: =O17/2 -> 8.9734451 | Q17: =O17-P17 -> 8.9734451 | V17: =IFERROR(VLOOKUP(B17,#REF!,3,0),0) -> 0 | W17: =SUMIF(#REF!,total!B17,#REF!) -> #REF! | X17: =IFERROR(VLOOKUP(B17,#REF!,4,0),0) -> 0 | Y17: =IFERROR(VLOOKUP(B17,#REF!,5,0),0) -> 0 | Z17: =IFERROR(X17-Y17,0) -> 0 | AA17: =IFERROR(VLOOKUP(B17,#REF!,3,0),0) -> 0 | AB17: =IFERROR(VLOOKUP(B17,#REF!,3,0),0) -> 0 | AC17: =IFERROR(VLOOKUP(B17,#REF!,5,0),0) -> 0 | AD17: 275 | AE17: =IFERROR(VLOOKUP(B17,#REF!,3,0),0) -> 0 | AF17: =IFERROR(VLOOKUP(B17,#REF!,3,0),0) -> 0 | AG17: =IFERROR(VLOOKUP(B17,#REF!,3,0),0) -> 0 | AK17: =IFERROR(VLOOKUP(B17,#REF!,3,0),0) -> 0 | AL17: =IFERROR(VLOOKUP(B17,ingles!$A$2:$C$673,3,0),"-") -> 165 | AM17: =ROUNDUP(IFERROR(AL17*39.39%,"0"),1) -> 65 | AN17: =IFERROR(AL17-AM17,"-") -> 100 | AO17: =SUMIFS(zenklub!I:I,zenklub!A:A,total!B17) -> 90.566667 | AP17: =SUMIF(zenklub!$A$49:$A$106,total!B17,zenklub!$I$49:$I$106) -> 23.9 | AQ17: =AO17-AP17 -> 66.666667 | AR17: =SUMIF([3]bradesco!$C:$C,B17,[3]bradesco!$M:$M) -> #VALUE! | AS17: =SUMIF([3]bradesco!$C:$C,B17,[3]bradesco!$V:$V) -> #VALUE! | AT17: =IFERROR(SUMIF([3]bradesco!$C:$C,B17,[3]bradesco!$Y:$Y),0) -> 0 | AU17: =SUMIF([4]bradesco!$C:$C,B17,[4]bradesco!$M:$M) -> #VALUE! | AV17: =SUMIF([4]bradesco!$C:$C,B17,[4]bradesco!$V:$V) -> #VALUE! | AW17: =AU17-AV17 -> #VALUE! | AX17: =IFERROR(VLOOKUP(B17,#REF!,3,0),0) -> 0 | AY17: =IFERROR(VLOOKUP(B17,#REF!,3,0),0) -> 0 | AZ17: =IFERROR(VLOOKUP(B17,#REF!,3,0),0) -> 0 | BA17: 0 | BB17: =IFERROR(VLOOKUP(B17,#REF!,3,0),0) -> 0 | BC17: =IF(E17>=0,IF(AND(E17>tabelas!$C$11,E17<=tabelas!$C$12),BB17*tabelas!$E$11,IF(AND(E17>=tabelas!$C$12,E17<=tabelas!$C$13),BB17*tabelas!$E$12,IF(AND(E17>=tabelas!$C$13,E17<=tabelas!$C$14),BB17*tabelas!$E$13,IF(AND(E17>0,E17>tabelas!$C$14),BB17*tabelas!$E$14,0))))) -> 0 | BD17: =BB17-BC17 -> 0 | BE17: =SUMIF(open_english!A:A,total!B17,open_english!C:C) -> 138.88889 | BF17: =SUMIF(open_english!A:A,total!B17,open_english!D:D) -> 96.56 | BG17: =SUMIF(open_english!A:A,total!B17,open_english!E:E) -> 42.328889 | BH17: =IFERROR(VLOOKUP(B17,gympass!$A$2:$F$527,6,0),"-") -> 166.66667 | BI17: =IFERROR(VLOOKUP(B17,#REF!,4,0),"-") -> - | BJ17: =IFERROR(VLOOKUP(B17,#REF!,3,0),0) -> 0 | BK17: =IF(E17>=0,IF(AND(E17>tabelas!$C$11,E17<=tabelas!$C$12),BJ17*tabelas!$E$11,IF(AND(E17>=tabelas!$C$12,E17<=tabelas!$C$13),BJ17*tabelas!$E$12,IF(AND(E17>=tabelas!$C$13,E17<=tabelas!$C$14),BJ17*tabelas!$E$13,IF(AND(E17>0,E17>tabelas!$C$14),BJ17*tabelas!$E$14,0))))) -> 0 | BL17: =BJ17-BK17 -> 0 | BM17: =IFERROR(INDEX(dif_sistel!L:L,MATCH(total!B17,dif_sistel!D:D,0)),0)+IFERROR(INDEX(dif_sistel!N:N,MATCH(total!B17,dif_sistel!D:D,0)),0) -> 0 | BN17: =IFERROR(VLOOKUP(B17,dif_sistel!$D$3:$X$257,21,0),0) -> 0 | BO17: =IFERROR(SUMIF(#REF!,total!B17,#REF!),"0") -> 0 | BP17: =IFERROR(SUMIF(#REF!,total!B17,#REF!),"0") -> 0
B18: 15 | C18: =VLOOKUP(B18,salario!$A$3:$C$195,2,0) -> ATIVO | D18: =VLOOKUP(B18,salario!$A$3:$C$195,3,0) -> Colaborador 15 | E18: =IFERROR(VLOOKUP(B18,salario!$A$3:$K$854,11,0), "0") -> 5591.86 | F18: =SUMIF([2]unimed!$AL:$AL,B18,[2]unimed!$AJ:$AJ) -> #VALUE! | G18: =SUMIF([2]unimed!$AL:$AL,B18,[2]unimed!$AQ:$AQ) -> #VALUE! | H18: =SUMIF([2]unimed!$AL:$AL,B18,[2]unimed!$AP:$AP) -> #VALUE! | I18: =IFERROR(VLOOKUP(B18,uniodonto!$B$3:$F$339,5,0),0) -> 42.19 | J18: =IF(E18>=0,IF(AND(E18>tabelas!$C$4,E18<=tabelas!$C$5),I18*tabelas!$E$4,IF(AND(E18>=tabelas!$C$5,E18<=tabelas!$C$6),I18*tabelas!$E$5,IF(AND(E18>=tabelas!$C$6,E18<=tabelas!$C$7),I18*tabelas!$E$6,IF(AND(E18>0,E18>tabelas!$C$7),I18*tabelas!$E$7,0))))) -> 6.3285 | K18: =I18-J18 -> 35.8615 | L18: =SUMIF(caju!$A$4:$A$562,total!B18,caju!$C$4:$C$2900) -> 500 | M18: =IF(E18>=0,IF(AND(E18>tabelas!$C$11,E18<=tabelas!$C$12),L18*tabelas!$E$11,IF(AND(E18>=tabelas!$C$12,E18<=tabelas!$C$13),L18*tabelas!$E$12,IF(AND(E18>=tabelas!$C$13,E18<=tabelas!$C$14),L18*tabelas!$E$13,IF(AND(E18>0,E18>tabelas!$C$14),L18*tabelas!$E$14,0))))) -> 30 | N18: =L18-M18 -> 470 | O18: =IFERROR(VLOOKUP(B18,segurodevida!$B$4:$E$588,4,0),0) -> 17.865993 | P18: =O18/2 -> 8.9329963 | Q18: =O18-P18 -> 8.9329963 | V18: =IFERROR(VLOOKUP(B18,#REF!,3,0),0) -> 0 | W18: =SUMIF(#REF!,total!B18,#REF!) -> #REF! | X18: =IFERROR(VLOOKUP(B18,#REF!,4,0),0) -> 0 | Y18: =IFERROR(VLOOKUP(B18,#REF!,5,0),0) -> 0 | Z18: =IFERROR(X18-Y18,0) -> 0 | AA18: =IFERROR(VLOOKUP(B18,#REF!,3,0),0) -> 0 | AB18: =IFERROR(VLOOKUP(B18,#REF!,3,0),0) -> 0 | AC18: =IFERROR(VLOOKUP(B18,#REF!,5,0),0) -> 0 | AD18: 275 | AE18: =IFERROR(VLOOKUP(B18,#REF!,3,0),0) -> 0 | AF18: =IFERROR(VLOOKUP(B18,#REF!,3,0),0) -> 0 | AG18: =IFERROR(VLOOKUP(B18,#REF!,3,0),0) -> 0 | AK18: =IFERROR(VLOOKUP(B18,#REF!,3,0),0) -> 0 | AL18: =IFERROR(VLOOKUP(B18,ingles!$A$2:$C$673,3,0),"-") -> 165 | AM18: =ROUNDUP(IFERROR(AL18*39.39%,"0"),1) -> 65 | AN18: =IFERROR(AL18-AM18,"-") -> 100 | AO18: =SUMIFS(zenklub!I:I,zenklub!A:A,total!B18) -> 90.566667 | AP18: =SUMIF(zenklub!$A$49:$A$106,total!B18,zenklub!$I$49:$I$106) -> 23.9 | AQ18: =AO18-AP18 -> 66.666667 | AR18: =SUMIF([3]bradesco!$C:$C,B18,[3]bradesco!$M:$M) -> #VALUE! | AS18: =SUMIF([3]bradesco!$C:$C,B18,[3]bradesco!$V:$V) -> #VALUE! | AT18: =IFERROR(SUMIF([3]bradesco!$C:$C,B18,[3]bradesco!$Y:$Y),0) -> 0 | AU18: =SUMIF([4]bradesco!$C:$C,B18,[4]bradesco!$M:$M) -> #VALUE! | AV18: =SUMIF([4]bradesco!$C:$C,B18,[4]bradesco!$V:$V) -> #VALUE! | AW18: =AU18-AV18 -> #VALUE! | AX18: =IFERROR(VLOOKUP(B18,#REF!,3,0),0) -> 0 | AY18: =IFERROR(VLOOKUP(B18,#REF!,3,0),0) -> 0 | AZ18: =IFERROR(VLOOKUP(B18,#REF!,3,0),0) -> 0 | BA18: 0 | BB18: =IFERROR(VLOOKUP(B18,#REF!,3,0),0) -> 0 | BC18: =IF(E18>=0,IF(AND(E18>tabelas!$C$11,E18<=tabelas!$C$12),BB18*tabelas!$E$11,IF(AND(E18>=tabelas!$C$12,E18<=tabelas!$C$13),BB18*tabelas!$E$12,IF(AND(E18>=tabelas!$C$13,E18<=tabelas!$C$14),BB18*tabelas!$E$13,IF(AND(E18>0,E18>tabelas!$C$14),BB18*tabelas!$E$14,0))))) -> 0 | BD18: =BB18-BC18 -> 0 | BE18: =SUMIF(open_english!A:A,total!B18,open_english!C:C) -> 138.88889 | BF18: =SUMIF(open_english!A:A,total!B18,open_english!D:D) -> 96.56 | BG18: =SUMIF(open_english!A:A,total!B18,open_english!E:E) -> 42.328889 | BH18: =IFERROR(VLOOKUP(B18,gympass!$A$2:$F$527,6,0),"-") -> 166.66667 | BI18: =IFERROR(VLOOKUP(B18,#REF!,4,0),"-") -> - | BJ18: =IFERROR(VLOOKUP(B18,#REF!,3,0),0) -> 0 | BK18: =IF(E18>=0,IF(AND(E18>tabelas!$C$11,E18<=tabelas!$C$12),BJ18*tabelas!$E$11,IF(AND(E18>=tabelas!$C$12,E18<=tabelas!$C$13),BJ18*tabelas!$E$12,IF(AND(E18>=tabelas!$C$13,E18<=tabelas!$C$14),BJ18*tabelas!$E$13,IF(AND(E18>0,E18>tabelas!$C$14),BJ18*tabelas!$E$14,0))))) -> 0 | BL18: =BJ18-BK18 -> 0 | BM18: =IFERROR(INDEX(dif_sistel!L:L,MATCH(total!B18,dif_sistel!D:D,0)),0)+IFERROR(INDEX(dif_sistel!N:N,MATCH(total!B18,dif_sistel!D:D,0)),0) -> 0 | BN18: =IFERROR(VLOOKUP(B18,dif_sistel!$D$3:$X$257,21,0),0) -> 0 | BO18: =IFERROR(SUMIF(#REF!,total!B18,#REF!),"0") -> 0 | BP18: =IFERROR(SUMIF(#REF!,total!B18,#REF!),"0") -> 0
B19: 16 | C19: =VLOOKUP(B19,salario!$A$3:$C$195,2,0) -> ATIVO | D19: =VLOOKUP(B19,salario!$A$3:$C$195,3,0) -> Colaborador 16 | E19: =IFERROR(VLOOKUP(B19,salario!$A$3:$K$854,11,0), "0") -> 7685.13 | F19: =SUMIF([2]unimed!$AL:$AL,B19,[2]unimed!$AJ:$AJ) -> #VALUE! | G19: =SUMIF([2]unimed!$AL:$AL,B19,[2]unimed!$AQ:$AQ) -> #VALUE! | H19: =SUMIF([2]unimed!$AL:$AL,B19,[2]unimed!$AP:$AP) -> #VALUE! | I19: =IFERROR(VLOOKUP(B19,uniodonto!$B$3:$F$339,5,0),0) -> 210.95 | J19: =IF(E19>=0,IF(AND(E19>tabelas!$C$4,E19<=tabelas!$C$5),I19*tabelas!$E$4,IF(AND(E19>=tabelas!$C$5,E19<=tabelas!$C$6),I19*tabelas!$E$5,IF(AND(E19>=tabelas!$C$6,E19<=tabelas!$C$7),I19*tabelas!$E$6,IF(AND(E19>0,E19>tabelas!$C$7),I19*tabelas!$E$7,0))))) -> 48.5185 | K19: =I19-J19 -> 162.4315 | L19: =SUMIF(caju!$A$4:$A$562,total!B19,caju!$C$4:$C$2900) -> 500 | M19: =IF(E19>=0,IF(AND(E19>tabelas!$C$11,E19<=tabelas!$C$12),L19*tabelas!$E$11,IF(AND(E19>=tabelas!$C$12,E19<=tabelas!$C$13),L19*tabelas!$E$12,IF(AND(E19>=tabelas!$C$13,E19<=tabelas!$C$14),L19*tabelas!$E$13,IF(AND(E19>0,E19>tabelas!$C$14),L19*tabelas!$E$14,0))))) -> 50 | N19: =L19-M19 -> 450 | O19: =IFERROR(VLOOKUP(B19,segurodevida!$B$4:$E$588,4,0),0) -> 24.55399 | P19: =O19/2 -> 12.276995 | Q19: =O19-P19 -> 12.276995 | V19: =IFERROR(VLOOKUP(B19,#REF!,3,0),0) -> 0 | W19: =SUMIF(#REF!,total!B19,#REF!) -> #REF! | X19: =IFERROR(VLOOKUP(B19,#REF!,4,0),0) -> 0 | Y19: =IFERROR(VLOOKUP(B19,#REF!,5,0),0) -> 0 | Z19: =IFERROR(X19-Y19,0) -> 0 | AA19: =IFERROR(VLOOKUP(B19,#REF!,3,0),0) -> 0 | AB19: =IFERROR(VLOOKUP(B19,#REF!,3,0),0) -> 0 | AC19: =IFERROR(VLOOKUP(B19,#REF!,5,0),0) -> 0 | AD19: 275 | AE19: =IFERROR(VLOOKUP(B19,#REF!,3,0),0) -> 0 | AF19: =IFERROR(VLOOKUP(B19,#REF!,3,0),0) -> 0 | AG19: =IFERROR(VLOOKUP(B19,#REF!,3,0),0) -> 0 | AK19: =IFERROR(VLOOKUP(B19,#REF!,3,0),0) -> 0 | AL19: =IFERROR(VLOOKUP(B19,ingles!$A$2:$C$673,3,0),"-") -> 165 | AM19: =ROUNDUP(IFERROR(AL19*39.39%,"0"),1) -> 65 | AN19: =IFERROR(AL19-AM19,"-") -> 100 | AO19: =SUMIFS(zenklub!I:I,zenklub!A:A,total!B19) -> 90.566667 | AP19: =SUMIF(zenklub!$A$49:$A$106,total!B19,zenklub!$I$49:$I$106) -> 23.9 | AQ19: =AO19-AP19 -> 66.666667 | AR19: =SUMIF([3]bradesco!$C:$C,B19,[3]bradesco!$M:$M) -> #VALUE! | AS19: =SUMIF([3]bradesco!$C:$C,B19,[3]bradesco!$V:$V) -> #VALUE! | AT19: =IFERROR(SUMIF([3]bradesco!$C:$C,B19,[3]bradesco!$Y:$Y),0) -> 0 | AU19: =SUMIF([4]bradesco!$C:$C,B19,[4]bradesco!$M:$M) -> #VALUE! | AV19: =SUMIF([4]bradesco!$C:$C,B19,[4]bradesco!$V:$V) -> #VALUE! | AW19: =AU19-AV19 -> #VALUE! | AX19: =IFERROR(VLOOKUP(B19,#REF!,3,0),0) -> 0 | AY19: =IFERROR(VLOOKUP(B19,#REF!,3,0),0) -> 0 | AZ19: =IFERROR(VLOOKUP(B19,#REF!,3,0),0) -> 0 | BA19: 0 | BB19: =IFERROR(VLOOKUP(B19,#REF!,3,0),0) -> 0 | BC19: =IF(E19>=0,IF(AND(E19>tabelas!$C$11,E19<=tabelas!$C$12),BB19*tabelas!$E$11,IF(AND(E19>=tabelas!$C$12,E19<=tabelas!$C$13),BB19*tabelas!$E$12,IF(AND(E19>=tabelas!$C$13,E19<=tabelas!$C$14),BB19*tabelas!$E$13,IF(AND(E19>0,E19>tabelas!$C$14),BB19*tabelas!$E$14,0))))) -> 0 | BD19: =BB19-BC19 -> 0 | BE19: =SUMIF(open_english!A:A,total!B19,open_english!C:C) -> 138.88889 | BF19: =SUMIF(open_english!A:A,total!B19,open_english!D:D) -> 96.56 | BG19: =SUMIF(open_english!A:A,total!B19,open_english!E:E) -> 42.328889 | BH19: =IFERROR(VLOOKUP(B19,gympass!$A$2:$F$527,6,0),"-") -> 166.66667 | BI19: =IFERROR(VLOOKUP(B19,#REF!,4,0),"-") -> - | BJ19: =IFERROR(VLOOKUP(B19,#REF!,3,0),0) -> 0 | BK19: =IF(E19>=0,IF(AND(E19>tabelas!$C$11,E19<=tabelas!$C$12),BJ19*tabelas!$E$11,IF(AND(E19>=tabelas!$C$12,E19<=tabelas!$C$13),BJ19*tabelas!$E$12,IF(AND(E19>=tabelas!$C$13,E19<=tabelas!$C$14),BJ19*tabelas!$E$13,IF(AND(E19>0,E19>tabelas!$C$14),BJ19*tabelas!$E$14,0))))) -> 0 | BL19: =BJ19-BK19 -> 0 | BM19: =IFERROR(INDEX(dif_sistel!L:L,MATCH(total!B19,dif_sistel!D:D,0)),0)+IFERROR(INDEX(dif_sistel!N:N,MATCH(total!B19,dif_sistel!D:D,0)),0) -> 0 | BN19: =IFERROR(VLOOKUP(B19,dif_sistel!$D$3:$X$257,21,0),0) -> 0 | BO19: =IFERROR(SUMIF(#REF!,total!B19,#REF!),"0") -> 0 | BP19: =IFERROR(SUMIF(#REF!,total!B19,#REF!),"0") -> 0
B20: 17 | C20: =VLOOKUP(B20,salario!$A$3:$C$195,2,0) -> ATIVO | D20: =VLOOKUP(B20,salario!$A$3:$C$195,3,0) -> Colaborador 17 | E20: =IFERROR(VLOOKUP(B20,salario!$A$3:$K$854,11,0), "0") -> 3652.6 | F20: =SUMIF([2]unimed!$AL:$AL,B20,[2]unimed!$AJ:$AJ) -> #VALUE! | G20: =SUMIF([2]unimed!$AL:$AL,B20,[2]unimed!$AQ:$AQ) -> #VALUE! | H20: =SUMIF([2]unimed!$AL:$AL,B20,[2]unimed!$AP:$AP) -> #VALUE! | I20: =IFERROR(VLOOKUP(B20,uniodonto!$B$3:$F$339,5,0),0) -> 126.57 | J20: =IF(E20>=0,IF(AND(E20>tabelas!$C$4,E20<=tabelas!$C$5),I20*tabelas!$E$4,IF(AND(E20>=tabelas!$C$5,E20<=tabelas!$C$6),I20*tabelas!$E$5,IF(AND(E20>=tabelas!$C$6,E20<=tabelas!$C$7),I20*tabelas!$E$6,IF(AND(E20>0,E20>tabelas!$C$7),I20*tabelas!$E$7,0))))) -> 8.8599 | K20: =I20-J20 -> 117.7101 | L20: =SUMIF(caju!$A$4:$A$562,total!B20,caju!$C$4:$C$2900) -> 500 | M20: =IF(E20>=0,IF(AND(E20>tabelas!$C$11,E20<=tabelas!$C$12),L20*tabelas!$E$11,IF(AND(E20>=tabelas!$C$12,E20<=tabelas!$C$13),L20*tabelas!$E$12,IF(AND(E20>=tabelas!$C$13,E20<=tabelas!$C$14),L20*tabelas!$E$13,IF(AND(E20>0,E20>tabelas!$C$14),L20*tabelas!$E$14,0))))) -> 10 | N20: =L20-M20 -> 490 | O20: =IFERROR(VLOOKUP(B20,segurodevida!$B$4:$E$588,4,0),0) -> 11.670057 | P20: =O20/2 -> 5.8350285 | Q20: =O20-P20 -> 5.8350285 | V20: =IFERROR(VLOOKUP(B20,#REF!,3,0),0) -> 0 | W20: =SUMIF(#REF!,total!B20,#REF!) -> #REF! | X20: =IFERROR(VLOOKUP(B20,#REF!,4,0),0) -> 0 | Y20: =IFERROR(VLOOKUP(B20,#REF!,5,0),0) -> 0 | Z20: =IFERROR(X20-Y20,0) -> 0 | AA20: =IFERROR(VLOOKUP(B20,#REF!,3,0),0) -> 0 | AB20: =IFERROR(VLOOKUP(B20,#REF!,3,0),0) -> 0 | AC20: =IFERROR(VLOOKUP(B20,#REF!,5,0),0) -> 0 | AD20: 275 | AE20: =IFERROR(VLOOKUP(B20,#REF!,3,0),0) -> 0 | AF20: =IFERROR(VLOOKUP(B20,#REF!,3,0),0) -> 0 | AG20: =IFERROR(VLOOKUP(B20,#REF!,3,0),0) -> 0 | AK20: =IFERROR(VLOOKUP(B20,#REF!,3,0),0) -> 0 | AL20: =IFERROR(VLOOKUP(B20,ingles!$A$2:$C$673,3,0),"-") -> 165 | AM20: =ROUNDUP(IFERROR(AL20*39.39%,"0"),1) -> 65 | AN20: =IFERROR(AL20-AM20,"-") -> 100 | AO20: =SUMIFS(zenklub!I:I,zenklub!A:A,total!B20) -> 90.566667 | AP20: =SUMIF(zenklub!$A$49:$A$106,total!B20,zenklub!$I$49:$I$106) -> 23.9 | AQ20: =AO20-AP20 -> 66.666667 | AR20: =SUMIF([3]bradesco!$C:$C,B20,[3]bradesco!$M:$M) -> #VALUE! | AS20: =SUMIF([3]bradesco!$C:$C,B20,[3]bradesco!$V:$V) -> #VALUE! | AT20: =IFERROR(SUMIF([3]bradesco!$C:$C,B20,[3]bradesco!$Y:$Y),0) -> 0 | AU20: =SUMIF([4]bradesco!$C:$C,B20,[4]bradesco!$M:$M) -> #VALUE! | AV20: =SUMIF([4]bradesco!$C:$C,B20,[4]bradesco!$V:$V) -> #VALUE! | AW20: =AU20-AV20 -> #VALUE! | AX20: =IFERROR(VLOOKUP(B20,#REF!,3,0),0) -> 0 | AY20: =IFERROR(VLOOKUP(B20,#REF!,3,0),0) -> 0 | AZ20: =IFERROR(VLOOKUP(B20,#REF!,3,0),0) -> 0 | BA20: 0 | BB20: =IFERROR(VLOOKUP(B20,#REF!,3,0),0) -> 0 | BC20: =IF(E20>=0,IF(AND(E20>tabelas!$C$11,E20<=tabelas!$C$12),BB20*tabelas!$E$11,IF(AND(E20>=tabelas!$C$12,E20<=tabelas!$C$13),BB20*tabelas!$E$12,IF(AND(E20>=tabelas!$C$13,E20<=tabelas!$C$14),BB20*tabelas!$E$13,IF(AND(E20>0,E20>tabelas!$C$14),BB20*tabelas!$E$14,0))))) -> 0 | BD20: =BB20-BC20 -> 0 | BE20: =SUMIF(open_english!A:A,total!B20,open_english!C:C) -> 138.88889 | BF20: =SUMIF(open_english!A:A,total!B20,open_english!D:D) -> 96.56 | BG20: =SUMIF(open_english!A:A,total!B20,open_english!E:E) -> 42.328889 | BH20: =IFERROR(VLOOKUP(B20,gympass!$A$2:$F$527,6,0),"-") -> 166.66667 | BI20: =IFERROR(VLOOKUP(B20,#REF!,4,0),"-") -> - | BJ20: =IFERROR(VLOOKUP(B20,#REF!,3,0),0) -> 0 | BK20: =IF(E20>=0,IF(AND(E20>tabelas!$C$11,E20<=tabelas!$C$12),BJ20*tabelas!$E$11,IF(AND(E20>=tabelas!$C$12,E20<=tabelas!$C$13),BJ20*tabelas!$E$12,IF(AND(E20>=tabelas!$C$13,E20<=tabelas!$C$14),BJ20*tabelas!$E$13,IF(AND(E20>0,E20>tabelas!$C$14),BJ20*tabelas!$E$14,0))))) -> 0 | BL20: =BJ20-BK20 -> 0 | BM20: =IFERROR(INDEX(dif_sistel!L:L,MATCH(total!B20,dif_sistel!D:D,0)),0)+IFERROR(INDEX(dif_sistel!N:N,MATCH(total!B20,dif_sistel!D:D,0)),0) -> 0 | BN20: =IFERROR(VLOOKUP(B20,dif_sistel!$D$3:$X$257,21,0),0) -> 0 | BO20: =IFERROR(SUMIF(#REF!,total!B20,#REF!),"0") -> 0 | BP20: =IFERROR(SUMIF(#REF!,total!B20,#REF!),"0") -> 0
B21: 18 | C21: =VLOOKUP(B21,salario!$A$3:$C$195,2,0) -> ATIVO | D21: =VLOOKUP(B21,salario!$A$3:$C$195,3,0) -> Colaborador 18 | E21: =IFERROR(VLOOKUP(B21,salario!$A$3:$K$854,11,0), "0") -> 7943.86 | F21: =SUMIF([2]unimed!$AL:$AL,B21,[2]unimed!$AJ:$AJ) -> #VALUE! | G21: =SUMIF([2]unimed!$AL:$AL,B21,[2]unimed!$AQ:$AQ) -> #VALUE! | H21: =SUMIF([2]unimed!$AL:$AL,B21,[2]unimed!$AP:$AP) -> #VALUE! | I21: =IFERROR(VLOOKUP(B21,uniodonto!$B$3:$F$339,5,0),0) -> 168.76 | J21: =IF(E21>=0,IF(AND(E21>tabelas!$C$4,E21<=tabelas!$C$5),I21*tabelas!$E$4,IF(AND(E21>=tabelas!$C$5,E21<=tabelas!$C$6),I21*tabelas!$E$5,IF(AND(E21>=tabelas!$C$6,E21<=tabelas!$C$7),I21*tabelas!$E$6,IF(AND(E21>0,E21>tabelas!$C$7),I21*tabelas!$E$7,0))))) -> 38.8148 | K21: =I21-J21 -> 129.9452 | L21: =SUMIF(caju!$A$4:$A$562,total!B21,caju!$C$4:$C$2900) -> 500 | M21: =IF(E21>=0,IF(AND(E21>tabelas!$C$11,E21<=tabelas!$C$12),L21*tabelas!$E$11,IF(AND(E21>=tabelas!$C$12,E21<=tabelas!$C$13),L21*tabelas!$E$12,IF(AND(E21>=tabelas!$C$13,E21<=tabelas!$C$14),L21*tabelas!$E$13,IF(AND(E21>0,E21>tabelas!$C$14),L21*tabelas!$E$14,0))))) -> 50 | N21: =L21-M21 -> 450 | O21: =IFERROR(VLOOKUP(B21,segurodevida!$B$4:$E$588,4,0),0) -> 25.380633 | P21: =O21/2 -> 12.690316 | Q21: =O21-P21 -> 12.690316 | V21: =IFERROR(VLOOKUP(B21,#REF!,3,0),0) -> 0 | W21: =SUMIF(#REF!,total!B21,#REF!) -> #REF! | X21: =IFERROR(VLOOKUP(B21,#REF!,4,0),0) -> 0 | Y21: =IFERROR(VLOOKUP(B21,#REF!,5,0),0) -> 0 | Z21: =IFERROR(X21-Y21,0) -> 0 | AA21: =IFERROR(VLOOKUP(B21,#REF!,3,0),0) -> 0 | AB21: =IFERROR(VLOOKUP(B21,#REF!,3,0),0) -> 0 | AC21: =IFERROR(VLOOKUP(B21,#REF!,5,0),0) -> 0 | AD21: 275 | AE21: =IFERROR(VLOOKUP(B21,#REF!,3,0),0) -> 0 | AF21: =IFERROR(VLOOKUP(B21,#REF!,3,0),0) -> 0 | AG21: =IFERROR(VLOOKUP(B21,#REF!,3,0),0) -> 0 | AK21: =IFERROR(VLOOKUP(B21,#REF!,3,0),0) -> 0 | AL21: =IFERROR(VLOOKUP(B21,ingles!$A$2:$C$673,3,0),"-") -> 165 | AM21: =ROUNDUP(IFERROR(AL21*39.39%,"0"),1) -> 65 | AN21: =IFERROR(AL21-AM21,"-") -> 100 | AO21: =SUMIFS(zenklub!I:I,zenklub!A:A,total!B21) -> 90.566667 | AP21: =SUMIF(zenklub!$A$49:$A$106,total!B21,zenklub!$I$49:$I$106) -> 23.9 | AQ21: =AO21-AP21 -> 66.666667 | AR21: =SUMIF([3]bradesco!$C:$C,B21,[3]bradesco!$M:$M) -> #VALUE! | AS21: =SUMIF([3]bradesco!$C:$C,B21,[3]bradesco!$V:$V) -> #VALUE! | AT21: =IFERROR(SUMIF([3]bradesco!$C:$C,B21,[3]bradesco!$Y:$Y),0) -> 0 | AU21: =SUMIF([4]bradesco!$C:$C,B21,[4]bradesco!$M:$M) -> #VALUE! | AV21: =SUMIF([4]bradesco!$C:$C,B21,[4]bradesco!$V:$V) -> #VALUE! | AW21: =AU21-AV21 -> #VALUE! | AX21: =IFERROR(VLOOKUP(B21,#REF!,3,0),0) -> 0 | AY21: =IFERROR(VLOOKUP(B21,#REF!,3,0),0) -> 0 | AZ21: =IFERROR(VLOOKUP(B21,#REF!,3,0),0) -> 0 | BA21: 0 | BB21: =IFERROR(VLOOKUP(B21,#REF!,3,0),0) -> 0 | BC21: =IF(E21>=0,IF(AND(E21>tabelas!$C$11,E21<=tabelas!$C$12),BB21*tabelas!$E$11,IF(AND(E21>=tabelas!$C$12,E21<=tabelas!$C$13),BB21*tabelas!$E$12,IF(AND(E21>=tabelas!$C$13,E21<=tabelas!$C$14),BB21*tabelas!$E$13,IF(AND(E21>0,E21>tabelas!$C$14),BB21*tabelas!$E$14,0))))) -> 0 | BD21: =BB21-BC21 -> 0 | BE21: =SUMIF(open_english!A:A,total!B21,open_english!C:C) -> 138.88889 | BF21: =SUMIF(open_english!A:A,total!B21,open_english!D:D) -> 96.56 | BG21: =SUMIF(open_english!A:A,total!B21,open_english!E:E) -> 42.328889 | BH21: =IFERROR(VLOOKUP(B21,gympass!$A$2:$F$527,6,0),"-") -> 166.66667 | BI21: =IFERROR(VLOOKUP(B21,#REF!,4,0),"-") -> - | BJ21: =IFERROR(VLOOKUP(B21,#REF!,3,0),0) -> 0 | BK21: =IF(E21>=0,IF(AND(E21>tabelas!$C$11,E21<=tabelas!$C$12),BJ21*tabelas!$E$11,IF(AND(E21>=tabelas!$C$12,E21<=tabelas!$C$13),BJ21*tabelas!$E$12,IF(AND(E21>=tabelas!$C$13,E21<=tabelas!$C$14),BJ21*tabelas!$E$13,IF(AND(E21>0,E21>tabelas!$C$14),BJ21*tabelas!$E$14,0))))) -> 0 | BL21: =BJ21-BK21 -> 0 | BM21: =IFERROR(INDEX(dif_sistel!L:L,MATCH(total!B21,dif_sistel!D:D,0)),0)+IFERROR(INDEX(dif_sistel!N:N,MATCH(total!B21,dif_sistel!D:D,0)),0) -> 0 | BN21: =IFERROR(VLOOKUP(B21,dif_sistel!$D$3:$X$257,21,0),0) -> 0 | BO21: =IFERROR(SUMIF(#REF!,total!B21,#REF!),"0") -> 0 | BP21: =IFERROR(SUMIF(#REF!,total!B21,#REF!),"0") -> 0
B22: 19 | C22: =VLOOKUP(B22,salario!$A$3:$C$195,2,0) -> ATIVO | D22: =VLOOKUP(B22,salario!$A$3:$C$195,3,0) -> Colaborador 19 | E22: =IFERROR(VLOOKUP(B22,salario!$A$3:$K$854,11,0), "0") -> 7131.14 | F22: =SUMIF([2]unimed!$AL:$AL,B22,[2]unimed!$AJ:$AJ) -> #VALUE! | G22: =SUMIF([2]unimed!$AL:$AL,B22,[2]unimed!$AQ:$AQ) -> #VALUE! | H22: =SUMIF([2]unimed!$AL:$AL,B22,[2]unimed!$AP:$AP) -> #VALUE! | I22: =IFERROR(VLOOKUP(B22,uniodonto!$B$3:$F$339,5,0),0) -> 84.38 | J22: =IF(E22>=0,IF(AND(E22>tabelas!$C$4,E22<=tabelas!$C$5),I22*tabelas!$E$4,IF(AND(E22>=tabelas!$C$5,E22<=tabelas!$C$6),I22*tabelas!$E$5,IF(AND(E22>=tabelas!$C$6,E22<=tabelas!$C$7),I22*tabelas!$E$6,IF(AND(E22>0,E22>tabelas!$C$7),I22*tabelas!$E$7,0))))) -> 12.657 | K22: =I22-J22 -> 71.723 | L22: =SUMIF(caju!$A$4:$A$562,total!B22,caju!$C$4:$C$2900) -> 500 | M22: =IF(E22>=0,IF(AND(E22>tabelas!$C$11,E22<=tabelas!$C$12),L22*tabelas!$E$11,IF(AND(E22>=tabelas!$C$12,E22<=tabelas!$C$13),L22*tabelas!$E$12,IF(AND(E22>=tabelas!$C$13,E22<=tabelas!$C$14),L22*tabelas!$E$13,IF(AND(E22>0,E22>tabelas!$C$14),L22*tabelas!$E$14,0))))) -> 30 | N22: =L22-M22 -> 470 | O22: =IFERROR(VLOOKUP(B22,segurodevida!$B$4:$E$588,4,0),0) -> 22.783992 | P22: =O22/2 -> 11.391996 | Q22: =O22-P22 -> 11.391996 | V22: =IFERROR(VLOOKUP(B22,#REF!,3,0),0) -> 0 | W22: =SUMIF(#REF!,total!B22,#REF!) -> #REF! | X22: =IFERROR(VLOOKUP(B22,#REF!,4,0),0) -> 0 | Y22: =IFERROR(VLOOKUP(B22,#REF!,5,0),0) -> 0 | Z22: =IFERROR(X22-Y22,0) -> 0 | AA22: =IFERROR(VLOOKUP(B22,#REF!,3,0),0) -> 0 | AB22: =IFERROR(VLOOKUP(B22,#REF!,3,0),0) -> 0 | AC22: =IFERROR(VLOOKUP(B22,#REF!,5,0),0) -> 0 | AD22: 275 | AE22: =IFERROR(VLOOKUP(B22,#REF!,3,0),0) -> 0 | AF22: =IFERROR(VLOOKUP(B22,#REF!,3,0),0) -> 0 | AG22: =IFERROR(VLOOKUP(B22,#REF!,3,0),0) -> 0 | AK22: =IFERROR(VLOOKUP(B22,#REF!,3,0),0) -> 0 | AL22: =IFERROR(VLOOKUP(B22,ingles!$A$2:$C$673,3,0),"-") -> 165 | AM22: =ROUNDUP(IFERROR(AL22*39.39%,"0"),1) -> 65 | AN22: =IFERROR(AL22-AM22,"-") -> 100 | AO22: =SUMIFS(zenklub!I:I,zenklub!A:A,total!B22) -> 90.566667 | AP22: =SUMIF(zenklub!$A$49:$A$106,total!B22,zenklub!$I$49:$I$106) -> 23.9 | AQ22: =AO22-AP22 -> 66.666667 | AR22: =SUMIF([3]bradesco!$C:$C,B22,[3]bradesco!$M:$M) -> #VALUE! | AS22: =SUMIF([3]bradesco!$C:$C,B22,[3]bradesco!$V:$V) -> #VALUE! | AT22: =IFERROR(SUMIF([3]bradesco!$C:$C,B22,[3]bradesco!$Y:$Y),0) -> 0 | AU22: =SUMIF([4]bradesco!$C:$C,B22,[4]bradesco!$M:$M) -> #VALUE! | AV22: =SUMIF([4]bradesco!$C:$C,B22,[4]bradesco!$V:$V) -> #VALUE! | AW22: =AU22-AV22 -> #VALUE! | AX22: =IFERROR(VLOOKUP(B22,#REF!,3,0),0) -> 0 | AY22: =IFERROR(VLOOKUP(B22,#REF!,3,0),0) -> 0 | AZ22: =IFERROR(VLOOKUP(B22,#REF!,3,0),0) -> 0 | BA22: 0 | BB22: =IFERROR(VLOOKUP(B22,#REF!,3,0),0) -> 0 | BC22: =IF(E22>=0,IF(AND(E22>tabelas!$C$11,E22<=tabelas!$C$12),BB22*tabelas!$E$11,IF(AND(E22>=tabelas!$C$12,E22<=tabelas!$C$13),BB22*tabelas!$E$12,IF(AND(E22>=tabelas!$C$13,E22<=tabelas!$C$14),BB22*tabelas!$E$13,IF(AND(E22>0,E22>tabelas!$C$14),BB22*tabelas!$E$14,0))))) -> 0 | BD22: =BB22-BC22 -> 0 | BE22: =SUMIF(open_english!A:A,total!B22,open_english!C:C) -> 138.88889 | BF22: =SUMIF(open_english!A:A,total!B22,open_english!D:D) -> 96.56 | BG22: =SUMIF(open_english!A:A,total!B22,open_english!E:E) -> 42.328889 | BH22: =IFERROR(VLOOKUP(B22,gympass!$A$2:$F$527,6,0),"-") -> 166.66667 | BI22: =IFERROR(VLOOKUP(B22,#REF!,4,0),"-") -> - | BJ22: =IFERROR(VLOOKUP(B22,#REF!,3,0),0) -> 0 | BK22: =IF(E22>=0,IF(AND(E22>tabelas!$C$11,E22<=tabelas!$C$12),BJ22*tabelas!$E$11,IF(AND(E22>=tabelas!$C$12,E22<=tabelas!$C$13),BJ22*tabelas!$E$12,IF(AND(E22>=tabelas!$C$13,E22<=tabelas!$C$14),BJ22*tabelas!$E$13,IF(AND(E22>0,E22>tabelas!$C$14),BJ22*tabelas!$E$14,0))))) -> 0 | BL22: =BJ22-BK22 -> 0 | BM22: =IFERROR(INDEX(dif_sistel!L:L,MATCH(total!B22,dif_sistel!D:D,0)),0)+IFERROR(INDEX(dif_sistel!N:N,MATCH(total!B22,dif_sistel!D:D,0)),0) -> 0 | BN22: =IFERROR(VLOOKUP(B22,dif_sistel!$D$3:$X$257,21,0),0) -> 0 | BO22: =IFERROR(SUMIF(#REF!,total!B22,#REF!),"0") -> 0 | BP22: =IFERROR(SUMIF(#REF!,total!B22,#REF!),"0") -> 0
B23: 20 | C23: =VLOOKUP(B23,salario!$A$3:$C$195,2,0) -> ATIVO | D23: =VLOOKUP(B23,salario!$A$3:$C$195,3,0) -> Colaborador 20 | E23: =IFERROR(VLOOKUP(B23,salario!$A$3:$K$854,11,0), "0") -> 5245.5 | F23: =SUMIF([2]unimed!$AL:$AL,B23,[2]unimed!$AJ:$AJ) -> #VALUE! | G23: =SUMIF([2]unimed!$AL:$AL,B23,[2]unimed!$AQ:$AQ) -> #VALUE! | H23: =SUMIF([2]unimed!$AL:$AL,B23,[2]unimed!$AP:$AP) -> #VALUE! | I23: =IFERROR(VLOOKUP(B23,uniodonto!$B$3:$F$339,5,0),0) -> 168.76 | J23: =IF(E23>=0,IF(AND(E23>tabelas!$C$4,E23<=tabelas!$C$5),I23*tabelas!$E$4,IF(AND(E23>=tabelas!$C$5,E23<=tabelas!$C$6),I23*tabelas!$E$5,IF(AND(E23>=tabelas!$C$6,E23<=tabelas!$C$7),I23*tabelas!$E$6,IF(AND(E23>0,E23>tabelas!$C$7),I23*tabelas!$E$7,0))))) -> 25.314 | K23: =I23-J23 -> 143.446 | L23: =SUMIF(caju!$A$4:$A$562,total!B23,caju!$C$4:$C$2900) -> 500 | M23: =IF(E23>=0,IF(AND(E23>tabelas!$C$11,E23<=tabelas!$C$12),L23*tabelas!$E$11,IF(AND(E23>=tabelas!$C$12,E23<=tabelas!$C$13),L23*tabelas!$E$12,IF(AND(E23>=tabelas!$C$13,E23<=tabelas!$C$14),L23*tabelas!$E$13,IF(AND(E23>0,E23>tabelas!$C$14),L23*tabelas!$E$14,0))))) -> 30 | N23: =L23-M23 -> 470 | O23: =IFERROR(VLOOKUP(B23,segurodevida!$B$4:$E$588,4,0),0) -> 16.759373 | P23: =O23/2 -> 8.3796863 | Q23: =O23-P23 -> 8.3796863 | V23: =IFERROR(VLOOKUP(B23,#REF!,3,0),0) -> 0 | W23: =SUMIF(#REF!,total!B23,#REF!) -> #REF! | X23: =IFERROR(VLOOKUP(B23,#REF!,4,0),0) -> 0 | Y23: =IFERROR(VLOOKUP(B23,#REF!,5,0),0) -> 0 | Z23: =IFERROR(X23-Y23,0) -> 0 | AA23: =IFERROR(VLOOKUP(B23,#REF!,3,0),0) -> 0 | AB23: =IFERROR(VLOOKUP(B23,#REF!,3,0),0) -> 0 | AC23: =IFERROR(VLOOKUP(B23,#REF!,5,0),0) -> 0 | AD23: 275 | AE23: =IFERROR(VLOOKUP(B23,#REF!,3,0),0) -> 0 | AF23: =IFERROR(VLOOKUP(B23,#REF!,3,0),0) -> 0 | AG23: =IFERROR(VLOOKUP(B23,#REF!,3,0),0) -> 0 | AK23: =IFERROR(VLOOKUP(B23,#REF!,3,0),0) -> 0 | AL23: =IFERROR(VLOOKUP(B23,ingles!$A$2:$C$673,3,0),"-") -> 165 | AM23: =ROUNDUP(IFERROR(AL23*39.39%,"0"),1) -> 65 | AN23: =IFERROR(AL23-AM23,"-") -> 100 | AO23: =SUMIFS(zenklub!I:I,zenklub!A:A,total!B23) -> 90.566667 | AP23: =SUMIF(zenklub!$A$49:$A$106,total!B23,zenklub!$I$49:$I$106) -> 23.9 | AQ23: =AO23-AP23 -> 66.666667 | AR23: =SUMIF([3]bradesco!$C:$C,B23,[3]bradesco!$M:$M) -> #VALUE! | AS23: =SUMIF([3]bradesco!$C:$C,B23,[3]bradesco!$V:$V) -> #VALUE! | AT23: =IFERROR(SUMIF([3]bradesco!$C:$C,B23,[3]bradesco!$Y:$Y),0) -> 0 | AU23: =SUMIF([4]bradesco!$C:$C,B23,[4]bradesco!$M:$M) -> #VALUE! | AV23: =SUMIF([4]bradesco!$C:$C,B23,[4]bradesco!$V:$V) -> #VALUE! | AW23: =AU23-AV23 -> #VALUE! | AX23: =IFERROR(VLOOKUP(B23,#REF!,3,0),0) -> 0 | AY23: =IFERROR(VLOOKUP(B23,#REF!,3,0),0) -> 0 | AZ23: =IFERROR(VLOOKUP(B23,#REF!,3,0),0) -> 0 | BA23: 0 | BB23: =IFERROR(VLOOKUP(B23,#REF!,3,0),0) -> 0 | BC23: =IF(E23>=0,IF(AND(E23>tabelas!$C$11,E23<=tabelas!$C$12),BB23*tabelas!$E$11,IF(AND(E23>=tabelas!$C$12,E23<=tabelas!$C$13),BB23*tabelas!$E$12,IF(AND(E23>=tabelas!$C$13,E23<=tabelas!$C$14),BB23*tabelas!$E$13,IF(AND(E23>0,E23>tabelas!$C$14),BB23*tabelas!$E$14,0))))) -> 0 | BD23: =BB23-BC23 -> 0 | BE23: =SUMIF(open_english!A:A,total!B23,open_english!C:C) -> 138.88889 | BF23: =SUMIF(open_english!A:A,total!B23,open_english!D:D) -> 96.56 | BG23: =SUMIF(open_english!A:A,total!B23,open_english!E:E) -> 42.328889 | BH23: =IFERROR(VLOOKUP(B23,gympass!$A$2:$F$527,6,0),"-") -> 166.66667 | BI23: =IFERROR(VLOOKUP(B23,#REF!,4,0),"-") -> - | BJ23: =IFERROR(VLOOKUP(B23,#REF!,3,0),0) -> 0 | BK23: =IF(E23>=0,IF(AND(E23>tabelas!$C$11,E23<=tabelas!$C$12),BJ23*tabelas!$E$11,IF(AND(E23>=tabelas!$C$12,E23<=tabelas!$C$13),BJ23*tabelas!$E$12,IF(AND(E23>=tabelas!$C$13,E23<=tabelas!$C$14),BJ23*tabelas!$E$13,IF(AND(E23>0,E23>tabelas!$C$14),BJ23*tabelas!$E$14,0))))) -> 0 | BL23: =BJ23-BK23 -> 0 | BM23: =IFERROR(INDEX(dif_sistel!L:L,MATCH(total!B23,dif_sistel!D:D,0)),0)+IFERROR(INDEX(dif_sistel!N:N,MATCH(total!B23,dif_sistel!D:D,0)),0) -> 0 | BN23: =IFERROR(VLOOKUP(B23,dif_sistel!$D$3:$X$257,21,0),0) -> 0 | BO23: =IFERROR(SUMIF(#REF!,total!B23,#REF!),"0") -> 0 | BP23: =IFERROR(SUMIF(#REF!,total!B23,#REF!),"0") -> 0
B24: 21 | C24: =VLOOKUP(B24,salario!$A$3:$C$195,2,0) -> ATIVO | D24: =VLOOKUP(B24,salario!$A$3:$C$195,3,0) -> Colaborador 21 | E24: =IFERROR(VLOOKUP(B24,salario!$A$3:$K$854,11,0), "0") -> 4229.32 | F24: =SUMIF([2]unimed!$AL:$AL,B24,[2]unimed!$AJ:$AJ) -> #VALUE! | G24: =SUMIF([2]unimed!$AL:$AL,B24,[2]unimed!$AQ:$AQ) -> #VALUE! | H24: =SUMIF([2]unimed!$AL:$AL,B24,[2]unimed!$AP:$AP) -> #VALUE! | I24: =IFERROR(VLOOKUP(B24,uniodonto!$B$3:$F$339,5,0),0) -> 210.95 | J24: =IF(E24>=0,IF(AND(E24>tabelas!$C$4,E24<=tabelas!$C$5),I24*tabelas!$E$4,IF(AND(E24>=tabelas!$C$5,E24<=tabelas!$C$6),I24*tabelas!$E$5,IF(AND(E24>=tabelas!$C$6,E24<=tabelas!$C$7),I24*tabelas!$E$6,IF(AND(E24>0,E24>tabelas!$C$7),I24*tabelas!$E$7,0))))) -> 31.6425 | K24: =I24-J24 -> 179.3075 | L24: =SUMIF(caju!$A$4:$A$562,total!B24,caju!$C$4:$C$2900) -> 500 | M24: =IF(E24>=0,IF(AND(E24>tabelas!$C$11,E24<=tabelas!$C$12),L24*tabelas!$E$11,IF(AND(E24>=tabelas!$C$12,E24<=tabelas!$C$13),L24*tabelas!$E$12,IF(AND(E24>=tabelas!$C$13,E24<=tabelas!$C$14),L24*tabelas!$E$13,IF(AND(E24>0,E24>tabelas!$C$14),L24*tabelas!$E$14,0))))) -> 30 | N24: =L24-M24 -> 470 | O24: =IFERROR(VLOOKUP(B24,segurodevida!$B$4:$E$588,4,0),0) -> 13.512677 | P24: =O24/2 -> 6.7563387 | Q24: =O24-P24 -> 6.7563387 | V24: =IFERROR(VLOOKUP(B24,#REF!,3,0),0) -> 0 | W24: =SUMIF(#REF!,total!B24,#REF!) -> #REF! | X24: =IFERROR(VLOOKUP(B24,#REF!,4,0),0) -> 0 | Y24: =IFERROR(VLOOKUP(B24,#REF!,5,0),0) -> 0 | Z24: =IFERROR(X24-Y24,0) -> 0 | AA24: =IFERROR(VLOOKUP(B24,#REF!,3,0),0) -> 0 | AB24: =IFERROR(VLOOKUP(B24,#REF!,3,0),0) -> 0 | AC24: =IFERROR(VLOOKUP(B24,#REF!,5,0),0) -> 0 | AD24: 275 | AE24: =IFERROR(VLOOKUP(B24,#REF!,3,0),0) -> 0 | AF24: =IFERROR(VLOOKUP(B24,#REF!,3,0),0) -> 0 | AG24: =IFERROR(VLOOKUP(B24,#REF!,3,0),0) -> 0 | AK24: =IFERROR(VLOOKUP(B24,#REF!,3,0),0) -> 0 | AL24: =IFERROR(VLOOKUP(B24,ingles!$A$2:$C$673,3,0),"-") -> - | AM24: =ROUNDUP(IFERROR(AL24*39.39%,"0"),1) -> 0 | AN24: =IFERROR(AL24-AM24,"-") -> - | AO24: =SUMIFS(zenklub!I:I,zenklub!A:A,total!B24) -> 90.566667 | AP24: =SUMIF(zenklub!$A$49:$A$106,total!B24,zenklub!$I$49:$I$106) -> 23.9 | AQ24: =AO24-AP24 -> 66.666667 | AR24: =SUMIF([3]bradesco!$C:$C,B24,[3]bradesco!$M:$M) -> #VALUE! | AS24: =SUMIF([3]bradesco!$C:$C,B24,[3]bradesco!$V:$V) -> #VALUE! | AT24: =IFERROR(SUMIF([3]bradesco!$C:$C,B24,[3]bradesco!$Y:$Y),0) -> 0 | AU24: =SUMIF([4]bradesco!$C:$C,B24,[4]bradesco!$M:$M) -> #VALUE! | AV24: =SUMIF([4]bradesco!$C:$C,B24,[4]bradesco!$V:$V) -> #VALUE! | AW24: =AU24-AV24 -> #VALUE! | AX24: =IFERROR(VLOOKUP(B24,#REF!,3,0),0) -> 0 | AY24: =IFERROR(VLOOKUP(B24,#REF!,3,0),0) -> 0 | AZ24: =IFERROR(VLOOKUP(B24,#REF!,3,0),0) -> 0 | BA24: 0 | BB24: =IFERROR(VLOOKUP(B24,#REF!,3,0),0) -> 0 | BC24: =IF(E24>=0,IF(AND(E24>tabelas!$C$11,E24<=tabelas!$C$12),BB24*tabelas!$E$11,IF(AND(E24>=tabelas!$C$12,E24<=tabelas!$C$13),BB24*tabelas!$E$12,IF(AND(E24>=tabelas!$C$13,E24<=tabelas!$C$14),BB24*tabelas!$E$13,IF(AND(E24>0,E24>tabelas!$C$14),BB24*tabelas!$E$14,0))))) -> 0 | BD24: =BB24-BC24 -> 0 | BE24: =SUMIF(open_english!A:A,total!B24,open_english!C:C) -> 138.88889 | BF24: =SUMIF(open_english!A:A,total!B24,open_english!D:D) -> 96.56 | BG24: =SUMIF(open_english!A:A,total!B24,open_english!E:E) -> 42.328889 | BH24: =IFERROR(VLOOKUP(B24,gympass!$A$2:$F$527,6,0),"-") -> 166.66667 | BI24: =IFERROR(VLOOKUP(B24,#REF!,4,0),"-") -> - | BJ24: =IFERROR(VLOOKUP(B24,#REF!,3,0),0) -> 0 | BK24: =IF(E24>=0,IF(AND(E24>tabelas!$C$11,E24<=tabelas!$C$12),BJ24*tabelas!$E$11,IF(AND(E24>=tabelas!$C$12,E24<=tabelas!$C$13),BJ24*tabelas!$E$12,IF(AND(E24>=tabelas!$C$13,E24<=tabelas!$C$14),BJ24*tabelas!$E$13,IF(AND(E24>0,E24>tabelas!$C$14),BJ24*tabelas!$E$14,0))))) -> 0 | BL24: =BJ24-BK24 -> 0 | BM24: =IFERROR(INDEX(dif_sistel!L:L,MATCH(total!B24,dif_sistel!D:D,0)),0)+IFERROR(INDEX(dif_sistel!N:N,MATCH(total!B24,dif_sistel!D:D,0)),0) -> 0 | BN24: =IFERROR(VLOOKUP(B24,dif_sistel!$D$3:$X$257,21,0),0) -> 0 | BO24: =IFERROR(SUMIF(#REF!,total!B24,#REF!),"0") -> 0 | BP24: =IFERROR(SUMIF(#REF!,total!B24,#REF!),"0") -> 0
B25: 22 | C25: =VLOOKUP(B25,salario!$A$3:$C$195,2,0) -> ATIVO | D25: =VLOOKUP(B25,salario!$A$3:$C$195,3,0) -> Colaborador 22 | E25: =IFERROR(VLOOKUP(B25,salario!$A$3:$K$854,11,0), "0") -> 2404.84 | F25: =SUMIF([2]unimed!$AL:$AL,B25,[2]unimed!$AJ:$AJ) -> #VALUE! | G25: =SUMIF([2]unimed!$AL:$AL,B25,[2]unimed!$AQ:$AQ) -> #VALUE! | H25: =SUMIF([2]unimed!$AL:$AL,B25,[2]unimed!$AP:$AP) -> #VALUE! | I25: =IFERROR(VLOOKUP(B25,uniodonto!$B$3:$F$339,5,0),0) -> 168.76 | J25: =IF(E25>=0,IF(AND(E25>tabelas!$C$4,E25<=tabelas!$C$5),I25*tabelas!$E$4,IF(AND(E25>=tabelas!$C$5,E25<=tabelas!$C$6),I25*tabelas!$E$5,IF(AND(E25>=tabelas!$C$6,E25<=tabelas!$C$7),I25*tabelas!$E$6,IF(AND(E25>0,E25>tabelas!$C$7),I25*tabelas!$E$7,0))))) -> 11.8132 | K25: =I25-J25 -> 156.9468 | L25: =SUMIF(caju!$A$4:$A$562,total!B25,caju!$C$4:$C$2900) -> 500 | M25: =IF(E25>=0,IF(AND(E25>tabelas!$C$11,E25<=tabelas!$C$12),L25*tabelas!$E$11,IF(AND(E25>=tabelas!$C$12,E25<=tabelas!$C$13),L25*tabelas!$E$12,IF(AND(E25>=tabelas!$C$13,E25<=tabelas!$C$14),L25*tabelas!$E$13,IF(AND(E25>0,E25>tabelas!$C$14),L25*tabelas!$E$14,0))))) -> 10 | N25: =L25-M25 -> 490 | O25: =IFERROR(VLOOKUP(B25,segurodevida!$B$4:$E$588,4,0),0) -> 7.6834638 | P25: =O25/2 -> 3.8417319 | Q25: =O25-P25 -> 3.8417319 | V25: =IFERROR(VLOOKUP(B25,#REF!,3,0),0) -> 0 | W25: =SUMIF(#REF!,total!B25,#REF!) -> #REF! | X25: =IFERROR(VLOOKUP(B25,#REF!,4,0),0) -> 0 | Y25: =IFERROR(VLOOKUP(B25,#REF!,5,0),0) -> 0 | Z25: =IFERROR(X25-Y25,0) -> 0 | AA25: =IFERROR(VLOOKUP(B25,#REF!,3,0),0) -> 0 | AB25: =IFERROR(VLOOKUP(B25,#REF!,3,0),0) -> 0 | AC25: =IFERROR(VLOOKUP(B25,#REF!,5,0),0) -> 0 | AD25: 275 | AE25: =IFERROR(VLOOKUP(B25,#REF!,3,0),0) -> 0 | AF25: =IFERROR(VLOOKUP(B25,#REF!,3,0),0) -> 0 | AG25: =IFERROR(VLOOKUP(B25,#REF!,3,0),0) -> 0 | AK25: =IFERROR(VLOOKUP(B25,#REF!,3,0),0) -> 0 | AL25: =IFERROR(VLOOKUP(B25,ingles!$A$2:$C$673,3,0),"-") -> - | AM25: =ROUNDUP(IFERROR(AL25*39.39%,"0"),1) -> 0 | AN25: =IFERROR(AL25-AM25,"-") -> - | AO25: =SUMIFS(zenklub!I:I,zenklub!A:A,total!B25) -> 90.566667 | AP25: =SUMIF(zenklub!$A$49:$A$106,total!B25,zenklub!$I$49:$I$106) -> 23.9 | AQ25: =AO25-AP25 -> 66.666667 | AR25: =SUMIF([3]bradesco!$C:$C,B25,[3]bradesco!$M:$M) -> #VALUE! | AS25: =SUMIF([3]bradesco!$C:$C,B25,[3]bradesco!$V:$V) -> #VALUE! | AT25: =IFERROR(SUMIF([3]bradesco!$C:$C,B25,[3]bradesco!$Y:$Y),0) -> 0 | AU25: =SUMIF([4]bradesco!$C:$C,B25,[4]bradesco!$M:$M) -> #VALUE! | AV25: =SUMIF([4]bradesco!$C:$C,B25,[4]bradesco!$V:$V) -> #VALUE! | AW25: =AU25-AV25 -> #VALUE! | AX25: =IFERROR(VLOOKUP(B25,#REF!,3,0),0) -> 0 | AY25: =IFERROR(VLOOKUP(B25,#REF!,3,0),0) -> 0 | AZ25: =IFERROR(VLOOKUP(B25,#REF!,3,0),0) -> 0 | BA25: 0 | BB25: =IFERROR(VLOOKUP(B25,#REF!,3,0),0) -> 0 | BC25: =IF(E25>=0,IF(AND(E25>tabelas!$C$11,E25<=tabelas!$C$12),BB25*tabelas!$E$11,IF(AND(E25>=tabelas!$C$12,E25<=tabelas!$C$13),BB25*tabelas!$E$12,IF(AND(E25>=tabelas!$C$13,E25<=tabelas!$C$14),BB25*tabelas!$E$13,IF(AND(E25>0,E25>tabelas!$C$14),BB25*tabelas!$E$14,0))))) -> 0 | BD25: =BB25-BC25 -> 0 | BE25: =SUMIF(open_english!A:A,total!B25,open_english!C:C) -> 138.88889 | BF25: =SUMIF(open_english!A:A,total!B25,open_english!D:D) -> 96.56 | BG25: =SUMIF(open_english!A:A,total!B25,open_english!E:E) -> 42.328889 | BH25: =IFERROR(VLOOKUP(B25,gympass!$A$2:$F$527,6,0),"-") -> 166.66667 | BI25: =IFERROR(VLOOKUP(B25,#REF!,4,0),"-") -> - | BJ25: =IFERROR(VLOOKUP(B25,#REF!,3,0),0) -> 0 | BK25: =IF(E25>=0,IF(AND(E25>tabelas!$C$11,E25<=tabelas!$C$12),BJ25*tabelas!$E$11,IF(AND(E25>=tabelas!$C$12,E25<=tabelas!$C$13),BJ25*tabelas!$E$12,IF(AND(E25>=tabelas!$C$13,E25<=tabelas!$C$14),BJ25*tabelas!$E$13,IF(AND(E25>0,E25>tabelas!$C$14),BJ25*tabelas!$E$14,0))))) -> 0 | BL25: =BJ25-BK25 -> 0 | BM25: =IFERROR(INDEX(dif_sistel!L:L,MATCH(total!B25,dif_sistel!D:D,0)),0)+IFERROR(INDEX(dif_sistel!N:N,MATCH(total!B25,dif_sistel!D:D,0)),0) -> 0 | BN25: =IFERROR(VLOOKUP(B25,dif_sistel!$D$3:$X$257,21,0),0) -> 0 | BO25: =IFERROR(SUMIF(#REF!,total!B25,#REF!),"0") -> 0 | BP25: =IFERROR(SUMIF(#REF!,total!B25,#REF!),"0") -> 0
B26: 23 | C26: =VLOOKUP(B26,salario!$A$3:$C$195,2,0) -> ATIVO | D26: =VLOOKUP(B26,salario!$A$3:$C$195,3,0) -> Colaborador 23 | E26: =IFERROR(VLOOKUP(B26,salario!$A$3:$K$854,11,0), "0") -> 2335.03 | F26: =SUMIF([2]unimed!$AL:$AL,B26,[2]unimed!$AJ:$AJ) -> #VALUE! | G26: =SUMIF([2]unimed!$AL:$AL,B26,[2]unimed!$AQ:$AQ) -> #VALUE! | H26: =SUMIF([2]unimed!$AL:$AL,B26,[2]unimed!$AP:$AP) -> #VALUE! | I26: =IFERROR(VLOOKUP(B26,uniodonto!$B$3:$F$339,5,0),0) -> 126.57 | J26: =IF(E26>=0,IF(AND(E26>tabelas!$C$4,E26<=tabelas!$C$5),I26*tabelas!$E$4,IF(AND(E26>=tabelas!$C$5,E26<=tabelas!$C$6),I26*tabelas!$E$5,IF(AND(E26>=tabelas!$C$6,E26<=tabelas!$C$7),I26*tabelas!$E$6,IF(AND(E26>0,E26>tabelas!$C$7),I26*tabelas!$E$7,0))))) -> 8.8599 | K26: =I26-J26 -> 117.7101 | L26: =SUMIF(caju!$A$4:$A$562,total!B26,caju!$C$4:$C$2900) -> 550 | M26: =IF(E26>=0,IF(AND(E26>tabelas!$C$11,E26<=tabelas!$C$12),L26*tabelas!$E$11,IF(AND(E26>=tabelas!$C$12,E26<=tabelas!$C$13),L26*tabelas!$E$12,IF(AND(E26>=tabelas!$C$13,E26<=tabelas!$C$14),L26*tabelas!$E$13,IF(AND(E26>0,E26>tabelas!$C$14),L26*tabelas!$E$14,0))))) -> 11 | N26: =L26-M26 -> 539 | O26: =IFERROR(VLOOKUP(B26,segurodevida!$B$4:$E$588,4,0),0) -> 7.4604209 | P26: =O26/2 -> 3.7302104 | Q26: =O26-P26 -> 3.7302104 | V26: =IFERROR(VLOOKUP(B26,#REF!,3,0),0) -> 0 | W26: =SUMIF(#REF!,total!B26,#REF!) -> #REF! | X26: =IFERROR(VLOOKUP(B26,#REF!,4,0),0) -> 0 | Y26: =IFERROR(VLOOKUP(B26,#REF!,5,0),0) -> 0 | Z26: =IFERROR(X26-Y26,0) -> 0 | AA26: =IFERROR(VLOOKUP(B26,#REF!,3,0),0) -> 0 | AB26: =IFERROR(VLOOKUP(B26,#REF!,3,0),0) -> 0 | AC26: =IFERROR(VLOOKUP(B26,#REF!,5,0),0) -> 0 | AD26: 275 | AE26: =IFERROR(VLOOKUP(B26,#REF!,3,0),0) -> 0 | AF26: =IFERROR(VLOOKUP(B26,#REF!,3,0),0) -> 0 | AG26: =IFERROR(VLOOKUP(B26,#REF!,3,0),0) -> 0 | AK26: =IFERROR(VLOOKUP(B26,#REF!,3,0),0) -> 0 | AL26: =IFERROR(VLOOKUP(B26,ingles!$A$2:$C$673,3,0),"-") -> - | AM26: =ROUNDUP(IFERROR(AL26*39.39%,"0"),1) -> 0 | AN26: =IFERROR(AL26-AM26,"-") -> - | AO26: =SUMIFS(zenklub!I:I,zenklub!A:A,total!B26) -> 90.566667 | AP26: =SUMIF(zenklub!$A$49:$A$106,total!B26,zenklub!$I$49:$I$106) -> 23.9 | AQ26: =AO26-AP26 -> 66.666667 | AR26: =SUMIF([3]bradesco!$C:$C,B26,[3]bradesco!$M:$M) -> #VALUE! | AS26: =SUMIF([3]bradesco!$C:$C,B26,[3]bradesco!$V:$V) -> #VALUE! | AT26: =IFERROR(SUMIF([3]bradesco!$C:$C,B26,[3]bradesco!$Y:$Y),0) -> 0 | AU26: =SUMIF([4]bradesco!$C:$C,B26,[4]bradesco!$M:$M) -> #VALUE! | AV26: =SUMIF([4]bradesco!$C:$C,B26,[4]bradesco!$V:$V) -> #VALUE! | AW26: =AU26-AV26 -> #VALUE! | AX26: =IFERROR(VLOOKUP(B26,#REF!,3,0),0) -> 0 | AY26: =IFERROR(VLOOKUP(B26,#REF!,3,0),0) -> 0 | AZ26: =IFERROR(VLOOKUP(B26,#REF!,3,0),0) -> 0 | BA26: 0 | BB26: =IFERROR(VLOOKUP(B26,#REF!,3,0),0) -> 0 | BC26: =IF(E26>=0,IF(AND(E26>tabelas!$C$11,E26<=tabelas!$C$12),BB26*tabelas!$E$11,IF(AND(E26>=tabelas!$C$12,E26<=tabelas!$C$13),BB26*tabelas!$E$12,IF(AND(E26>=tabelas!$C$13,E26<=tabelas!$C$14),BB26*tabelas!$E$13,IF(AND(E26>0,E26>tabelas!$C$14),BB26*tabelas!$E$14,0))))) -> 0 | BD26: =BB26-BC26 -> 0 | BE26: =SUMIF(open_english!A:A,total!B26,open_english!C:C) -> 138.88889 | BF26: =SUMIF(open_english!A:A,total!B26,open_english!D:D) -> 96.56 | BG26: =SUMIF(open_english!A:A,total!B26,open_english!E:E) -> 42.328889 | BH26: =IFERROR(VLOOKUP(B26,gympass!$A$2:$F$527,6,0),"-") -> 166.66667 | BI26: =IFERROR(VLOOKUP(B26,#REF!,4,0),"-") -> - | BJ26: =IFERROR(VLOOKUP(B26,#REF!,3,0),0) -> 0 | BK26: =IF(E26>=0,IF(AND(E26>tabelas!$C$11,E26<=tabelas!$C$12),BJ26*tabelas!$E$11,IF(AND(E26>=tabelas!$C$12,E26<=tabelas!$C$13),BJ26*tabelas!$E$12,IF(AND(E26>=tabelas!$C$13,E26<=tabelas!$C$14),BJ26*tabelas!$E$13,IF(AND(E26>0,E26>tabelas!$C$14),BJ26*tabelas!$E$14,0))))) -> 0 | BL26: =BJ26-BK26 -> 0 | BM26: =IFERROR(INDEX(dif_sistel!L:L,MATCH(total!B26,dif_sistel!D:D,0)),0)+IFERROR(INDEX(dif_sistel!N:N,MATCH(total!B26,dif_sistel!D:D,0)),0) -> 0 | BN26: =IFERROR(VLOOKUP(B26,dif_sistel!$D$3:$X$257,21,0),0) -> 0 | BO26: =IFERROR(SUMIF(#REF!,total!B26,#REF!),"0") -> 0 | BP26: =IFERROR(SUMIF(#REF!,total!B26,#REF!),"0") -> 0
B27: 24 | C27: =VLOOKUP(B27,salario!$A$3:$C$195,2,0) -> ATIVO | D27: =VLOOKUP(B27,salario!$A$3:$C$195,3,0) -> Colaborador 24 | E27: =IFERROR(VLOOKUP(B27,salario!$A$3:$K$854,11,0), "0") -> 3290.79 | F27: =SUMIF([2]unimed!$AL:$AL,B27,[2]unimed!$AJ:$AJ) -> #VALUE! | G27: =SUMIF([2]unimed!$AL:$AL,B27,[2]unimed!$AQ:$AQ) -> #VALUE! | H27: =SUMIF([2]unimed!$AL:$AL,B27,[2]unimed!$AP:$AP) -> #VALUE! | I27: =IFERROR(VLOOKUP(B27,uniodonto!$B$3:$F$339,5,0),0) -> 84.38 | J27: =IF(E27>=0,IF(AND(E27>tabelas!$C$4,E27<=tabelas!$C$5),I27*tabelas!$E$4,IF(AND(E27>=tabelas!$C$5,E27<=tabelas!$C$6),I27*tabelas!$E$5,IF(AND(E27>=tabelas!$C$6,E27<=tabelas!$C$7),I27*tabelas!$E$6,IF(AND(E27>0,E27>tabelas!$C$7),I27*tabelas!$E$7,0))))) -> 5.9066 | K27: =I27-J27 -> 78.4734 | L27: =SUMIF(caju!$A$4:$A$562,total!B27,caju!$C$4:$C$2900) -> 500 | M27: =IF(E27>=0,IF(AND(E27>tabelas!$C$11,E27<=tabelas!$C$12),L27*tabelas!$E$11,IF(AND(E27>=tabelas!$C$12,E27<=tabelas!$C$13),L27*tabelas!$E$12,IF(AND(E27>=tabelas!$C$13,E27<=tabelas!$C$14),L27*tabelas!$E$13,IF(AND(E27>0,E27>tabelas!$C$14),L27*tabelas!$E$14,0))))) -> 10 | N27: =L27-M27 -> 490 | O27: =IFERROR(VLOOKUP(B27,segurodevida!$B$4:$E$588,4,0),0) -> 10.514074 | P27: =O27/2 -> 5.257037 | Q27: =O27-P27 -> 5.257037 | V27: =IFERROR(VLOOKUP(B27,#REF!,3,0),0) -> 0 | W27: =SUMIF(#REF!,total!B27,#REF!) -> #REF! | X27: =IFERROR(VLOOKUP(B27,#REF!,4,0),0) -> 0 | Y27: =IFERROR(VLOOKUP(B27,#REF!,5,0),0) -> 0 | Z27: =IFERROR(X27-Y27,0) -> 0 | AA27: =IFERROR(VLOOKUP(B27,#REF!,3,0),0) -> 0 | AB27: =IFERROR(VLOOKUP(B27,#REF!,3,0),0) -> 0 | AC27: =IFERROR(VLOOKUP(B27,#REF!,5,0),0) -> 0 | AD27: 275 | AE27: =IFERROR(VLOOKUP(B27,#REF!,3,0),0) -> 0 | AF27: =IFERROR(VLOOKUP(B27,#REF!,3,0),0) -> 0 | AG27: =IFERROR(VLOOKUP(B27,#REF!,3,0),0) -> 0 | AK27: =IFERROR(VLOOKUP(B27,#REF!,3,0),0) -> 0 | AL27: =IFERROR(VLOOKUP(B27,ingles!$A$2:$C$673,3,0),"-") -> - | AM27: =ROUNDUP(IFERROR(AL27*39.39%,"0"),1) -> 0 | AN27: =IFERROR(AL27-AM27,"-") -> - | AO27: =SUMIFS(zenklub!I:I,zenklub!A:A,total!B27) -> 90.566667 | AP27: =SUMIF(zenklub!$A$49:$A$106,total!B27,zenklub!$I$49:$I$106) -> 23.9 | AQ27: =AO27-AP27 -> 66.666667 | AR27: =SUMIF([3]bradesco!$C:$C,B27,[3]bradesco!$M:$M) -> #VALUE! | AS27: =SUMIF([3]bradesco!$C:$C,B27,[3]bradesco!$V:$V) -> #VALUE! | AT27: =IFERROR(SUMIF([3]bradesco!$C:$C,B27,[3]bradesco!$Y:$Y),0) -> 0 | AU27: =SUMIF([4]bradesco!$C:$C,B27,[4]bradesco!$M:$M) -> #VALUE! | AV27: =SUMIF([4]bradesco!$C:$C,B27,[4]bradesco!$V:$V) -> #VALUE! | AW27: =AU27-AV27 -> #VALUE! | AX27: =IFERROR(VLOOKUP(B27,#REF!,3,0),0) -> 0 | AY27: =IFERROR(VLOOKUP(B27,#REF!,3,0),0) -> 0 | AZ27: =IFERROR(VLOOKUP(B27,#REF!,3,0),0) -> 0 | BA27: 0 | BB27: =IFERROR(VLOOKUP(B27,#REF!,3,0),0) -> 0 | BC27: =IF(E27>=0,IF(AND(E27>tabelas!$C$11,E27<=tabelas!$C$12),BB27*tabelas!$E$11,IF(AND(E27>=tabelas!$C$12,E27<=tabelas!$C$13),BB27*tabelas!$E$12,IF(AND(E27>=tabelas!$C$13,E27<=tabelas!$C$14),BB27*tabelas!$E$13,IF(AND(E27>0,E27>tabelas!$C$14),BB27*tabelas!$E$14,0))))) -> 0 | BD27: =BB27-BC27 -> 0 | BE27: =SUMIF(open_english!A:A,total!B27,open_english!C:C) -> 138.88889 | BF27: =SUMIF(open_english!A:A,total!B27,open_english!D:D) -> 96.56 | BG27: =SUMIF(open_english!A:A,total!B27,open_english!E:E) -> 42.328889 | BH27: =IFERROR(VLOOKUP(B27,gympass!$A$2:$F$527,6,0),"-") -> 166.66667 | BI27: =IFERROR(VLOOKUP(B27,#REF!,4,0),"-") -> - | BJ27: =IFERROR(VLOOKUP(B27,#REF!,3,0),0) -> 0 | BK27: =IF(E27>=0,IF(AND(E27>tabelas!$C$11,E27<=tabelas!$C$12),BJ27*tabelas!$E$11,IF(AND(E27>=tabelas!$C$12,E27<=tabelas!$C$13),BJ27*tabelas!$E$12,IF(AND(E27>=tabelas!$C$13,E27<=tabelas!$C$14),BJ27*tabelas!$E$13,IF(AND(E27>0,E27>tabelas!$C$14),BJ27*tabelas!$E$14,0))))) -> 0 | BL27: =BJ27-BK27 -> 0 | BM27: =IFERROR(INDEX(dif_sistel!L:L,MATCH(total!B27,dif_sistel!D:D,0)),0)+IFERROR(INDEX(dif_sistel!N:N,MATCH(total!B27,dif_sistel!D:D,0)),0) -> 0 | BN27: =IFERROR(VLOOKUP(B27,dif_sistel!$D$3:$X$257,21,0),0) -> 0 | BO27: =IFERROR(SUMIF(#REF!,total!B27,#REF!),"0") -> 0 | BP27: =IFERROR(SUMIF(#REF!,total!B27,#REF!),"0") -> 0
B28: 25 | C28: =VLOOKUP(B28,salario!$A$3:$C$195,2,0) -> ATIVO | D28: =VLOOKUP(B28,salario!$A$3:$C$195,3,0) -> Colaborador 25 | E28: =IFERROR(VLOOKUP(B28,salario!$A$3:$K$854,11,0), "0") -> 1102.16 | F28: =SUMIF([2]unimed!$AL:$AL,B28,[2]unimed!$AJ:$AJ) -> #VALUE! | G28: =SUMIF([2]unimed!$AL:$AL,B28,[2]unimed!$AQ:$AQ) -> #VALUE! | H28: =SUMIF([2]unimed!$AL:$AL,B28,[2]unimed!$AP:$AP) -> #VALUE! | I28: =IFERROR(VLOOKUP(B28,uniodonto!$B$3:$F$339,5,0),0) -> 84.38 | J28: =IF(E28>=0,IF(AND(E28>tabelas!$C$4,E28<=tabelas!$C$5),I28*tabelas!$E$4,IF(AND(E28>=tabelas!$C$5,E28<=tabelas!$C$6),I28*tabelas!$E$5,IF(AND(E28>=tabelas!$C$6,E28<=tabelas!$C$7),I28*tabelas!$E$6,IF(AND(E28>0,E28>tabelas!$C$7),I28*tabelas!$E$7,0))))) -> 5.9066 | K28: =I28-J28 -> 78.4734 | L28: =SUMIF(caju!$A$4:$A$562,total!B28,caju!$C$4:$C$2900) -> 500 | M28: =IF(E28>=0,IF(AND(E28>tabelas!$C$11,E28<=tabelas!$C$12),L28*tabelas!$E$11,IF(AND(E28>=tabelas!$C$12,E28<=tabelas!$C$13),L28*tabelas!$E$12,IF(AND(E28>=tabelas!$C$13,E28<=tabelas!$C$14),L28*tabelas!$E$13,IF(AND(E28>0,E28>tabelas!$C$14),L28*tabelas!$E$14,0))))) -> 10 | N28: =L28-M28 -> 490 | O28: =IFERROR(VLOOKUP(B28,segurodevida!$B$4:$E$588,4,0),0) -> 3.5214012 | P28: =O28/2 -> 1.7607006 | Q28: =O28-P28 -> 1.7607006 | V28: =IFERROR(VLOOKUP(B28,#REF!,3,0),0) -> 0 | W28: =SUMIF(#REF!,total!B28,#REF!) -> #REF! | X28: =IFERROR(VLOOKUP(B28,#REF!,4,0),0) -> 0 | Y28: =IFERROR(VLOOKUP(B28,#REF!,5,0),0) -> 0 | Z28: =IFERROR(X28-Y28,0) -> 0 | AA28: =IFERROR(VLOOKUP(B28,#REF!,3,0),0) -> 0 | AB28: =IFERROR(VLOOKUP(B28,#REF!,3,0),0) -> 0 | AC28: =IFERROR(VLOOKUP(B28,#REF!,5,0),0) -> 0 | AD28: 275 | AE28: =IFERROR(VLOOKUP(B28,#REF!,3,0),0) -> 0 | AF28: =IFERROR(VLOOKUP(B28,#REF!,3,0),0) -> 0 | AG28: =IFERROR(VLOOKUP(B28,#REF!,3,0),0) -> 0 | AK28: =IFERROR(VLOOKUP(B28,#REF!,3,0),0) -> 0 | AL28: =IFERROR(VLOOKUP(B28,ingles!$A$2:$C$673,3,0),"-") -> - | AM28: =ROUNDUP(IFERROR(AL28*39.39%,"0"),1) -> 0 | AN28: =IFERROR(AL28-AM28,"-") -> - | AO28: =SUMIFS(zenklub!I:I,zenklub!A:A,total!B28) -> 90.566667 | AP28: =SUMIF(zenklub!$A$49:$A$106,total!B28,zenklub!$I$49:$I$106) -> 23.9 | AQ28: =AO28-AP28 -> 66.666667 | AR28: =SUMIF([3]bradesco!$C:$C,B28,[3]bradesco!$M:$M) -> #VALUE! | AS28: =SUMIF([3]bradesco!$C:$C,B28,[3]bradesco!$V:$V) -> #VALUE! | AT28: =IFERROR(SUMIF([3]bradesco!$C:$C,B28,[3]bradesco!$Y:$Y),0) -> 0 | AU28: =SUMIF([4]bradesco!$C:$C,B28,[4]bradesco!$M:$M) -> #VALUE! | AV28: =SUMIF([4]bradesco!$C:$C,B28,[4]bradesco!$V:$V) -> #VALUE! | AW28: =AU28-AV28 -> #VALUE! | AX28: =IFERROR(VLOOKUP(B28,#REF!,3,0),0) -> 0 | AY28: =IFERROR(VLOOKUP(B28,#REF!,3,0),0) -> 0 | AZ28: =IFERROR(VLOOKUP(B28,#REF!,3,0),0) -> 0 | BA28: 0 | BB28: =IFERROR(VLOOKUP(B28,#REF!,3,0),0) -> 0 | BC28: =IF(E28>=0,IF(AND(E28>tabelas!$C$11,E28<=tabelas!$C$12),BB28*tabelas!$E$11,IF(AND(E28>=tabelas!$C$12,E28<=tabelas!$C$13),BB28*tabelas!$E$12,IF(AND(E28>=tabelas!$C$13,E28<=tabelas!$C$14),BB28*tabelas!$E$13,IF(AND(E28>0,E28>tabelas!$C$14),BB28*tabelas!$E$14,0))))) -> 0 | BD28: =BB28-BC28 -> 0 | BE28: =SUMIF(open_english!A:A,total!B28,open_english!C:C) -> 138.88889 | BF28: =SUMIF(open_english!A:A,total!B28,open_english!D:D) -> 96.56 | BG28: =SUMIF(open_english!A:A,total!B28,open_english!E:E) -> 42.328889 | BH28: =IFERROR(VLOOKUP(B28,gympass!$A$2:$F$527,6,0),"-") -> 166.66667 | BI28: =IFERROR(VLOOKUP(B28,#REF!,4,0),"-") -> - | BJ28: =IFERROR(VLOOKUP(B28,#REF!,3,0),0) -> 0 | BK28: =IF(E28>=0,IF(AND(E28>tabelas!$C$11,E28<=tabelas!$C$12),BJ28*tabelas!$E$11,IF(AND(E28>=tabelas!$C$12,E28<=tabelas!$C$13),BJ28*tabelas!$E$12,IF(AND(E28>=tabelas!$C$13,E28<=tabelas!$C$14),BJ28*tabelas!$E$13,IF(AND(E28>0,E28>tabelas!$C$14),BJ28*tabelas!$E$14,0))))) -> 0 | BL28: =BJ28-BK28 -> 0 | BM28: =IFERROR(INDEX(dif_sistel!L:L,MATCH(total!B28,dif_sistel!D:D,0)),0)+IFERROR(INDEX(dif_sistel!N:N,MATCH(total!B28,dif_sistel!D:D,0)),0) -> 0 | BN28: =IFERROR(VLOOKUP(B28,dif_sistel!$D$3:$X$257,21,0),0) -> 0 | BO28: =IFERROR(SUMIF(#REF!,total!B28,#REF!),"0") -> 0 | BP28: =IFERROR(SUMIF(#REF!,total!B28,#REF!),"0") -> 0
... B33: 30 | C33: =VLOOKUP(B33,salario!$A$3:$C$195,2,0) -> ATIVO | D33: =VLOOKUP(B33,salario!$A$3:$C$195,3,0) -> Colaborador 30 | E33: =IFERROR(VLOOKUP(B33,salario!$A$3:$K$854,11,0), "0") -> 7943.86 | F33: =SUMIF([2]unimed!$AL:$AL,B33,[2]unimed!$AJ:$AJ) -> #VALUE! | G33: =SUMIF([2]unimed!$AL:$AL,B33,[2]unimed!$AQ:$AQ) -> #VALUE! | H33: =SUMIF([2]unimed!$AL:$AL,B33,[2]unimed!$AP:$AP) -> #VALUE! | I33: =IFERROR(VLOOKUP(B33,uniodonto!$B$3:$F$339,5,0),0) -> 210.95 | J33: =IF(E33>=0,IF(AND(E33>tabelas!$C$4,E33<=tabelas!$C$5),I33*tabelas!$E$4,IF(AND(E33>=tabelas!$C$5,E33<=tabelas!$C$6),I33*tabelas!$E$5,IF(AND(E33>=tabelas!$C$6,E33<=tabelas!$C$7),I33*tabelas!$E$6,IF(AND(E33>0,E33>tabelas!$C$7),I33*tabelas!$E$7,0))))) -> 48.5185 | K33: =I33-J33 -> 162.4315 | L33: =SUMIF(caju!$A$4:$A$562,total!B33,caju!$C$4:$C$2900) -> 500 | M33: =IF(E33>=0,IF(AND(E33>tabelas!$C$11,E33<=tabelas!$C$12),L33*tabelas!$E$11,IF(AND(E33>=tabelas!$C$12,E33<=tabelas!$C$13),L33*tabelas!$E$12,IF(AND(E33>=tabelas!$C$13,E33<=tabelas!$C$14),L33*tabelas!$E$13,IF(AND(E33>0,E33>tabelas!$C$14),L33*tabelas!$E$14,0))))) -> 50 | N33: =L33-M33 -> 450 | O33: =IFERROR(VLOOKUP(B33,segurodevida!$B$4:$E$588,4,0),0) -> 25.380633 | P33: =O33/2 -> 12.690316 | Q33: =O33-P33 -> 12.690316 | V33: =IFERROR(VLOOKUP(B33,#REF!,3,0),0) -> 0 | W33: =SUMIF(#REF!,total!B33,#REF!) -> #REF! | X33: =IFERROR(VLOOKUP(B33,#REF!,4,0),0) -> 0 | Y33: =IFERROR(VLOOKUP(B33,#REF!,5,0),0) -> 0 | Z33: =IFERROR(X33-Y33,0) -> 0 | AA33: =IFERROR(VLOOKUP(B33,#REF!,3,0),0) -> 0 | AB33: =IFERROR(VLOOKUP(B33,#REF!,3,0),0) -> 0 | AC33: =IFERROR(VLOOKUP(B33,#REF!,5,0),0) -> 0 | AD33: 275 | AE33: =IFERROR(VLOOKUP(B33,#REF!,3,0),0) -> 0 | AF33: =IFERROR(VLOOKUP(B33,#REF!,3,0),0) -> 0 | AG33: =IFERROR(VLOOKUP(B33,#REF!,3,0),0) -> 0 | AK33: =IFERROR(VLOOKUP(B33,#REF!,3,0),0) -> 0 | AL33: =IFERROR(VLOOKUP(B33,ingles!$A$2:$C$673,3,0),"-") -> 165 | AM33: =ROUNDUP(IFERROR(AL33*39.39%,"0"),1) -> 65 | AN33: =IFERROR(AL33-AM33,"-") -> 100 | AO33: =SUMIFS(zenklub!I:I,zenklub!A:A,total!B33) -> 90.566667 | AP33: =SUMIF(zenklub!$A$49:$A$106,total!B33,zenklub!$I$49:$I$106) -> 23.9 | AQ33: =AO33-AP33 -> 66.666667 | AR33: =SUMIF([3]bradesco!$C:$C,B33,[3]bradesco!$M:$M) -> #VALUE! | AS33: =SUMIF([3]bradesco!$C:$C,B33,[3]bradesco!$V:$V) -> #VALUE! | AT33: =IFERROR(SUMIF([3]bradesco!$C:$C,B33,[3]bradesco!$Y:$Y),0) -> 0 | AU33: =SUMIF([4]bradesco!$C:$C,B33,[4]bradesco!$M:$M) -> #VALUE! | AV33: =SUMIF([4]bradesco!$C:$C,B33,[4]bradesco!$V:$V) -> #VALUE! | AW33: =AU33-AV33 -> #VALUE! | AX33: =IFERROR(VLOOKUP(B33,#REF!,3,0),0) -> 0 | AY33: =IFERROR(VLOOKUP(B33,#REF!,3,0),0) -> 0 | AZ33: =IFERROR(VLOOKUP(B33,#REF!,3,0),0) -> 0 | BA33: 0 | BB33: =IFERROR(VLOOKUP(B33,#REF!,3,0),0) -> 0 | BC33: =IF(E33>=0,IF(AND(E33>tabelas!$C$11,E33<=tabelas!$C$12),BB33*tabelas!$E$11,IF(AND(E33>=tabelas!$C$12,E33<=tabelas!$C$13),BB33*tabelas!$E$12,IF(AND(E33>=tabelas!$C$13,E33<=tabelas!$C$14),BB33*tabelas!$E$13,IF(AND(E33>0,E33>tabelas!$C$14),BB33*tabelas!$E$14,0))))) -> 0 | BD33: =BB33-BC33 -> 0 | BE33: =SUMIF(open_english!A:A,total!B33,open_english!C:C) -> 138.88889 | BF33: =SUMIF(open_english!A:A,total!B33,open_english!D:D) -> 96.56 | BG33: =SUMIF(open_english!A:A,total!B33,open_english!E:E) -> 42.328889 | BH33: =IFERROR(VLOOKUP(B33,gympass!$A$2:$F$527,6,0),"-") -> 166.66667 | BI33: =IFERROR(VLOOKUP(B33,#REF!,4,0),"-") -> - | BJ33: =IFERROR(VLOOKUP(B33,#REF!,3,0),0) -> 0 | BK33: =IF(E33>=0,IF(AND(E33>tabelas!$C$11,E33<=tabelas!$C$12),BJ33*tabelas!$E$11,IF(AND(E33>=tabelas!$C$12,E33<=tabelas!$C$13),BJ33*tabelas!$E$12,IF(AND(E33>=tabelas!$C$13,E33<=tabelas!$C$14),BJ33*tabelas!$E$13,IF(AND(E33>0,E33>tabelas!$C$14),BJ33*tabelas!$E$14,0))))) -> 0 | BL33: =BJ33-BK33 -> 0 | BM33: =IFERROR(INDEX(dif_sistel!L:L,MATCH(total!B33,dif_sistel!D:D,0)),0)+IFERROR(INDEX(dif_sistel!N:N,MATCH(total!B33,dif_sistel!D:D,0)),0) -> 0 | BN33: =IFERROR(VLOOKUP(B33,dif_sistel!$D$3:$X$257,21,0),0) -> 0 | BO33: =IFERROR(SUMIF(#REF!,total!B33,#REF!),"0") -> 0 | BP33: =IFERROR(SUMIF(#REF!,total!B33,#REF!),"0") -> 0
D34: TOTAL | E34: =SUM(E4:E33) -> 146612.78 | F34: =SUM(F4:F33) -> #VALUE! | G34: =SUM(G4:G33) -> #VALUE! | H34: =SUM(H4:H33) -> #VALUE! | I34: =SUM(I4:I33) -> 4514.33 | J34: =SUM(J4:J33) -> 640.0223 | K34: =SUM(K4:K33) -> 3874.3077 | L34: =SUM(L4:L33) -> 15150 | ... BP34: =SUM(BP4:BP33) -> 0

Sheet salario
K1: =SUBTOTAL(9,K3:K275) -> 146612.78
A2: Mat | B2: Status | C2: Nome | D2: Nascimento | E2: Step | F2: RG | G2: CPF | H2: Carga Horária | I2: Tipo | J2: Data de Admissão | K2: Salário | L2: Cargo | M2: Função | N2: Nível | O2: Data de Demissão | P2: Pedido de Demissão
A3: 1 | B3: ATIVO | C3: Colaborador 1 | D3: 28746 | E3: 0 | F3: 0 | G3: 0 | H3: 40 | I3: CLT | J3: 46023 | K3: 5826.03 | L3: Cargo | M3: Função | N3: Nível | Q3: =A3 -> 1
A4: 2 | B4: ATIVO | C4: Colaborador 2 | D4: 27499 | E4: 0 | F4: 0 | G4: 0 | H4: 40 | I4: CLT | J4: 46023 | K4: 4332.22 | L4: Cargo | M4: Função | N4: Nível | Q4: =A4 -> 2
A5: 3 | B5: ATIVO | C5: Colaborador 3 | D5: 28584 | E5: 0 | F5: 0 | G5: 0 | H5: 40 | I5: CLT | J5: 46023 | K5: 4714.12 | L5: Cargo | M5: Função | N5: Nível | Q5: =A5 -> 3
A6: 4 | B6: ATIVO | C6: Colaborador 4 | D6: 29369 | E6: 0 | F6: 0 | G6: 0 | H6: 40 | I6: CLT | J6: 46023 | K6: 7685.13 | L6: Cargo | M6: Função | N6: Nível | Q6: =A6 -> 4
A7: 5 | B7: ATIVO | C7: Colaborador 5 | D7: 28648 | E7: 0 | F7: 0 | G7: 0 | H7: 40 | I7: CLT | J7: 46023 | K7: 3652.6 | L7: Cargo | M7: Função | N7: Nível | Q7: =A7 -> 5
A8: 6 | B8: ATIVO | C8: Colaborador 6 | D8: 28318 | E8: 0 | F8: 0 | G8: 0 | H8: 40 | I8: CLT | J8: 46023 | K8: 7943.86 | L8: Cargo | M8: Função | N8: Nível | Q8: =A8 -> 6
A9: 7 | B9: ATIVO | C9: Colaborador 7 | D9: 28754 | E9: 0 | F9: 0 | G9: 0 | H9: 40 | I9: CLT | J9: 46023 | K9: 7131.14 | L9: Cargo | M9: Função | N9: Nível | Q9: =A9 -> 7
A10: 8 | B10: ATIVO | C10: Colaborador 8 | D10: 29935 | E10: 0 | F10: 0 | G10: 0 | H10: 40 | I10: CLT | J10: 46023 | K10: 5245.5 | L10: Cargo | M10: Função | N10: Nível | Q10: =A10 -> 8
A11: 9 | B11: ATIVO | C11: Colaborador 9 | D11: 30813 | E11: 0 | F11: 0 | G11: 0 | H11: 40 | I11: CLT | J11: 46023 | K11: 4229.32 | L11: Cargo | M11: Função | N11: Nível | Q11: =A11 -> 9
A12: 10 | B12: ATIVO | C12: Colaborador 10 | D12: 28678 | E12: 0 | F12: 0 | G12: 0 | H12: 40 | I12: CLT | J12: 46023 | K12: 2404.84 | L12: Cargo | M12: Função | N12: Nível | Q12: =A12 -> 10
A13: 11 | B13: ATIVO | C13: Colaborador 11 | D13: 30176 | E13: 0 | F13: 0 | G13: 0 | H13: 40 | I13: CLT | J13: 46023 | K13: 2335.03 | L13: Cargo | M13: Função | N13: Nível | Q13: =A13 -> 11
A14: 12 | B14: ATIVO | C14: Colaborador 12 | D14: 31990 | E14: 0 | F14: 0 | G14: 0 | H14: 40 | I14: CLT | J14: 46023 | K14: 3290.79 | L14: Cargo | M14: Função | N14: Nível | Q14: =A14 -> 12
... A32: 30 | B32: ATIVO | C32: Colaborador 30 | D32: 28413 | E32: 0 | F32: 0 | G32: 0 | H32: 40 | I32: CLT | J32: 46023 | K32: 7943.86 | L32: Cargo | M32: Função | N32: Nível | Q32: =A32 -> 30

Sheet rs_nova
H1: =16665.66+407.9 -> 17073.56 | I1: -287.5 | J1: =10188.05+532.89 -> 10720.94 | K1: =4940.42+6266.72 -> 11207.14 | L1: 4266.94 | M1: 421.79 | N1: =6521.67+1465.26 -> 7986.93 | O1: =SUM(H1:N1) -> 51389.8 | P1: =total!AB1 -> 0 | Q1: =172822+3910 -> 176732 | U1: =total!AG1 -> 0 | W1: =9675+400 -> 10075 | Y1: =#REF! -> #REF! | AA1: =total!AT1 -> 0 | AB1: =total!AW1 -> #VALUE! | AC1: =total!T1 -> 0 | AD1: =total!K1 -> 3874.3077 | AE1: =total!N1-8030 -> 6315 | AF1: =total!Q1 -> 234.21392 | AG1: =total!AJ1+total!H1 -> #VALUE! | AH1: =152260+2300 -> 154560 | AK1: 1280149.9 | AL1: 51875.47 | AM1: 382347.48
A2: Referência | B2: 45017 | H2: 133 | I2: 134 | J2: 60 | K2: 116 | L2: 61 | M2: 117 | N2: 49 | P2: 2150 | BF2: 11 | BG2: 8 | BH2: 55 | BI2: 99 | BJ2: 110 | BL2: 114 | BM2: 208
A3: Total | B3: =COUNTIF(A6:A1000,"<>0") -> 825 | G3: =SUBTOTAL(9,G6:G716) -> 146612.78 | H3: =SUBTOTAL(9,H6:H1000) -> 0 | I3: =SUBTOTAL(9,I6:I1000) -> 0 | J3: =SUBTOTAL(9,J6:J1000) -> 0 | K3: =SUBTOTAL(9,K6:K1000) -> 0 | L3: =SUBTOTAL(9,L6:L1000) -> 0 | M3: =SUBTOTAL(9,M6:M1000) -> 0 | N3: =SUBTOTAL(9,N6:N1000) -> 0 | O3: =SUBTOTAL(9,O6:O1000) -> 0 | ... BA3: =SUBTOTAL(9,BA6:BA1000) -> #REF! | BB3: 160 | BF3: =SUBTOTAL(9,BF6:BF1000) -> 46742 | BG3: =SUBTOTAL(9,BG6:BG1000) -> 0 | BH3: =SUBTOTAL(9,BH6:BH1000) -> 0 | BI3: =SUBTOTAL(9,BI6:BI1000) -> 0 | BJ3: =SUBTOTAL(9,BJ6:BJ1000) -> 0 | BK3: =SUBTOTAL(9,BK6:BK1000) -> 0 | BL3: =SUBTOTAL(9,BL6:BL1000) -> 0 | BM3: =SUBTOTAL(9,BM6:BM1000) -> 0 | BN3: =SUBTOTAL(9,BN6:BN1000) -> 46742
A4: Matricula | B4: Dias Trabalhados | C4: Nome | D4: Admissão | E4: Demissão | F4: Demissão Volutária? | G4: Salário Mês | H4: Sobre Aviso | I4: Horas Banco desconto | J4: Hora Extra 50 | K4: Hora Extra 50 Banco | L4: Hora Extra 100 | M4: Hora Extra Noturno | N4: DSR | O4: Total Hora Extra | P4: Gratificação | Q4: Auxilio Creche | R4: Vale Transporte | S4: Gympass | T4: Zenklub | U4: Indicação Premiada | V4: Pós Graduação | W4: Gratificação ASCAN | X4: Academy | Y4: Agiel | Z4: Diaria de Viagem | AA4: Bradesco Saúde | AB4: Bradesco Dental | AC4: Sistel | AD4: Odonto | AE4: Refeicao | AF4: Seguro de Vida | AG4: Saude | AH4: Auxilio HO | AI4: Auxilio Ingles | AJ4: Total Beneficios | AK4: INSS | AL4: PIS | AM4: FGTS | AN4: Aviso Prévio | AO4: Multa FGTS 50% | AP4: Capacitação e inovação | AQ4: 13º Salário | AR4: INSS S/ 13o | AS4: FGTS S/ 13o | AT4: Férias | AU4: INSS S/ Férias | AV4: FGTS S/ Férias | AW4: - | AX4: Total Encargos | AY4: Total Provisionamentos | AZ4: Custo Total sem Prov. | BA4: Custo Total Com Prov. | BB4: Sal | BC4: Enc. | BD4: Ben. | BE4: Salário Bruto | BF4: Salário Base | BG4: Salário Maternidade | BH4: Salário Licenca | BI4: Complemento de Folha | BJ4: Base Férias | BK4: Base Férias Mês Anterior | BL4: Complemento de Férias | BM4: 13o | BN4: Base de Calculo
AK5: 0.268 | AL5: 0.01 | AM5: 0.08 | AN5: 0.0833 | AO5: 0.04 | AP5: 0.035 | AQ5: 0.083333333 | AR5: 0.022333333 | AS5: 0.0066666667 | AT5: 0.083333333 | AU5: 0.022333333 | AV5: 0.0066666667
A6: =total!B4 -> 1 | B6: =IFERROR(IF(E6="",IF(D6<=B$2,30,31-DAY(D6)),IF(E6<B$2,0,IF(D6>=B$2,DAY(E6)-DAY(D6),DAY(E6)))),0) -> 30 | C6: =total!D4 -> Colaborador 1 | D6: =IFERROR(VLOOKUP(A6,salario!A$3:J$32,10,FALSE),"") -> 46023 | E6: =IFERROR(IF(VLOOKUP(A6,salario!A$3:O$32,15,FALSE)="","",VLOOKUP(A6,salario!A$3:O$32,15,FALSE)),"") | F6: =IFERROR(VLOOKUP(A6,[5]base_pessoal!$B$2:$P$1504,13,FALSE),"") | G6: =IFERROR(VLOOKUP(A6,salario!A$2:P$91,11,FALSE),0)*B6/30 -> 5826.03 | H6: =SUMIFS(topmanager!$D:$D,topmanager!$C:$C,rs_nova!$A6,topmanager!$A:$A,rs_nova!H$2)+SUMIFS(topmanager!$D:$D,topmanager!$C:$C,rs_nova!$A6,topmanager!$A:$A,63) -> 0 | I6: =-SUMIFS(topmanager!$D:$D,topmanager!$C:$C,rs_nova!$A6,topmanager!$A:$A,rs_nova!I$2) -> 0 | J6: =SUMIFS(topmanager!$D:$D,topmanager!$C:$C,rs_nova!$A6,topmanager!$A:$A,rs_nova!J$2) -> 0 | K6: =SUMIFS(topmanager!$D:$D,topmanager!$C:$C,rs_nova!$A6,topmanager!$A:$A,rs_nova!K$2)+SUMIFS(topmanager!$D:$D,topmanager!$C:$C,rs_nova!$A6,topmanager!$A:$A,911) -> 0 | L6: =SUMIFS(topmanager!$D:$D,topmanager!$C:$C,rs_nova!$A6,topmanager!$A:$A,rs_nova!L$2) -> 0 | M6: =SUMIFS(topmanager!$D:$D,topmanager!$C:$C,rs_nova!$A6,topmanager!$A:$A,rs_nova!M$2)+SUMIFS(topmanager!$D:$D,topmanager!$C:$C,rs_nova!$A6,topmanager!$A:$A,908)+SUMIFS(topmanager!$D:$D,topmanager!$C:$C,rs_nova!$A6,topmanager!$A:$A,550) -> 0 | N6: =SUMIFS(topmanager!$D:$D,topmanager!$C:$C,rs_nova!$A6,topmanager!$A:$A,rs_nova!N$2) -> 0 | O6: =SUM(H6:N6) -> 0 | P6: =IFERROR(VLOOKUP($A6,total!$B$4:$AW$437,27,0),0) -> 0 | Q6: =IFERROR(VLOOKUP($A6,total!$B$4:$AW$437,21,0),0) -> 0 | R6: =IFERROR(VLOOKUP($A6,total!$B$4:$AW$437,25,0),0)+IFERROR(VLOOKUP($A6,total!$B$4:$AW$437,36,0),0) -> 0 | S6: =IFERROR(VLOOKUP(A6,gympass!$A$2:$F$148,6,0),0) -> 166.66667 | T6: =IFERROR(VLOOKUP($A6,total!$B$4:$AW$437,42,0),0) -> 66.666667 | U6: =IFERROR(VLOOKUP($A6,total!$B$4:$AW$437,32,0),0) -> 0 | V6: =IFERROR(VLOOKUP($A6,total!$B$4:$AW$437,28,0),0) -> 0 | W6: =IFERROR(VLOOKUP($A6,total!$B$4:$AX$437,49,0),0) -> 0 | Y6: =IFERROR(VLOOKUP(A6,#REF!,4,0),0) -> 0 | Z6: =IFERROR(VLOOKUP(B6,#REF!,8,0),0) -> 0 | AA6: =IFERROR(VLOOKUP($A6,total!$B$4:$AW$437,45,0),0) -> 0 | AB6: =IFERROR(VLOOKUP($A6,total!$B$4:$AW$437,48,0),0) -> 0 | AC6: =IFERROR(VLOOKUP($A6,total!$B$4:$AB$437,19,0),0) -> 0 | AD6: =IFERROR(VLOOKUP($A6,total!$B$4:$AB$437,10,0),0) -> 71.723 | AE6: =IFERROR(VLOOKUP($A6,total!$B$4:$AB$437,13,0),0)-SUMIFS(topmanager!$D:$D,topmanager!$C:$C,rs_nova!$A10,topmanager!$A:$A,856) -> 470 | AF6: =IFERROR(VLOOKUP($A6,total!$B$4:$AB$437,16,0),0) -> 9.3070829 | AG6: =IFERROR(VLOOKUP($A6,total!$B$4:$AB$437,7,0),0) -> 0 | AH6: =IFERROR(VLOOKUP($A6,total!$B$4:$AD$437,29,0),0) -> 275 | AI6: =IFERROR(VLOOKUP(A6,total!$B$4:$AN$437,39,0),0) -> 100 | AJ6: =SUM(P6:AI6) -> 1159.3634 | AK6: =AK$5*($BN6-BG6) -> 0 | AL6: =AL$5*($BN6+BJ6+BK6+BL6+BM6) -> 0 | AM6: =IF(F6="NÃO",0,AM$5*$BN6) -> 0 | AN6: =IF(AND($A6>1000,$A6<=1999),0,AN$5*$G6) -> 485.3083 | AO6: =IF(AND($A6>1000,$A6<=1999),0,AO$5*$G6) -> 233.0412 | AP6: =IF(AND($A6>1000,$A6<=1999),0,AP$5*$G6) -> 203.91105 | AQ6: =IFERROR(VLOOKUP(TEXT($A6,"000000"),[6]Página1!$A$8:$S$801,13,FALSE),0) -> 0 | AR6: =IFERROR(VLOOKUP(TEXT($A6,"000000"),[6]Página1!$A$8:$S$801,16,FALSE),0) -> 0 | AS6: =IFERROR(VLOOKUP(TEXT($A6,"000000"),[6]Página1!$A$8:$S$801,19,FALSE),0) -> 0 | AT6: =IFERROR(VLOOKUP(TEXT($A6,"000000"),[7]Página1!$A$8:$R$814,12,FALSE),0) -> 0 | AU6: =IFERROR(VLOOKUP(TEXT($A6,"000000"),[7]Página1!$A$8:$R$814,15,FALSE),0) -> 0 | AV6: =IFERROR(VLOOKUP(TEXT($A6,"000000"),[7]Página1!$A$8:$R$814,18,FALSE),0) -> 0 | AX6: =SUM(AK6:AW6) -> 922.26055 | AY6: =AN6+AO6+AP6 -> 922.26055 | AZ6: =AX6+AJ6+O6+G6-AY6 -> 6985.3934 | BA6: =AX6+AJ6+O6+G6 -> 7907.654 | BB6: =($G6)/$BB$3 -> 36.412687 | BC6: =$AX6/$BB$3 -> 5.7641284 | BD6: =$AJ6/$BB$3 -> 7.2460214 | BE6: =IFERROR(VLOOKUP(A6,salario!A$2:P$91,11,FALSE),0) -> 5826.03 | BF6: =SUMIFS(topmanager!$D:$D,topmanager!$C:$C,rs_nova!$A6,topmanager!$A:$A,rs_nova!BF$2) -> 0 | BG6: =SUMIFS(topmanager!$D:$D,topmanager!$C:$C,rs_nova!$A6,topmanager!$A:$A,rs_nova!BG$2) -> 0 | BH6: =SUMIFS(topmanager!$D:$D,topmanager!$C:$C,rs_nova!$A6,topmanager!$A:$A,rs_nova!BH$2) -> 0 | BI6: =SUMIFS(topmanager!$D:$D,topmanager!$C:$C,rs_nova!$A6,topmanager!$A:$A,rs_nova!BI$2) -> 0 | BJ6: =SUMIFS(topmanager!$D:$D,topmanager!$C:$C,rs_nova!$A6,topmanager!$A:$A,rs_nova!BJ$2)+SUMIFS(topmanager!$D:$D,topmanager!$C:$C,rs_nova!$A6,topmanager!$A:$A,rs_nova!BJ$2+1) -> 0 | BK6: =IFERROR(VLOOKUP(A6,[8]ferias!$C$4:$G$100,5,FALSE),0) -> 0 | BL6: =SUMIFS(topmanager!$D:$D,topmanager!$C:$C,rs_nova!$A6,topmanager!$A:$A,rs_nova!BL$2) -> 0 | BM6: =SUMIFS(topmanager!$D:$D,topmanager!$C:$C,rs_nova!$A6,topmanager!$A:$A,rs_nova!BM$2)+SUMIFS(topmanager!$D:$D,topmanager!$C:$C,rs_nova!$A10,topmanager!$A:$A,151) -> 0 | BN6: =BF6+BG6+BH6+BI6+P6+O6+W6 -> 0
A7: =total!B5 -> 2 | B7: =IFERROR(IF(E7="",IF(D7<=B$2,30,31-DAY(D7)),IF(E7<B$2,0,IF(D7>=B$2,DAY(E7)-DAY(D7),DAY(E7)))),0) -> 30 | C7: =total!D5 -> Colaborador 2 | D7: =IFERROR(VLOOKUP(A7,salario!A$3:J$32,10,FALSE),"") -> 46023 | E7: =IFERROR(IF(VLOOKUP(A7,salario!A$3:O$32,15,FALSE)="","",VLOOKUP(A7,salario!A$3:O$32,15,FALSE)),"") | F7: =IFERROR(VLOOKUP(A7,[5]base_pessoal!$B$2:$P$1504,13,FALSE),"") | G7: =IFERROR(VLOOKUP(A7,salario!A$2:P$91,11,FALSE),0)*B7/30 -> 4332.22 | H7: =SUMIFS(topmanager!$D:$D,topmanager!$C:$C,rs_nova!$A7,topmanager!$A:$A,rs_nova!H$2)+SUMIFS(topmanager!$D:$D,topmanager!$C:$C,rs_nova!$A7,topmanager!$A:$A,63) -> 0 | I7: =-SUMIFS(topmanager!$D:$D,topmanager!$C:$C,rs_nova!$A7,topmanager!$A:$A,rs_nova!I$2) -> 0 | J7: =SUMIFS(topmanager!$D:$D,topmanager!$C:$C,rs_nova!$A7,topmanager!$A:$A,rs_nova!J$2) -> 0 | K7: =SUMIFS(topmanager!$D:$D,topmanager!$C:$C,rs_nova!$A7,topmanager!$A:$A,rs_nova!K$2)+SUMIFS(topmanager!$D:$D,topmanager!$C:$C,rs_nova!$A7,topmanager!$A:$A,911) -> 0 | L7: =SUMIFS(topmanager!$D:$D,topmanager!$C:$C,rs_nova!$A7,topmanager!$A:$A,rs_nova!L$2) -> 0 | M7: =SUMIFS(topmanager!$D:$D,topmanager!$C:$C,rs_nova!$A7,topmanager!$A:$A,rs_nova!M$2)+SUMIFS(topmanager!$D:$D,topmanager!$C:$C,rs_nova!$A7,topmanager!$A:$A,908)+SUMIFS(topmanager!$D:$D,topmanager!$C:$C,rs_nova!$A7,topmanager!$A:$A,550) -> 0 | N7: =SUMIFS(topmanager!$D:$D,topmanager!$C:$C,rs_nova!$A7,topmanager!$A:$A,rs_nova!N$2) -> 0 | O7: =SUM(H7:N7) -> 0 | P7: =IFERROR(VLOOKUP($A7,total!$B$4:$AW$437,27,0),0) -> 0 | Q7: =IFERROR(VLOOKUP($A7,total!$B$4:$AW$437,21,0),0) -> 0 | R7: =IFERROR(VLOOKUP($A7,total!$B$4:$AW$437,25,0),0)+IFERROR(VLOOKUP($A7,total!$B$4:$AW$437,36,0),0) -> 0 | S7: =IFERROR(VLOOKUP(A7,gympass!$A$2:$F$148,6,0),0) -> 166.66667 | T7: =IFERROR(VLOOKUP($A7,total!$B$4:$AW$437,42,0),0) -> 66.666667 | U7: =IFERROR(VLOOKUP($A7,total!$B$4:$AW$437,32,0),0) -> 0 | V7: =IFERROR(VLOOKUP($A7,total!$B$4:$AW$437,28,0),0) -> 0 | W7: =IFERROR(VLOOKUP($A7,total!$B$4:$AX$437,49,0),0) -> 0 | Y7: =IFERROR(VLOOKUP(A7,#REF!,4,0),0) -> 0 | Z7: =IFERROR(VLOOKUP(B7,#REF!,8,0),0) -> 0 | AA7: =IFERROR(VLOOKUP($A7,total!$B$4:$AW$437,45,0),0) -> 0 | AB7: =IFERROR(VLOOKUP($A7,total!$B$4:$AW$437,48,0),0) -> 0 | AC7: =IFERROR(VLOOKUP($A7,total!$B$4:$AB$437,19,0),0) -> 0 | AD7: =IFERROR(VLOOKUP($A7,total!$B$4:$AB$437,10,0),0) -> 179.3075 | AE7: =IFERROR(VLOOKUP($A7,total!$B$4:$AB$437,13,0),0)-SUMIFS(topmanager!$D:$D,topmanager!$C:$C,rs_nova!$A11,topmanager!$A:$A,856) -> 470 | AF7: =IFERROR(VLOOKUP($A7,total!$B$4:$AB$437,16,0),0) -> 6.9207215 | AG7: =IFERROR(VLOOKUP($A7,total!$B$4:$AB$437,7,0),0) -> 0 | AH7: =IFERROR(VLOOKUP($A7,total!$B$4:$AD$437,29,0),0) -> 275 | AI7: =IFERROR(VLOOKUP(A7,total!$B$4:$AN$437,39,0),0) -> 100 | AJ7: =SUM(P7:AI7) -> 1264.5616 | AK7: =AK$5*($BN7-BG7) -> 0 | AL7: =AL$5*($BN7+BJ7+BK7+BL7+BM7) -> 0 | AM7: =IF(F7="NÃO",0,AM$5*$BN7) -> 0 | AN7: =IF(AND($A7>1000,$A7<=1999),0,AN$5*$G7) -> 360.87393 | AO7: =IF(AND($A7>1000,$A7<=1999),0,AO$5*$G7) -> 173.2888 | AP7: =IF(AND($A7>1000,$A7<=1999),0,AP$5*$G7) -> 151.6277 | AQ7: =IFERROR(VLOOKUP(TEXT($A7,"000000"),[6]Página1!$A$8:$S$801,13,FALSE),0) -> 0 | AR7: =IFERROR(VLOOKUP(TEXT($A7,"000000"),[6]Página1!$A$8:$S$801,16,FALSE),0) -> 0 | AS7: =IFERROR(VLOOKUP(TEXT($A7,"000000"),[6]Página1!$A$8:$S$801,19,FALSE),0) -> 0 | AT7: =IFERROR(VLOOKUP(TEXT($A7,"000000"),[7]Página1!$A$8:$R$814,12,FALSE),0) -> 0 | AU7: =IFERROR(VLOOKUP(TEXT($A7,"000000"),[7]Página1!$A$8:$R$814,15,FALSE),0) -> 0 | AV7: =IFERROR(VLOOKUP(TEXT($A7,"000000"),[7]Página1!$A$8:$R$814,18,FALSE),0) -> 0 | AX7: =SUM(AK7:AW7) -> 685.79043 | AY7: =AN7+AO7+AP7 -> 685.79043 | AZ7: =AX7+AJ7+O7+G7-AY7 -> 5596.7816 | BA7: =AX7+AJ7+O7+G7 -> 6282.572 | BB7: =($G7)/$BB$3 -> 27.076375 | BC7: =$AX7/$BB$3 -> 4.2861902 | BD7: =$AJ7/$BB$3 -> 7.9035097 | BE7: =IFERROR(VLOOKUP(A7,salario!A$2:P$91,11,FALSE),0) -> 4332.22 | BF7: =SUMIFS(topmanager!$D:$D,topmanager!$C:$C,rs_nova!$A7,topmanager!$A:$A,rs_nova!BF$2) -> 0 | BG7: =SUMIFS(topmanager!$D:$D,topmanager!$C:$C,rs_nova!$A7,topmanager!$A:$A,rs_nova!BG$2) -> 0 | BH7: =SUMIFS(topmanager!$D:$D,topmanager!$C:$C,rs_nova!$A7,topmanager!$A:$A,rs_nova!BH$2) -> 0 | BI7: =SUMIFS(topmanager!$D:$D,topmanager!$C:$C,rs_nova!$A7,topmanager!$A:$A,rs_nova!BI$2) -> 0 | BJ7: =SUMIFS(topmanager!$D:$D,topmanager!$C:$C,rs_nova!$A7,topmanager!$A:$A,rs_nova!BJ$2)+SUMIFS(topmanager!$D:$D,topmanager!$C:$C,rs_nova!$A7,topmanager!$A:$A,rs_nova!BJ$2+1) -> 0 | BK7: =IFERROR(VLOOKUP(A7,[8]ferias!$C$4:$G$100,5,FALSE),0) -> 0 | BL7: =SUMIFS(topmanager!$D:$D,topmanager!$C:$C,rs_nova!$A7,topmanager!$A:$A,rs_nova!BL$2) -> 0 | BM7: =SUMIFS(topmanager!$D:$D,topmanager!$C:$C,rs_nova!$A7,topmanager!$A:$A,rs_nova!BM$2)+SUMIFS(topmanager!$D:$D,topmanager!$C:$C,rs_nova!$A11,topmanager!$A:$A,151) -> 0 | BN7: =BF7+BG7+BH7+BI7+P7+O7+W7 -> 0
A8: =total!B6 -> 3 | B8: =IFERROR(IF(E8="",IF(D8<=B$2,30,31-DAY(D8)),IF(E8<B$2,0,IF(D8>=B$2,DAY(E8)-DAY(D8),DAY(E8)))),0) -> 30 | C8: =total!D6 -> Colaborador 3 | D8: =IFERROR(VLOOKUP(A8,salario!A$3:J$32,10,FALSE),"") -> 46023 | E8: =IFERROR(IF(VLOOKUP(A8,salario!A$3:O$32,15,FALSE)="","",VLOOKUP(A8,salario!A$3:O$32,15,FALSE)),"") | F8: =IFERROR(VLOOKUP(A8,[5]base_pessoal!$B$2:$P$1504,13,FALSE),"") | G8: =IFERROR(VLOOKUP(A8,salario!A$2:P$91,11,FALSE),0)*B8/30 -> 4714.12 | H8: =SUMIFS(topmanager!$D:$D,topmanager!$C:$C,rs_nova!$A8,topmanager!$A:$A,rs_nova!H$2)+SUMIFS(topmanager!$D:$D,topmanager!$C:$C,rs_nova!$A8,topmanager!$A:$A,63) -> 0 | I8: =-SUMIFS(topmanager!$D:$D,topmanager!$C:$C,rs_nova!$A8,topmanager!$A:$A,rs_nova!I$2) -> 0 | J8: =SUMIFS(topmanager!$D:$D,topmanager!$C:$C,rs_nova!$A8,topmanager!$A:$A,rs_nova!J$2) -> 0 | K8: =SUMIFS(topmanager!$D:$D,topmanager!$C:$C,rs_nova!$A8,topmanager!$A:$A,rs_nova!K$2)+SUMIFS(topmanager!$D:$D,topmanager!$C:$C,rs_nova!$A8,topmanager!$A:$A,911) -> 0 | L8: =SUMIFS(topmanager!$D:$D,topmanager!$C:$C,rs_nova!$A8,topmanager!$A:$A,rs_nova!L$2) -> 0 | M8: =SUMIFS(topmanager!$D:$D,topmanager!$C:$C,rs_nova!$A8,topmanager!$A:$A,rs_nova!M$2)+SUMIFS(topmanager!$D:$D,topmanager!$C:$C,rs_nova!$A8,topmanager!$A:$A,908)+SUMIFS(topmanager!$D:$D,topmanager!$C:$C,rs_nova!$A8,topmanager!$A:$A,550) -> 0 | N8: =SUMIFS(topmanager!$D:$D,topmanager!$C:$C,rs_nova!$A8,topmanager!$A:$A,rs_nova!N$2) -> 0 | O8: =SUM(H8:N8) -> 0 | P8: =IFERROR(VLOOKUP($A8,total!$B$4:$AW$437,27,0),0) -> 0 | Q8: =IFERROR(VLOOKUP($A8,total!$B$4:$AW$437,21,0),0) -> 0 | R8: =IFERROR(VLOOKUP($A8,total!$B$4:$AW$437,25,0),0)+IFERROR(VLOOKUP($A8,total!$B$4:$AW$437,36,0),0) -> 0 | S8: =IFERROR(VLOOKUP(A8,gympass!$A$2:$F$148,6,0),0) -> 166.66667 | T8: =IFERROR(VLOOKUP($A8,total!$B$4:$AW$437,42,0),0) -> 66.666667 | U8: =IFERROR(VLOOKUP($A8,total!$B$4:$AW$437,32,0),0) -> 0 | V8: =IFERROR(VLOOKUP($A8,total!$B$4:$AW$437,28,0),0) -> 0 | W8: =IFERROR(VLOOKUP($A8,total!$B$4:$AX$437,49,0),0) -> 0 | Y8: =IFERROR(VLOOKUP(A8,#REF!,4,0),0) -> 0 | Z8: =IFERROR(VLOOKUP(B8,#REF!,8,0),0) -> 0 | AA8: =IFERROR(VLOOKUP($A8,total!$B$4:$AW$437,45,0),0) -> 0 | AB8: =IFERROR(VLOOKUP($A8,total!$B$4:$AW$437,48,0),0) -> 0 | AC8: =IFERROR(VLOOKUP($A8,total!$B$4:$AB$437,19,0),0) -> 0 | AD8: =IFERROR(VLOOKUP($A8,total!$B$4:$AB$437,10,0),0) -> 215.169 | AE8: =IFERROR(VLOOKUP($A8,total!$B$4:$AB$437,13,0),0)-SUMIFS(topmanager!$D:$D,topmanager!$C:$C,rs_nova!$A12,topmanager!$A:$A,856) -> 470 | AF8: =IFERROR(VLOOKUP($A8,total!$B$4:$AB$437,16,0),0) -> 7.5308067 | AG8: =IFERROR(VLOOKUP($A8,total!$B$4:$AB$437,7,0),0) -> 0 | AH8: =IFERROR(VLOOKUP($A8,total!$B$4:$AD$437,29,0),0) -> 275 | AI8: =IFERROR(VLOOKUP(A8,total!$B$4:$AN$437,39,0),0) -> 100 | AJ8: =SUM(P8:AI8) -> 1301.0331 | AK8: =AK$5*($BN8-BG8) -> 0 | AL8: =AL$5*($BN8+BJ8+BK8+BL8+BM8) -> 0 | AM8: =IF(F8="NÃO",0,AM$5*$BN8) -> 0 | AN8: =IF(AND($A8>1000,$A8<=1999),0,AN$5*$G8) -> 392.6862 | AO8: =IF(AND($A8>1000,$A8<=1999),0,AO$5*$G8) -> 188.5648 | AP8: =IF(AND($A8>1000,$A8<=1999),0,AP$5*$G8) -> 164.9942 | AQ8: =IFERROR(VLOOKUP(TEXT($A8,"000000"),[6]Página1!$A$8:$S$801,13,FALSE),0) -> 0 | AR8: =IFERROR(VLOOKUP(TEXT($A8,"000000"),[6]Página1!$A$8:$S$801,16,FALSE),0) -> 0 | AS8: =IFERROR(VLOOKUP(TEXT($A8,"000000"),[6]Página1!$A$8:$S$801,19,FALSE),0) -> 0 | AT8: =IFERROR(VLOOKUP(TEXT($A8,"000000"),[7]Página1!$A$8:$R$814,12,FALSE),0) -> 0 | AU8: =IFERROR(VLOOKUP(TEXT($A8,"000000"),[7]Página1!$A$8:$R$814,15,FALSE),0) -> 0 | AV8: =IFERROR(VLOOKUP(TEXT($A8,"000000"),[7]Página1!$A$8:$R$814,18,FALSE),0) -> 0 | AX8: =SUM(AK8:AW8) -> 746.2452 | AY8: =AN8+AO8+AP8 -> 746.2452 | AZ8: =AX8+AJ8+O8+G8-AY8 -> 6015.1531 | BA8: =AX8+AJ8+O8+G8 -> 6761.3983 | BB8: =($G8)/$BB$3 -> 29.46325 | BC8: =$AX8/$BB$3 -> 4.6640325 | BD8: =$AJ8/$BB$3 -> 8.1314571 | BE8: =IFERROR(VLOOKUP(A8,salario!A$2:P$91,11,FALSE),0) -> 4714.12 | BF8: =SUMIFS(topmanager!$D:$D,topmanager!$C:$C,rs_nova!$A8,topmanager!$A:$A,rs_nova!BF$2) -> 0 | BG8: =SUMIFS(topmanager!$D:$D,topmanager!$C:$C,rs_nova!$A8,topmanager!$A:$A,rs_nova!BG$2) -> 0 | BH8: =SUMIFS(topmanager!$D:$D,topmanager!$C:$C,rs_nova!$A8,topmanager!$A:$A,rs_nova!BH$2) -> 0 | BI8: =SUMIFS(topmanager!$D:$D,topmanager!$C:$C,rs_nova!$A8,topmanager!$A:$A,rs_nova!BI$2) -> 0 | BJ8: =SUMIFS(topmanager!$D:$D,topmanager!$C:$C,rs_nova!$A8,topmanager!$A:$A,rs_nova!BJ$2)+SUMIFS(topmanager!$D:$D,topmanager!$C:$C,rs_nova!$A8,topmanager!$A:$A,rs_nova!BJ$2+1) -> 0 | BK8: =IFERROR(VLOOKUP(A8,[8]ferias!$C$4:$G$100,5,FALSE),0) -> 0 | BL8: =SUMIFS(topmanager!$D:$D,topmanager!$C:$C,rs_nova!$A8,topmanager!$A:$A,rs_nova!BL$2) -> 0 | BM8: =SUMIFS(topmanager!$D:$D,topmanager!$C:$C,rs_nova!$A8,topmanager!$A:$A,rs_nova!BM$2)+SUMIFS(topmanager!$D:$D,topmanager!$C:$C,rs_nova!$A12,topmanager!$A:$A,151) -> 0 | BN8: =BF8+BG8+BH8+BI8+P8+O8+W8 -> 0
A9: =total!B7 -> 4 | B9: =IFERROR(IF(E9="",IF(D9<=B$2,30,31-DAY(D9)),IF(E9<B$2,0,IF(D9>=B$2,DAY(E9)-DAY(D9),DAY(E9)))),0) -> 30 | C9: =total!D7 -> Colaborador 4 | D9: =IFERROR(VLOOKUP(A9,salario!A$3:J$32,10,FALSE),"") -> 46023 | E9: =IFERROR(IF(VLOOKUP(A9,salario!A$3:O$32,15,FALSE)="","",VLOOKUP(A9,salario!A$3:O$32,15,FALSE)),"") | F9: =IFERROR(VLOOKUP(A9,[5]base_pessoal!$B$2:$P$1504,13,FALSE),"") | G9: =IFERROR(VLOOKUP(A9,salario!A$2:P$91,11,FALSE),0)*B9/30 -> 7685.13 | H9: =SUMIFS(topmanager!$D:$D,topmanager!$C:$C,rs_nova!$A9,topmanager!$A:$A,rs_nova!H$2)+SUMIFS(topmanager!$D:$D,topmanager!$C:$C,rs_nova!$A9,topmanager!$A:$A,63) -> 0 | I9: =-SUMIFS(topmanager!$D:$D,topmanager!$C:$C,rs_nova!$A9,topmanager!$A:$A,rs_nova!I$2) -> 0 | J9: =SUMIFS(topmanager!$D:$D,topmanager!$C:$C,rs_nova!$A9,topmanager!$A:$A,rs_nova!J$2) -> 0 | K9: =SUMIFS(topmanager!$D:$D,topmanager!$C:$C,rs_nova!$A9,topmanager!$A:$A,rs_nova!K$2)+SUMIFS(topmanager!$D:$D,topmanager!$C:$C,rs_nova!$A9,topmanager!$A:$A,911) -> 0 | L9: =SUMIFS(topmanager!$D:$D,topmanager!$C:$C,rs_nova!$A9,topmanager!$A:$A,rs_nova!L$2) -> 0 | M9: =SUMIFS(topmanager!$D:$D,topmanager!$C:$C,rs_nova!$A9,topmanager!$A:$A,rs_nova!M$2)+SUMIFS(topmanager!$D:$D,topmanager!$C:$C,rs_nova!$A9,topmanager!$A:$A,908)+SUMIFS(topmanager!$D:$D,topmanager!$C:$C,rs_nova!$A9,topmanager!$A:$A,550) -> 0 | N9: =SUMIFS(topmanager!$D:$D,topmanager!$C:$C,rs_nova!$A9,topmanager!$A:$A,rs_nova!N$2) -> 0 | O9: =SUM(H9:N9) -> 0 | P9: =IFERROR(VLOOKUP($A9,total!$B$4:$AW$437,27,0),0) -> 0 | Q9: =IFERROR(VLOOKUP($A9,total!$B$4:$AW$437,21,0),0) -> 0 | R9: =IFERROR(VLOOKUP($A9,total!$B$4:$AW$437,25,0),0)+IFERROR(VLOOKUP($A9,total!$B$4:$AW$437,36,0),0) -> 0 | S9: =IFERROR(VLOOKUP(A9,gympass!$A$2:$F$148,6,0),0) -> 166.66667 | T9: =IFERROR(VLOOKUP($A9,total!$B$4:$AW$437,42,0),0) -> 66.666667 | U9: =IFERROR(VLOOKUP($A9,total!$B$4:$AW$437,32,0),0) -> 0 | V9: =IFERROR(VLOOKUP($A9,total!$B$4:$AW$437,28,0),0) -> 0 | W9: =IFERROR(VLOOKUP($A9,total!$B$4:$AX$437,49,0),0) -> 0 | Y9: =IFERROR(VLOOKUP(A9,#REF!,4,0),0) -> 0 | Z9: =IFERROR(VLOOKUP(B9,#REF!,8,0),0) -> 0 | AA9: =IFERROR(VLOOKUP($A9,total!$B$4:$AW$437,45,0),0) -> 0 | AB9: =IFERROR(VLOOKUP($A9,total!$B$4:$AW$437,48,0),0) -> 0 | AC9: =IFERROR(VLOOKUP($A9,total!$B$4:$AB$437,19,0),0) -> 0 | AD9: =IFERROR(VLOOKUP($A9,total!$B$4:$AB$437,10,0),0) -> 32.4863 | AE9: =IFERROR(VLOOKUP($A9,total!$B$4:$AB$437,13,0),0)-SUMIFS(topmanager!$D:$D,topmanager!$C:$C,rs_nova!$A13,topmanager!$A:$A,856) -> 450 | AF9: =IFERROR(VLOOKUP($A9,total!$B$4:$AB$437,16,0),0) -> 12.276995 | AG9: =IFERROR(VLOOKUP($A9,total!$B$4:$AB$437,7,0),0) -> 0 | AH9: =IFERROR(VLOOKUP($A9,total!$B$4:$AD$437,29,0),0) -> 275 | AI9: =IFERROR(VLOOKUP(A9,total!$B$4:$AN$437,39,0),0) -> 100 | AJ9: =SUM(P9:AI9) -> 1103.0966 | AK9: =AK$5*($BN9-BG9) -> 0 | AL9: =AL$5*($BN9+BJ9+BK9+BL9+BM9) -> 0 | AM9: =IF(F9="NÃO",0,AM$5*$BN9) -> 0 | AN9: =IF(AND($A9>1000,$A9<=1999),0,AN$5*$G9) -> 640.17133 | AO9: =IF(AND($A9>1000,$A9<=1999),0,AO$5*$G9) -> 307.4052 | AP9: =IF(AND($A9>1000,$A9<=1999),0,AP$5*$G9) -> 268.97955 | AQ9: =IFERROR(VLOOKUP(TEXT($A9,"000000"),[6]Página1!$A$8:$S$801,13,FALSE),0) -> 0 | AR9: =IFERROR(VLOOKUP(TEXT($A9,"000000"),[6]Página1!$A$8:$S$801,16,FALSE),0) -> 0 | AS9: =IFERROR(VLOOKUP(TEXT($A9,"000000"),[6]Página1!$A$8:$S$801,19,FALSE),0) -> 0 | AT9: =IFERROR(VLOOKUP(TEXT($A9,"000000"),[7]Página1!$A$8:$R$814,12,FALSE),0) -> 0 | AU9: =IFERROR(VLOOKUP(TEXT($A9,"000000"),[7]Página1!$A$8:$R$814,15,FALSE),0) -> 0 | AV9: =IFERROR(VLOOKUP(TEXT($A9,"000000"),[7]Página1!$A$8:$R$814,18,FALSE),0) -> 0 | AX9: =SUM(AK9:AW9) -> 1216.5561 | AY9: =AN9+AO9+AP9 -> 1216.5561 | AZ9: =AX9+AJ9+O9+G9-AY9 -> 8788.2266 | BA9: =AX9+AJ9+O9+G9 -> 10004.783 | BB9: =($G9)/$BB$3 -> 48.032063 | BC9: =$AX9/$BB$3 -> 7.6034755 | BD9: =$AJ9/$BB$3 -> 6.8943539 | BE9: =IFERROR(VLOOKUP(A9,salario!A$2:P$91,11,FALSE),0) -> 7685.13 | BF9: =SUMIFS(topmanager!$D:$D,topmanager!$C:$C,rs_nova!$A9,topmanager!$A:$A,rs_nova!BF$2) -> 0 | BG9: =SUMIFS(topmanager!$D:$D,topmanager!$C:$C,rs_nova!$A9,topmanager!$A:$A,rs_nova!BG$2) -> 0 | BH9: =SUMIFS(topmanager!$D:$D,topmanager!$C:$C,rs_nova!$A9,topmanager!$A:$A,rs_nova!BH$2) -> 0 | BI9: =SUMIFS(topmanager!$D:$D,topmanager!$C:$C,rs_nova!$A9,topmanager!$A:$A,rs_nova!BI$2) -> 0 | BJ9: =SUMIFS(topmanager!$D:$D,topmanager!$C:$C,rs_nova!$A9,topmanager!$A:$A,rs_nova!BJ$2)+SUMIFS(topmanager!$D:$D,topmanager!$C:$C,rs_nova!$A9,topmanager!$A:$A,rs_nova!BJ$2+1) -> 0 | BK9: =IFERROR(VLOOKUP(A9,[8]ferias!$C$4:$G$100,5,FALSE),0) -> 0 | BL9: =SUMIFS(topmanager!$D:$D,topmanager!$C:$C,rs_nova!$A9,topmanager!$A:$A,rs_nova!BL$2) -> 0 | BM9: =SUMIFS(topmanager!$D:$D,topmanager!$C:$C,rs_nova!$A9,topmanager!$A:$A,rs_nova!BM$2)+SUMIFS(topmanager!$D:$D,topmanager!$C:$C,rs_nova!$A13,topmanager!$A:$A,151) -> 0 | BN9: =BF9+BG9+BH9+BI9+P9+O9+W9 -> 0
A10: =total!B8 -> 5 | B10: =IFERROR(IF(E10="",IF(D10<=B$2,30,31-DAY(D10)),IF(E10<B$2,0,IF(D10>=B$2,DAY(E10)-DAY(D10),DAY(E10)))),0) -> 30 | C10: =total!D8 -> Colaborador 5 | D10: =IFERROR(VLOOKUP(A10,salario!A$3:J$32,10,FALSE),"") -> 46023 | E10: =IFERROR(IF(VLOOKUP(A10,salario!A$3:O$32,15,FALSE)="","",VLOOKUP(A10,salario!A$3:O$32,15,FALSE)),"") | F10: =IFERROR(VLOOKUP(A10,[5]base_pessoal!$B$2:$P$1504,13,FALSE),"") | G10: =IFERROR(VLOOKUP(A10,salario!A$2:P$91,11,FALSE),0)*B10/30 -> 3652.6 | H10: =SUMIFS(topmanager!$D:$D,topmanager!$C:$C,rs_nova!$A10,topmanager!$A:$A,rs_nova!H$2)+SUMIFS(topmanager!$D:$D,topmanager!$C:$C,rs_nova!$A10,topmanager!$A:$A,63) -> 0 | I10: =-SUMIFS(topmanager!$D:$D,topmanager!$C:$C,rs_nova!$A10,topmanager!$A:$A,rs_nova!I$2) -> 0 | J10: =SUMIFS(topmanager!$D:$D,topmanager!$C:$C,rs_nova!$A10,topmanager!$A:$A,rs_nova!J$2) -> 0 | K10: =SUMIFS(topmanager!$D:$D,topmanager!$C:$C,rs_nova!$A10,topmanager!$A:$A,rs_nova!K$2)+SUMIFS(topmanager!$D:$D,topmanager!$C:$C,rs_nova!$A10,topmanager!$A:$A,911) -> 0 | L10: =SUMIFS(topmanager!$D:$D,topmanager!$C:$C,rs_nova!$A10,topmanager!$A:$A,rs_nova!L$2) -> 0 | M10: =SUMIFS(topmanager!$D:$D,topmanager!$C:$C,rs_nova!$A10,topmanager!$A:$A,rs_nova!M$2)+SUMIFS(topmanager!$D:$D,topmanager!$C:$C,rs_nova!$A10,topmanager!$A:$A,908)+SUMIFS(topmanager!$D:$D,topmanager!$C:$C,rs_nova!$A10,topmanager!$A:$A,550) -> 0 | N10: =SUMIFS(topmanager!$D:$D,topmanager!$C:$C,rs_nova!$A10,topmanager!$A:$A,rs_nova!N$2) -> 0 | O10: =SUM(H10:N10) -> 0 | P10: =IFERROR(VLOOKUP($A10,total!$B$4:$AW$437,27,0),0) -> 0 | Q10: =IFERROR(VLOOKUP($A10,total!$B$4:$AW$437,21,0),0) -> 0 | R10: =IFERROR(VLOOKUP($A10,total!$B$4:$AW$437,25,0),0)+IFERROR(VLOOKUP($A10,total!$B$4:$AW$437,36,0),0) -> 0 | S10: =IFERROR(VLOOKUP(A10,gympass!$A$2:$F$148,6,0),0) -> 166.66667 | T10: =IFERROR(VLOOKUP($A10,total!$B$4:$AW$437,42,0),0) -> 66.666667 | U10: =IFERROR(VLOOKUP($A10,total!$B$4:$AW$437,32,0),0) -> 0 | V10: =IFERROR(VLOOKUP($A10,total!$B$4:$AW$437,28,0),0) -> 0 | W10: =IFERROR(VLOOKUP($A10,total!$B$4:$AX$437,49,0),0) -> 0 | Y10: =IFERROR(VLOOKUP(A10,#REF!,4,0),0) -> 0 | Z10: =IFERROR(VLOOKUP(B10,#REF!,8,0),0) -> 0 | AA10: =IFERROR(VLOOKUP($A10,total!$B$4:$AW$437,45,0),0) -> 0 | AB10: =IFERROR(VLOOKUP($A10,total!$B$4:$AW$437,48,0),0) -> 0 | AC10: =IFERROR(VLOOKUP($A10,total!$B$4:$AB$437,19,0),0) -> 0 | AD10: =IFERROR(VLOOKUP($A10,total!$B$4:$AB$437,10,0),0) -> 235.4202 | AE10: =IFERROR(VLOOKUP($A10,total!$B$4:$AB$437,13,0),0)-SUMIFS(topmanager!$D:$D,topmanager!$C:$C,rs_nova!$A14,topmanager!$A:$A,856) -> 490 | AF10: =IFERROR(VLOOKUP($A10,total!$B$4:$AB$437,16,0),0) -> 5.8350285 | AG10: =IFERROR(VLOOKUP($A10,total!$B$4:$AB$437,7,0),0) -> 0 | AH10: =IFERROR(VLOOKUP($A10,total!$B$4:$AD$437,29,0),0) -> 275 | AI10: =IFERROR(VLOOKUP(A10,total!$B$4:$AN$437,39,0),0) -> 100 | AJ10: =SUM(P10:AI10) -> 1339.5886 | AK10: =AK$5*($BN10-BG10) -> 0 | AL10: =AL$5*($BN10+BJ10+BK10+BL10+BM10) -> 0 | AM10: =IF(F10="NÃO",0,AM$5*$BN10) -> 0 | AN10: =IF(AND($A10>1000,$A10<=1999),0,AN$5*$G10) -> 304.26158 | AO10: =IF(AND($A10>1000,$A10<=1999),0,AO$5*$G10) -> 146.104 | AP10: =IF(AND($A10>1000,$A10<=1999),0,AP$5*$G10) -> 127.841 | AQ10: =IFERROR(VLOOKUP(TEXT($A10,"000000"),[6]Página1!$A$8:$S$801,13,FALSE),0) -> 0 | AR10: =IFERROR(VLOOKUP(TEXT($A10,"000000"),[6]Página1!$A$8:$S$801,16,FALSE),0) -> 0 | AS10: =IFERROR(VLOOKUP(TEXT($A10,"000000"),[6]Página1!$A$8:$S$801,19,FALSE),0) -> 0 | AT10: =IFERROR(VLOOKUP(TEXT($A10,"000000"),[7]Página1!$A$8:$R$814,12,FALSE),0) -> 0 | AU10: =IFERROR(VLOOKUP(TEXT($A10,"000000"),[7]Página1!$A$8:$R$814,15,FALSE),0) -> 0 | AV10: =IFERROR(VLOOKUP(TEXT($A10,"000000"),[7]Página1!$A$8:$R$814,18,FALSE),0) -> 0 | AX10: =SUM(AK10:AW10) -> 578.20658 | AY10: =AN10+AO10+AP10 -> 578.20658 | AZ10: =AX10+AJ10+O10+G10-AY10 -> 4992.1886 | BA10: =AX10+AJ10+O10+G10 -> 5570.3951 | BB10: =($G10)/$BB$3 -> 22.82875 | BC10: =$AX10/$BB$3 -> 3.6137911 | BD10: =$AJ10/$BB$3 -> 8.3724285 | BE10: =IFERROR(VLOOKUP(A10,salario!A$2:P$91,11,FALSE),0) -> 3652.6 | BF10: =SUMIFS(topmanager!$D:$D,topmanager!$C:$C,rs_nova!$A10,topmanager!$A:$A,rs_nova!BF$2) -> 0 | BG10: =SUMIFS(topmanager!$D:$D,topmanager!$C:$C,rs_nova!$A10,topmanager!$A:$A,rs_nova!BG$2) -> 0 | BH10: =SUMIFS(topmanager!$D:$D,topmanager!$C:$C,rs_nova!$A10,topmanager!$A:$A,rs_nova!BH$2) -> 0 | BI10: =SUMIFS(topmanager!$D:$D,topmanager!$C:$C,rs_nova!$A10,topmanager!$A:$A,rs_nova!BI$2) -> 0 | BJ10: =SUMIFS(topmanager!$D:$D,topmanager!$C:$C,rs_nova!$A10,topmanager!$A:$A,rs_nova!BJ$2)+SUMIFS(topmanager!$D:$D,topmanager!$C:$C,rs_nova!$A10,topmanager!$A:$A,rs_nova!BJ$2+1) -> 0 | BK10: =IFERROR(VLOOKUP(A10,[8]ferias!$C$4:$G$100,5,FALSE),0) -> 0 | BL10: =SUMIFS(topmanager!$D:$D,topmanager!$C:$C,rs_nova!$A10,topmanager!$A:$A,rs_nova!BL$2) -> 0 | BM10: =SUMIFS(topmanager!$D:$D,topmanager!$C:$C,rs_nova!$A10,topmanager!$A:$A,rs_nova!BM$2)+SUMIFS(topmanager!$D:$D,topmanager!$C:$C,rs_nova!$A14,topmanager!$A:$A,151) -> 0 | BN10: =BF10+BG10+BH10+BI10+P10+O10+W10 -> 0
A11: =total!B9 -> 6 | B11: =IFERROR(IF(E11="",IF(D11<=B$2,30,31-DAY(D11)),IF(E11<B$2,0,IF(D11>=B$2,DAY(E11)-DAY(D11),DAY(E11)))),0) -> 30 | C11: =total!D9 -> Colaborador 6 | D11: =IFERROR(VLOOKUP(A11,salario!A$3:J$32,10,FALSE),"") -> 46023 | E11: =IFERROR(IF(VLOOKUP(A11,salario!A$3:O$32,15,FALSE)="","",VLOOKUP(A11,salario!A$3:O$32,15,FALSE)),"") | F11: =IFERROR(VLOOKUP(A11,[5]base_pessoal!$B$2:$P$1504,13,FALSE),"") | G11: =IFERROR(VLOOKUP(A11,salario!A$2:P$91,11,FALSE),0)*B11/30 -> 7943.86 | H11: =SUMIFS(topmanager!$D:$D,topmanager!$C:$C,rs_nova!$A11,topmanager!$A:$A,rs_nova!H$2)+SUMIFS(topmanager!$D:$D,topmanager!$C:$C,rs_nova!$A11,topmanager!$A:$A,63) -> 0 | I11: =-SUMIFS(topmanager!$D:$D,topmanager!$C:$C,rs_nova!$A11,topmanager!$A:$A,rs_nova!I$2) -> 0 | J11: =SUMIFS(topmanager!$D:$D,topmanager!$C:$C,rs_nova!$A11,topmanager!$A:$A,rs_nova!J$2) -> 0 | K11: =SUMIFS(topmanager!$D:$D,topmanager!$C:$C,rs_nova!$A11,topmanager!$A:$A,rs_nova!K$2)+SUMIFS(topmanager!$D:$D,topmanager!$C:$C,rs_nova!$A11,topmanager!$A:$A,911) -> 0 | L11: =SUMIFS(topmanager!$D:$D,topmanager!$C:$C,rs_nova!$A11,topmanager!$A:$A,rs_nova!L$2) -> 0 | M11: =SUMIFS(topmanager!$D:$D,topmanager!$C:$C,rs_nova!$A11,topmanager!$A:$A,rs_nova!M$2)+SUMIFS(topmanager!$D:$D,topmanager!$C:$C,rs_nova!$A11,topmanager!$A:$A,908)+SUMIFS(topmanager!$D:$D,topmanager!$C:$C,rs_nova!$A11,topmanager!$A:$A,550) -> 0 | N11: =SUMIFS(topmanager!$D:$D,topmanager!$C:$C,rs_nova!$A11,topmanager!$A:$A,rs_nova!N$2) -> 0 | O11: =SUM(H11:N11) -> 0 | P11: =IFERROR(VLOOKUP($A11,total!$B$4:$AW$437,27,0),0) -> 0 | Q11: =IFERROR(VLOOKUP($A11,total!$B$4:$AW$437,21,0),0) -> 0 | R11: =IFERROR(VLOOKUP($A11,total!$B$4:$AW$437,25,0),0)+IFERROR(VLOOKUP($A11,total!$B$4:$AW$437,36,0),0) -> 0 | S11: =IFERROR(VLOOKUP(A11,gympass!$A$2:$F$148,6,0),0) -> 166.66667 | T11: =IFERROR(VLOOKUP($A11,total!$B$4:$AW$437,42,0),0) -> 66.666667 | U11: =IFERROR(VLOOKUP($A11,total!$B$4:$AW$437,32,0),0) -> 0 | V11: =IFERROR(VLOOKUP($A11,total!$B$4:$AW$437,28,0),0) -> 0 | W11: =IFERROR(VLOOKUP($A11,total!$B$4:$AX$437,49,0),0) -> 0 | Y11: =IFERROR(VLOOKUP(A11,#REF!,4,0),0) -> 0 | Z11: =IFERROR(VLOOKUP(B11,#REF!,8,0),0) -> 0 | AA11: =IFERROR(VLOOKUP($A11,total!$B$4:$AW$437,45,0),0) -> 0 | AB11: =IFERROR(VLOOKUP($A11,total!$B$4:$AW$437,48,0),0) -> 0 | AC11: =IFERROR(VLOOKUP($A11,total!$B$4:$AB$437,19,0),0) -> 0 | AD11: =IFERROR(VLOOKUP($A11,total!$B$4:$AB$437,10,0),0) -> 129.9452 | AE11: =IFERROR(VLOOKUP($A11,total!$B$4:$AB$437,13,0),0)-SUMIFS(topmanager!$D:$D,topmanager!$C:$C,rs_nova!$A15,topmanager!$A:$A,856) -> 450 | AF11: =IFERROR(VLOOKUP($A11,total!$B$4:$AB$437,16,0),0) -> 12.690316 | AG11: =IFERROR(VLOOKUP($A11,total!$B$4:$AB$437,7,0),0) -> 0 | AH11: =IFERROR(VLOOKUP($A11,total!$B$4:$AD$437,29,0),0) -> 275 | AI11: =IFERROR(VLOOKUP(A11,total!$B$4:$AN$437,39,0),0) -> 100 | AJ11: =SUM(P11:AI11) -> 1200.9688 | AK11: =AK$5*($BN11-BG11) -> 0 | AL11: =AL$5*($BN11+BJ11+BK11+BL11+BM11) -> 0 | AM11: =IF(F11="NÃO",0,AM$5*$BN11) -> 0 | AN11: =IF(AND($A11>1000,$A11<=1999),0,AN$5*$G11) -> 661.72354 | AO11: =IF(AND($A11>1000,$A11<=1999),0,AO$5*$G11) -> 317.7544 | AP11: =IF(AND($A11>1000,$A11<=1999),0,AP$5*$G11) -> 278.0351 | AQ11: =IFERROR(VLOOKUP(TEXT($A11,"000000"),[6]Página1!$A$8:$S$801,13,FALSE),0) -> 0 | AR11: =IFERROR(VLOOKUP(TEXT($A11,"000000"),[6]Página1!$A$8:$S$801,16,FALSE),0) -> 0 | AS11: =IFERROR(VLOOKUP(TEXT($A11,"000000"),[6]Página1!$A$8:$S$801,19,FALSE),0) -> 0 | AT11: =IFERROR(VLOOKUP(TEXT($A11,"000000"),[7]Página1!$A$8:$R$814,12,FALSE),0) -> 0 | AU11: =IFERROR(VLOOKUP(TEXT($A11,"000000"),[7]Página1!$A$8:$R$814,15,FALSE),0) -> 0 | AV11: =IFERROR(VLOOKUP(TEXT($A11,"000000"),[7]Página1!$A$8:$R$814,18,FALSE),0) -> 0 | AX11: =SUM(AK11:AW11) -> 1257.513 | AY11: =AN11+AO11+AP11 -> 1257.513 | AZ11: =AX11+AJ11+O11+G11-AY11 -> 9144.8288 | BA11: =AX11+AJ11+O11+G11 -> 10402.342 | BB11: =($G11)/$BB$3 -> 49.649125 | BC11: =$AX11/$BB$3 -> 7.8594565 | BD11: =$AJ11/$BB$3 -> 7.5060553 | BE11: =IFERROR(VLOOKUP(A11,salario!A$2:P$91,11,FALSE),0) -> 7943.86 | BF11: =SUMIFS(topmanager!$D:$D,topmanager!$C:$C,rs_nova!$A11,topmanager!$A:$A,rs_nova!BF$2) -> 0 | BG11: =SUMIFS(topmanager!$D:$D,topmanager!$C:$C,rs_nova!$A11,topmanager!$A:$A,rs_nova!BG$2) -> 0 | BH11: =SUMIFS(topmanager!$D:$D,topmanager!$C:$C,rs_nova!$A11,topmanager!$A:$A,rs_nova!BH$2) -> 0 | BI11: =SUMIFS(topmanager!$D:$D,topmanager!$C:$C,rs_nova!$A11,topmanager!$A:$A,rs_nova!BI$2) -> 0 | BJ11: =SUMIFS(topmanager!$D:$D,topmanager!$C:$C,rs_nova!$A11,topmanager!$A:$A,rs_nova!BJ$2)+SUMIFS(topmanager!$D:$D,topmanager!$C:$C,rs_nova!$A11,topmanager!$A:$A,rs_nova!BJ$2+1) -> 0 | BK11: =IFERROR(VLOOKUP(A11,[8]ferias!$C$4:$G$100,5,FALSE),0) -> 0 | BL11: =SUMIFS(topmanager!$D:$D,topmanager!$C:$C,rs_nova!$A11,topmanager!$A:$A,rs_nova!BL$2) -> 0 | BM11: =SUMIFS(topmanager!$D:$D,topmanager!$C:$C,rs_nova!$A11,topmanager!$A:$A,rs_nova!BM$2)+SUMIFS(topmanager!$D:$D,topmanager!$C:$C,rs_nova!$A15,topmanager!$A:$A,151) -> 0 | BN11: =BF11+BG11+BH11+BI11+P11+O11+W11 -> 0
A12: =total!B10 -> 7 | B12: =IFERROR(IF(E12="",IF(D12<=B$2,30,31-DAY(D12)),IF(E12<B$2,0,IF(D12>=B$2,DAY(E12)-DAY(D12),DAY(E12)))),0) -> 30 | C12: =total!D10 -> Colaborador 7 | D12: =IFERROR(VLOOKUP(A12,salario!A$3:J$32,10,FALSE),"") -> 46023 | E12: =IFERROR(IF(VLOOKUP(A12,salario!A$3:O$32,15,FALSE)="","",VLOOKUP(A12,salario!A$3:O$32,15,FALSE)),"") | F12: =IFERROR(VLOOKUP(A12,[5]base_pessoal!$B$2:$P$1504,13,FALSE),"") | G12: =IFERROR(VLOOKUP(A12,salario!A$2:P$91,11,FALSE),0)*B12/30 -> 7131.14 | H12: =SUMIFS(topmanager!$D:$D,topmanager!$C:$C,rs_nova!$A12,topmanager!$A:$A,rs_nova!H$2)+SUMIFS(topmanager!$D:$D,topmanager!$C:$C,rs_nova!$A12,topmanager!$A:$A,63) -> 0 | I12: =-SUMIFS(topmanager!$D:$D,topmanager!$C:$C,rs_nova!$A12,topmanager!$A:$A,rs_nova!I$2) -> 0 | J12: =SUMIFS(topmanager!$D:$D,topmanager!$C:$C,rs_nova!$A12,topmanager!$A:$A,rs_nova!J$2) -> 0 | K12: =SUMIFS(topmanager!$D:$D,topmanager!$C:$C,rs_nova!$A12,topmanager!$A:$A,rs_nova!K$2)+SUMIFS(topmanager!$D:$D,topmanager!$C:$C,rs_nova!$A12,topmanager!$A:$A,911) -> 0 | L12: =SUMIFS(topmanager!$D:$D,topmanager!$C:$C,rs_nova!$A12,topmanager!$A:$A,rs_nova!L$2) -> 0 | M12: =SUMIFS(topmanager!$D:$D,topmanager!$C:$C,rs_nova!$A12,topmanager!$A:$A,rs_nova!M$2)+SUMIFS(topmanager!$D:$D,topmanager!$C:$C,rs_nova!$A12,topmanager!$A:$A,908)+SUMIFS(topmanager!$D:$D,topmanager!$C:$C,rs_nova!$A12,topmanager!$A:$A,550) -> 0 | N12: =SUMIFS(topmanager!$D:$D,topmanager!$C:$C,rs_nova!$A12,topmanager!$A:$A,rs_nova!N$2) -> 0 | O12: =SUM(H12:N12) -> 0 | P12: =IFERROR(VLOOKUP($A12,total!$B$4:$AW$437,27,0),0) -> 0 | Q12: =IFERROR(VLOOKUP($A12,total!$B$4:$AW$437,21,0),0) -> 0 | R12: =IFERROR(VLOOKUP($A12,total!$B$4:$AW$437,25,0),0)+IFERROR(VLOOKUP($A12,total!$B$4:$AW$437,36,0),0) -> 0 | S12: =IFERROR(VLOOKUP(A12,gympass!$A$2:$F$148,6,0),0) -> 166.66667 | T12: =IFERROR(VLOOKUP($A12,total!$B$4:$AW$437,42,0),0) -> 66.666667 | U12: =IFERROR(VLOOKUP($A12,total!$B$4:$AW$437,32,0),0) -> 0 | V12: =IFERROR(VLOOKUP($A12,total!$B$4:$AW$437,28,0),0) -> 0 | W12: =IFERROR(VLOOKUP($A12,total!$B$4:$AX$437,49,0),0) -> 0 | Y12: =IFERROR(VLOOKUP(A12,#REF!,4,0),0) -> 0 | Z12: =IFERROR(VLOOKUP(B12,#REF!,8,0),0) -> 0 | AA12: =IFERROR(VLOOKUP($A12,total!$B$4:$AW$437,45,0),0) -> 0 | AB12: =IFERROR(VLOOKUP($A12,total!$B$4:$AW$437,48,0),0) -> 0 | AC12: =IFERROR(VLOOKUP($A12,total!$B$4:$AB$437,19,0),0) -> 0 | AD12: =IFERROR(VLOOKUP($A12,total!$B$4:$AB$437,10,0),0) -> 143.446 | AE12: =IFERROR(VLOOKUP($A12,total!$B$4:$AB$437,13,0),0)-SUMIFS(topmanager!$D:$D,topmanager!$C:$C,rs_nova!$A16,topmanager!$A:$A,856) -> 470 | AF12: =IFERROR(VLOOKUP($A12,total!$B$4:$AB$437,16,0),0) -> 11.391996 | AG12: =IFERROR(VLOOKUP($A12,total!$B$4:$AB$437,7,0),0) -> 0 | AH12: =IFERROR(VLOOKUP($A12,total!$B$4:$AD$437,29,0),0) -> 275 | AI12: =IFERROR(VLOOKUP(A12,total!$B$4:$AN$437,39,0),0) -> 100 | AJ12: =SUM(P12:AI12) -> 1233.1713 | AK12: =AK$5*($BN12-BG12) -> 0 | AL12: =AL$5*($BN12+BJ12+BK12+BL12+BM12) -> 0 | AM12: =IF(F12="NÃO",0,AM$5*$BN12) -> 0 | AN12: =IF(AND($A12>1000,$A12<=1999),0,AN$5*$G12) -> 594.02396 | AO12: =IF(AND($A12>1000,$A12<=1999),0,AO$5*$G12) -> 285.2456 | AP12: =IF(AND($A12>1000,$A12<=1999),0,AP$5*$G12) -> 249.5899 | AQ12: =IFERROR(VLOOKUP(TEXT($A12,"000000"),[6]Página1!$A$8:$S$801,13,FALSE),0) -> 0 | AR12: =IFERROR(VLOOKUP(TEXT($A12,"000000"),[6]Página1!$A$8:$S$801,16,FALSE),0) -> 0 | AS12: =IFERROR(VLOOKUP(TEXT($A12,"000000"),[6]Página1!$A$8:$S$801,19,FALSE),0) -> 0 | AT12: =IFERROR(VLOOKUP(TEXT($A12,"000000"),[7]Página1!$A$8:$R$814,12,FALSE),0) -> 0 | AU12: =IFERROR(VLOOKUP(TEXT($A12,"000000"),[7]Página1!$A$8:$R$814,15,FALSE),0) -> 0 | AV12: =IFERROR(VLOOKUP(TEXT($A12,"000000"),[7]Página1!$A$8:$R$814,18,FALSE),0) -> 0 | AX12: =SUM(AK12:AW12) -> 1128.8595 | AY12: =AN12+AO12+AP12 -> 1128.8595 | AZ12: =AX12+AJ12+O12+G12-AY12 -> 8364.3113 | BA12: =AX12+AJ12+O12+G12 -> 9493.1708 | BB12: =($G12)/$BB$3 -> 44.569625 | BC12: =$AX12/$BB$3 -> 7.0553716 | BD12: =$AJ12/$BB$3 -> 7.7073208 | BE12: =IFERROR(VLOOKUP(A12,salario!A$2:P$91,11,FALSE),0) -> 7131.14 | BF12: =SUMIFS(topmanager!$D:$D,topmanager!$C:$C,rs_nova!$A12,topmanager!$A:$A,rs_nova!BF$2) -> 0 | BG12: =SUMIFS(topmanager!$D:$D,topmanager!$C:$C,rs_nova!$A12,topmanager!$A:$A,rs_nova!BG$2) -> 0 | BH12: =SUMIFS(topmanager!$D:$D,topmanager!$C:$C,rs_nova!$A12,topmanager!$A:$A,rs_nova!BH$2) -> 0 | BI12: =SUMIFS(topmanager!$D:$D,topmanager!$C:$C,rs_nova!$A12,topmanager!$A:$A,rs_nova!BI$2) -> 0 | BJ12: =SUMIFS(topmanager!$D:$D,topmanager!$C:$C,rs_nova!$A12,topmanager!$A:$A,rs_nova!BJ$2)+SUMIFS(topmanager!$D:$D,topmanager!$C:$C,rs_nova!$A12,topmanager!$A:$A,rs_nova!BJ$2+1) -> 0 | BK12: =IFERROR(VLOOKUP(A12,[8]ferias!$C$4:$G$100,5,FALSE),0) -> 0 | BL12: =SUMIFS(topmanager!$D:$D,topmanager!$C:$C,rs_nova!$A12,topmanager!$A:$A,rs_nova!BL$2) -> 0 | BM12: =SUMIFS(topmanager!$D:$D,topmanager!$C:$C,rs_nova!$A12,topmanager!$A:$A,rs_nova!BM$2)+SUMIFS(topmanager!$D:$D,topmanager!$C:$C,rs_nova!$A16,topmanager!$A:$A,151) -> 0 | BN12: =BF12+BG12+BH12+BI12+P12+O12+W12 -> 0
A13: =total!#REF! -> #REF! | B13: =IFERROR(IF(E13="",IF(D13<=B$2,30,31-DAY(D13)),IF(E13<B$2,0,IF(D13>=B$2,DAY(E13)-DAY(D13),DAY(E13)))),0) -> 0 | C13: =total!#REF! -> #REF! | D13: =IFERROR(VLOOKUP(A13,salario!A$3:J$32,10,FALSE),"") | E13: =IFERROR(IF(VLOOKUP(A13,salario!A$3:O$32,15,FALSE)="","",VLOOKUP(A13,salario!A$3:O$32,15,FALSE)),"") | F13: =IFERROR(VLOOKUP(A13,[5]base_pessoal!$B$2:$P$1504,13,FALSE),"") | G13: =IFERROR(VLOOKUP(A13,salario!A$2:P$91,11,FALSE),0)*B13/30 -> 0 | H13: =SUMIFS(topmanager!$D:$D,topmanager!$C:$C,rs_nova!$A13,topmanager!$A:$A,rs_nova!H$2)+SUMIFS(topmanager!$D:$D,topmanager!$C:$C,rs_nova!$A13,topmanager!$A:$A,63) -> 0 | I13: =-SUMIFS(topmanager!$D:$D,topmanager!$C:$C,rs_nova!$A13,topmanager!$A:$A,rs_nova!I$2) -> 0 | J13: =SUMIFS(topmanager!$D:$D,topmanager!$C:$C,rs_nova!$A13,topmanager!$A:$A,rs_nova!J$2) -> 0 | K13: =SUMIFS(topmanager!$D:$D,topmanager!$C:$C,rs_nova!$A13,topmanager!$A:$A,rs_nova!K$2)+SUMIFS(topmanager!$D:$D,topmanager!$C:$C,rs_nova!$A13,topmanager!$A:$A,911) -> 0 | L13: =SUMIFS(topmanager!$D:$D,topmanager!$C:$C,rs_nova!$A13,topmanager!$A:$A,rs_nova!L$2) -> 0 | M13: =SUMIFS(topmanager!$D:$D,topmanager!$C:$C,rs_nova!$A13,topmanager!$A:$A,rs_nova!M$2)+SUMIFS(topmanager!$D:$D,topmanager!$C:$C,rs_nova!$A13,topmanager!$A:$A,908)+SUMIFS(topmanager!$D:$D,topmanager!$C:$C,rs_nova!$A13,topmanager!$A:$A,550) -> 0 | N13: =SUMIFS(topmanager!$D:$D,topmanager!$C:$C,rs_nova!$A13,topmanager!$A:$A,rs_nova!N$2) -> 0 | O13: =SUM(H13:N13) -> 0 | P13: =IFERROR(VLOOKUP($A13,total!$B$4:$AW$437,27,0),0) -> 0 | Q13: =IFERROR(VLOOKUP($A13,total!$B$4:$AW$437,21,0),0) -> 0 | R13: =IFERROR(VLOOKUP($A13,total!$B$4:$AW$437,25,0),0)+IFERROR(VLOOKUP($A13,total!$B$4:$AW$437,36,0),0) -> 0 | S13: =IFERROR(VLOOKUP(A13,gympass!$A$2:$F$148,6,0),0) -> 0 | T13: =IFERROR(VLOOKUP($A13,total!$B$4:$AW$437,42,0),0) -> 0 | U13: =IFERROR(VLOOKUP($A13,total!$B$4:$AW$437,32,0),0) -> 0 | V13: =IFERROR(VLOOKUP($A13,total!$B$4:$AW$437,28,0),0) -> 0 | W13: =IFERROR(VLOOKUP($A13,total!$B$4:$AX$437,49,0),0) -> 0 | Y13: =IFERROR(VLOOKUP(A13,#REF!,4,0),0) -> 0 | Z13: =IFERROR(VLOOKUP(B13,#REF!,8,0),0) -> 0 | AA13: =IFERROR(VLOOKUP($A13,total!$B$4:$AW$437,45,0),0) -> 0 | AB13: =IFERROR(VLOOKUP($A13,total!$B$4:$AW$437,48,0),0) -> 0 | AC13: =IFERROR(VLOOKUP($A13,total!$B$4:$AB$437,19,0),0) -> 0 | AD13: =IFERROR(VLOOKUP($A13,total!$B$4:$AB$437,10,0),0) -> 0 | AE13: =IFERROR(VLOOKUP($A13,total!$B$4:$AB$437,13,0),0)-SUMIFS(topmanager!$D:$D,topmanager!$C:$C,rs_nova!$A17,topmanager!$A:$A,856) -> 0 | AF13: =IFERROR(VLOOKUP($A13,total!$B$4:$AB$437,16,0),0) -> 0 | AG13: =IFERROR(VLOOKUP($A13,total!$B$4:$AB$437,7,0),0) -> 0 | AH13: =IFERROR(VLOOKUP($A13,total!$B$4:$AD$437,29,0),0) -> 0 | AI13: =IFERROR(VLOOKUP(A13,total!$B$4:$AN$437,39,0),0) -> 0 | AJ13: =SUM(P13:AI13) -> 0 | AK13: =AK$5*($BN13-BG13) -> 0 | AL13: =AL$5*($BN13+BJ13+BK13+BL13+BM13) -> 0 | AM13: =IF(F13="NÃO",0,AM$5*$BN13) -> 0 | AN13: =IF(AND($A13>1000,$A13<=1999),0,AN$5*$G13) -> #REF! | AO13: =IF(AND($A13>1000,$A13<=1999),0,AO$5*$G13) -> #REF! | AP13: =IF(AND($A13>1000,$A13<=1999),0,AP$5*$G13) -> #REF! | AQ13: =IFERROR(VLOOKUP(TEXT($A13,"000000"),[6]Página1!$A$8:$S$801,13,FALSE),0) -> 0 | AR13: =IFERROR(VLOOKUP(TEXT($A13,"000000"),[6]Página1!$A$8:$S$801,16,FALSE),0) -> 0 | AS13: =IFERROR(VLOOKUP(TEXT($A13,"000000"),[6]Página1!$A$8:$S$801,19,FALSE),0) -> 0 | AT13: =IFERROR(VLOOKUP(TEXT($A13,"000000"),[7]Página1!$A$8:$R$814,12,FALSE),0) -> 0 | AU13: =IFERROR(VLOOKUP(TEXT($A13,"000000"),[7]Página1!$A$8:$R$814,15,FALSE),0) -> 0 | AV13: =IFERROR(VLOOKUP(TEXT($A13,"000000"),[7]Página1!$A$8:$R$814,18,FALSE),0) -> 0 | AX13: =SUM(AK13:AW13) -> #REF! | AY13: =AN13+AO13+AP13 -> #REF! | AZ13: =AX13+AJ13+O13+G13-AY13 -> #REF! | BA13: =AX13+AJ13+O13+G13 -> #REF! | BB13: =($G13)/$BB$3 -> 0 | BC13: =$AX13/$BB$3 -> #REF! | BD13: =$AJ13/$BB$3 -> 0 | BE13: =IFERROR(VLOOKUP(A13,salario!A$2:P$91,11,FALSE),0) -> 0 | BF13: =SUMIFS(topmanager!$D:$D,topmanager!$C:$C,rs_nova!$A13,topmanager!$A:$A,rs_nova!BF$2) -> 0 | BG13: =SUMIFS(topmanager!$D:$D,topmanager!$C:$C,rs_nova!$A13,topmanager!$A:$A,rs_nova!BG$2) -> 0 | BH13: =SUMIFS(topmanager!$D:$D,topmanager!$C:$C,rs_nova!$A13,topmanager!$A:$A,rs_nova!BH$2) -> 0 | BI13: =SUMIFS(topmanager!$D:$D,topmanager!$C:$C,rs_nova!$A13,topmanager!$A:$A,rs_nova!BI$2) -> 0 | BJ13: =SUMIFS(topmanager!$D:$D,topmanager!$C:$C,rs_nova!$A13,topmanager!$A:$A,rs_nova!BJ$2)+SUMIFS(topmanager!$D:$D,topmanager!$C:$C,rs_nova!$A13,topmanager!$A:$A,rs_nova!BJ$2+1) -> 0 | BK13: =IFERROR(VLOOKUP(A13,[8]ferias!$C$4:$G$100,5,FALSE),0) -> 0 | BL13: =SUMIFS(topmanager!$D:$D,topmanager!$C:$C,rs_nova!$A13,topmanager!$A:$A,rs_nova!BL$2) -> 0 | BM13: =SUMIFS(topmanager!$D:$D,topmanager!$C:$C,rs_nova!$A13,topmanager!$A:$A,rs_nova!BM$2)+SUMIFS(topmanager!$D:$D,topmanager!$C:$C,rs_nova!$A17,topmanager!$A:$A,151) -> 0 | BN13: =BF13+BG13+BH13+BI13+P13+O13+W13 -> 0
A14: =total!#REF! -> #REF! | B14: =IFERROR(IF(E14="",IF(D14<=B$2,30,31-DAY(D14)),IF(E14<B$2,0,IF(D14>=B$2,DAY(E14)-DAY(D14),DAY(E14)))),0) -> 0 | C14: =total!#REF! -> #REF! | D14: =IFERROR(VLOOKUP(A14,salario!A$3:J$32,10,FALSE),"") | E14: =IFERROR(IF(VLOOKUP(A14,salario!A$3:O$32,15,FALSE)="","",VLOOKUP(A14,salario!A$3:O$32,15,FALSE)),"") | F14: =IFERROR(VLOOKUP(A14,[5]base_pessoal!$B$2:$P$1504,13,FALSE),"") | G14: =IFERROR(VLOOKUP(A14,salario!A$2:P$91,11,FALSE),0)*B14/30 -> 0 | H14: =SUMIFS(topmanager!$D:$D,topmanager!$C:$C,rs_nova!$A14,topmanager!$A:$A,rs_nova!H$2)+SUMIFS(topmanager!$D:$D,topmanager!$C:$C,rs_nova!$A14,topmanager!$A:$A,63) -> 0 | I14: =-SUMIFS(topmanager!$D:$D,topmanager!$C:$C,rs_nova!$A14,topmanager!$A:$A,rs_nova!I$2) -> 0 | J14: =SUMIFS(topmanager!$D:$D,topmanager!$C:$C,rs_nova!$A14,topmanager!$A:$A,rs_nova!J$2) -> 0 | K14: =SUMIFS(topmanager!$D:$D,topmanager!$C:$C,rs_nova!$A14,topmanager!$A:$A,rs_nova!K$2)+SUMIFS(topmanager!$D:$D,topmanager!$C:$C,rs_nova!$A14,topmanager!$A:$A,911) -> 0 | L14: =SUMIFS(topmanager!$D:$D,topmanager!$C:$C,rs_nova!$A14,topmanager!$A:$A,rs_nova!L$2) -> 0 | M14: =SUMIFS(topmanager!$D:$D,topmanager!$C:$C,rs_nova!$A14,topmanager!$A:$A,rs_nova!M$2)+SUMIFS(topmanager!$D:$D,topmanager!$C:$C,rs_nova!$A14,topmanager!$A:$A,908)+SUMIFS(topmanager!$D:$D,topmanager!$C:$C,rs_nova!$A14,topmanager!$A:$A,550) -> 0 | N14: =SUMIFS(topmanager!$D:$D,topmanager!$C:$C,rs_nova!$A14,topmanager!$A:$A,rs_nova!N$2) -> 0 | O14: =SUM(H14:N14) -> 0 | P14: =IFERROR(VLOOKUP($A14,total!$B$4:$AW$437,27,0),0) -> 0 | Q14: =IFERROR(VLOOKUP($A14,total!$B$4:$AW$437,21,0),0) -> 0 | R14: =IFERROR(VLOOKUP($A14,total!$B$4:$AW$437,25,0),0)+IFERROR(VLOOKUP($A14,total!$B$4:$AW$437,36,0),0) -> 0 | S14: =IFERROR(VLOOKUP(A14,gympass!$A$2:$F$148,6,0),0) -> 0 | T14: =IFERROR(VLOOKUP($A14,total!$B$4:$AW$437,42,0),0) -> 0 | U14: =IFERROR(VLOOKUP($A14,total!$B$4:$AW$437,32,0),0) -> 0 | V14: =IFERROR(VLOOKUP($A14,total!$B$4:$AW$437,28,0),0) -> 0 | W14: =IFERROR(VLOOKUP($A14,total!$B$4:$AX$437,49,0),0) -> 0 | Y14: =IFERROR(VLOOKUP(A14,#REF!,4,0),0) -> 0 | Z14: =IFERROR(VLOOKUP(B14,#REF!,8,0),0) -> 0 | AA14: =IFERROR(VLOOKUP($A14,total!$B$4:$AW$437,45,0),0) -> 0 | AB14: =IFERROR(VLOOKUP($A14,total!$B$4:$AW$437,48,0),0) -> 0 | AC14: =IFERROR(VLOOKUP($A14,total!$B$4:$AB$437,19,0),0) -> 0 | AD14: =IFERROR(VLOOKUP($A14,total!$B$4:$AB$437,10,0),0) -> 0 | AE14: =IFERROR(VLOOKUP($A14,total!$B$4:$AB$437,13,0),0)-SUMIFS(topmanager!$D:$D,topmanager!$C:$C,rs_nova!$A18,topmanager!$A:$A,856) -> 0 | AF14: =IFERROR(VLOOKUP($A14,total!$B$4:$AB$437,16,0),0) -> 0 | AG14: =IFERROR(VLOOKUP($A14,total!$B$4:$AB$437,7,0),0) -> 0 | AH14: =IFERROR(VLOOKUP($A14,total!$B$4:$AD$437,29,0),0) -> 0 | AI14: =IFERROR(VLOOKUP(A14,total!$B$4:$AN$437,39,0),0) -> 0 | AJ14: =SUM(P14:AI14) -> 0 | AK14: =AK$5*($BN14-BG14) -> 0 | AL14: =AL$5*($BN14+BJ14+BK14+BL14+BM14) -> 0 | AM14: =IF(F14="NÃO",0,AM$5*$BN14) -> 0 | AN14: =IF(AND($A14>1000,$A14<=1999),0,AN$5*$G14) -> #REF! | AO14: =IF(AND($A14>1000,$A14<=1999),0,AO$5*$G14) -> #REF! | AP14: =IF(AND($A14>1000,$A14<=1999),0,AP$5*$G14) -> #REF! | AQ14: =IFERROR(VLOOKUP(TEXT($A14,"000000"),[6]Página1!$A$8:$S$801,13,FALSE),0) -> 0 | AR14: =IFERROR(VLOOKUP(TEXT($A14,"000000"),[6]Página1!$A$8:$S$801,16,FALSE),0) -> 0 | AS14: =IFERROR(VLOOKUP(TEXT($A14,"000000"),[6]Página1!$A$8:$S$801,19,FALSE),0) -> 0 | AT14: =IFERROR(VLOOKUP(TEXT($A14,"000000"),[7]Página1!$A$8:$R$814,12,FALSE),0) -> 0 | AU14: =IFERROR(VLOOKUP(TEXT($A14,"000000"),[7]Página1!$A$8:$R$814,15,FALSE),0) -> 0 | AV14: =IFERROR(VLOOKUP(TEXT($A14,"000000"),[7]Página1!$A$8:$R$814,18,FALSE),0) -> 0 | AX14: =SUM(AK14:AW14) -> #REF! | AY14: =AN14+AO14+AP14 -> #REF! | AZ14: =AX14+AJ14+O14+G14-AY14 -> #REF! | BA14: =AX14+AJ14+O14+G14 -> #REF! | BB14: =($G14)/$BB$3 -> 0 | BC14: =$AX14/$BB$3 -> #REF! | BD14: =$AJ14/$BB$3 -> 0 | BE14: =IFERROR(VLOOKUP(A14,salario!A$2:P$91,11,FALSE),0) -> 0 | BF14: =SUMIFS(topmanager!$D:$D,topmanager!$C:$C,rs_nova!$A14,topmanager!$A:$A,rs_nova!BF$2) -> 0 | BG14: =SUMIFS(topmanager!$D:$D,topmanager!$C:$C,rs_nova!$A14,topmanager!$A:$A,rs_nova!BG$2) -> 0 | BH14: =SUMIFS(topmanager!$D:$D,topmanager!$C:$C,rs_nova!$A14,topmanager!$A:$A,rs_nova!BH$2) -> 0 | BI14: =SUMIFS(topmanager!$D:$D,topmanager!$C:$C,rs_nova!$A14,topmanager!$A:$A,rs_nova!BI$2) -> 0 | BJ14: =SUMIFS(topmanager!$D:$D,topmanager!$C:$C,rs_nova!$A14,topmanager!$A:$A,rs_nova!BJ$2)+SUMIFS(topmanager!$D:$D,topmanager!$C:$C,rs_nova!$A14,topmanager!$A:$A,rs_nova!BJ$2+1) -> 0 | BK14: =IFERROR(VLOOKUP(A14,[8]ferias!$C$4:$G$100,5,FALSE),0) -> 0 | BL14: =SUMIFS(topmanager!$D:$D,topmanager!$C:$C,rs_nova!$A14,topmanager!$A:$A,rs_nova!BL$2) -> 0 | BM14: =SUMIFS(topmanager!$D:$D,topmanager!$C:$C,rs_nova!$A14,topmanager!$A:$A,rs_nova!BM$2)+SUMIFS(topmanager!$D:$D,topmanager!$C:$C,rs_nova!$A18,topmanager!$A:$A,151) -> 0 | BN14: =BF14+BG14+BH14+BI14+P14+O14+W14 -> 0
A15: =total!B11 -> 8 | B15: =IFERROR(IF(E15="",IF(D15<=B$2,30,31-DAY(D15)),IF(E15<B$2,0,IF(D15>=B$2,DAY(E15)-DAY(D15),DAY(E15)))),0) -> 30 | C15: =total!D11 -> Colaborador 8 | D15: =IFERROR(VLOOKUP(A15,salario!A$3:J$32,10,FALSE),"") -> 46023 | E15: =IFERROR(IF(VLOOKUP(A15,salario!A$3:O$32,15,FALSE)="","",VLOOKUP(A15,salario!A$3:O$32,15,FALSE)),"") | F15: =IFERROR(VLOOKUP(A15,[5]base_pessoal!$B$2:$P$1504,13,FALSE),"") | G15: =IFERROR(VLOOKUP(A15,salario!A$2:P$91,11,FALSE),0)*B15/30 -> 5245.5 | H15: =SUMIFS(topmanager!$D:$D,topmanager!$C:$C,rs_nova!$A15,topmanager!$A:$A,rs_nova!H$2)+SUMIFS(topmanager!$D:$D,topmanager!$C:$C,rs_nova!$A15,topmanager!$A:$A,63) -> 0 | I15: =-SUMIFS(topmanager!$D:$D,topmanager!$C:$C,rs_nova!$A15,topmanager!$A:$A,rs_nova!I$2) -> 0 | J15: =SUMIFS(topmanager!$D:$D,topmanager!$C:$C,rs_nova!$A15,topmanager!$A:$A,rs_nova!J$2) -> 0 | K15: =SUMIFS(topmanager!$D:$D,topmanager!$C:$C,rs_nova!$A15,topmanager!$A:$A,rs_nova!K$2)+SUMIFS(topmanager!$D:$D,topmanager!$C:$C,rs_nova!$A15,topmanager!$A:$A,911) -> 0 | L15: =SUMIFS(topmanager!$D:$D,topmanager!$C:$C,rs_nova!$A15,topmanager!$A:$A,rs_nova!L$2) -> 0 | M15: =SUMIFS(topmanager!$D:$D,topmanager!$C:$C,rs_nova!$A15,topmanager!$A:$A,rs_nova!M$2)+SUMIFS(topmanager!$D:$D,topmanager!$C:$C,rs_nova!$A15,topmanager!$A:$A,908)+SUMIFS(topmanager!$D:$D,topmanager!$C:$C,rs_nova!$A15,topmanager!$A:$A,550) -> 0 | N15: =SUMIFS(topmanager!$D:$D,topmanager!$C:$C,rs_nova!$A15,topmanager!$A:$A,rs_nova!N$2) -> 0 | O15: =SUM(H15:N15) -> 0 | P15: =IFERROR(VLOOKUP($A15,total!$B$4:$AW$437,27,0),0) -> 0 | Q15: =IFERROR(VLOOKUP($A15,total!$B$4:$AW$437,21,0),0) -> 0 | R15: =IFERROR(VLOOKUP($A15,total!$B$4:$AW$437,25,0),0)+IFERROR(VLOOKUP($A15,total!$B$4:$AW$437,36,0),0) -> 0 | S15: =IFERROR(VLOOKUP(A15,gympass!$A$2:$F$148,6,0),0) -> 166.66667 | T15: =IFERROR(VLOOKUP($A15,total!$B$4:$AW$437,42,0),0) -> 66.666667 | U15: =IFERROR(VLOOKUP($A15,total!$B$4:$AW$437,32,0),0) -> 0 | V15: =IFERROR(VLOOKUP($A15,total!$B$4:$AW$437,28,0),0) -> 0 | W15: =IFERROR(VLOOKUP($A15,total!$B$4:$AX$437,49,0),0) -> 0 | Y15: =IFERROR(VLOOKUP(A15,#REF!,4,0),0) -> 0 | Z15: =IFERROR(VLOOKUP(B15,#REF!,8,0),0) -> 0 | AA15: =IFERROR(VLOOKUP($A15,total!$B$4:$AW$437,45,0),0) -> 0 | AB15: =IFERROR(VLOOKUP($A15,total!$B$4:$AW$437,48,0),0) -> 0 | AC15: =IFERROR(VLOOKUP($A15,total!$B$4:$AB$437,19,0),0) -> 0 | AD15: =IFERROR(VLOOKUP($A15,total!$B$4:$AB$437,10,0),0) -> 143.446 | AE15: =IFERROR(VLOOKUP($A15,total!$B$4:$AB$437,13,0),0)-SUMIFS(topmanager!$D:$D,topmanager!$C:$C,rs_nova!$A19,topmanager!$A:$A,856) -> 470 | AF15: =IFERROR(VLOOKUP($A15,total!$B$4:$AB$437,16,0),0) -> 8.3796863 | AG15: =IFERROR(VLOOKUP($A15,total!$B$4:$AB$437,7,0),0) -> 0 | AH15: =IFERROR(VLOOKUP($A15,total!$B$4:$AD$437,29,0),0) -> 275 | AI15: =IFERROR(VLOOKUP(A15,total!$B$4:$AN$437,39,0),0) -> 100 | AJ15: =SUM(P15:AI15) -> 1230.159 | AK15: =AK$5*($BN15-BG15) -> 0 | AL15: =AL$5*($BN15+BJ15+BK15+BL15+BM15) -> 0 | AM15: =IF(F15="NÃO",0,AM$5*$BN15) -> 0 | AN15: =IF(AND($A15>1000,$A15<=1999),0,AN$5*$G15) -> 436.95015 | AO15: =IF(AND($A15>1000,$A15<=1999),0,AO$5*$G15) -> 209.82 | AP15: =IF(AND($A15>1000,$A15<=1999),0,AP$5*$G15) -> 183.5925 | AQ15: =IFERROR(VLOOKUP(TEXT($A15,"000000"),[6]Página1!$A$8:$S$801,13,FALSE),0) -> 0 | AR15: =IFERROR(VLOOKUP(TEXT($A15,"000000"),[6]Página1!$A$8:$S$801,16,FALSE),0) -> 0 | AS15: =IFERROR(VLOOKUP(TEXT($A15,"000000"),[6]Página1!$A$8:$S$801,19,FALSE),0) -> 0 | AT15: =IFERROR(VLOOKUP(TEXT($A15,"000000"),[7]Página1!$A$8:$R$814,12,FALSE),0) -> 0 | AU15: =IFERROR(VLOOKUP(TEXT($A15,"000000"),[7]Página1!$A$8:$R$814,15,FALSE),0) -> 0 | AV15: =IFERROR(VLOOKUP(TEXT($A15,"000000"),[7]Página1!$A$8:$R$814,18,FALSE),0) -> 0 | AX15: =SUM(AK15:AW15) -> 830.36265 | AY15: =AN15+AO15+AP15 -> 830.36265 | AZ15: =AX15+AJ15+O15+G15-AY15 -> 6475.659 | BA15: =AX15+AJ15+O15+G15 -> 7306.0217 | BB15: =($G15)/$BB$3 -> 32.784375 | BC15: =$AX15/$BB$3 -> 5.1897666 | BD15: =$AJ15/$BB$3 -> 7.6884939 | BE15: =IFERROR(VLOOKUP(A15,salario!A$2:P$91,11,FALSE),0) -> 5245.5 | BF15: =SUMIFS(topmanager!$D:$D,topmanager!$C:$C,rs_nova!$A15,topmanager!$A:$A,rs_nova!BF$2) -> 0 | BG15: =SUMIFS(topmanager!$D:$D,topmanager!$C:$C,rs_nova!$A15,topmanager!$A:$A,rs_nova!BG$2) -> 0 | BH15: =SUMIFS(topmanager!$D:$D,topmanager!$C:$C,rs_nova!$A15,topmanager!$A:$A,rs_nova!BH$2) -> 0 | BI15: =SUMIFS(topmanager!$D:$D,topmanager!$C:$C,rs_nova!$A15,topmanager!$A:$A,rs_nova!BI$2) -> 0 | BJ15: =SUMIFS(topmanager!$D:$D,topmanager!$C:$C,rs_nova!$A15,topmanager!$A:$A,rs_nova!BJ$2)+SUMIFS(topmanager!$D:$D,topmanager!$C:$C,rs_nova!$A15,topmanager!$A:$A,rs_nova!BJ$2+1) -> 0 | BK15: =IFERROR(VLOOKUP(A15,[8]ferias!$C$4:$G$100,5,FALSE),0) -> 0 | BL15: =SUMIFS(topmanager!$D:$D,topmanager!$C:$C,rs_nova!$A15,topmanager!$A:$A,rs_nova!BL$2) -> 0 | BM15: =SUMIFS(topmanager!$D:$D,topmanager!$C:$C,rs_nova!$A15,topmanager!$A:$A,rs_nova!BM$2)+SUMIFS(topmanager!$D:$D,topmanager!$C:$C,rs_nova!$A19,topmanager!$A:$A,151) -> 0 | BN15: =BF15+BG15+BH15+BI15+P15+O15+W15 -> 0
A16: =total!B12 -> 9 | B16: =IFERROR(IF(E16="",IF(D16<=B$2,30,31-DAY(D16)),IF(E16<B$2,0,IF(D16>=B$2,DAY(E16)-DAY(D16),DAY(E16)))),0) -> 30 | C16: =total!D12 -> Colaborador 9 | D16: =IFERROR(VLOOKUP(A16,salario!A$3:J$32,10,FALSE),"") -> 46023 | E16: =IFERROR(IF(VLOOKUP(A16,salario!A$3:O$32,15,FALSE)="","",VLOOKUP(A16,salario!A$3:O$32,15,FALSE)),"") | F16: =IFERROR(VLOOKUP(A16,[5]base_pessoal!$B$2:$P$1504,13,FALSE),"") | G16: =IFERROR(VLOOKUP(A16,salario!A$2:P$91,11,FALSE),0)*B16/30 -> 4229.32 | H16: =SUMIFS(topmanager!$D:$D,topmanager!$C:$C,rs_nova!$A16,topmanager!$A:$A,rs_nova!H$2)+SUMIFS(topmanager!$D:$D,topmanager!$C:$C,rs_nova!$A16,topmanager!$A:$A,63) -> 0 | I16: =-SUMIFS(topmanager!$D:$D,topmanager!$C:$C,rs_nova!$A16,topmanager!$A:$A,rs_nova!I$2) -> 0 | J16: =SUMIFS(topmanager!$D:$D,topmanager!$C:$C,rs_nova!$A16,topmanager!$A:$A,rs_nova!J$2) -> 0 | K16: =SUMIFS(topmanager!$D:$D,topmanager!$C:$C,rs_nova!$A16,topmanager!$A:$A,rs_nova!K$2)+SUMIFS(topmanager!$D:$D,topmanager!$C:$C,rs_nova!$A16,topmanager!$A:$A,911) -> 0 | L16: =SUMIFS(topmanager!$D:$D,topmanager!$C:$C,rs_nova!$A16,topmanager!$A:$A,rs_nova!L$2) -> 0 | M16: =SUMIFS(topmanager!$D:$D,topmanager!$C:$C,rs_nova!$A16,topmanager!$A:$A,rs_nova!M$2)+SUMIFS(topmanager!$D:$D,topmanager!$C:$C,rs_nova!$A16,topmanager!$A:$A,908)+SUMIFS(topmanager!$D:$D,topmanager!$C:$C,rs_nova!$A16,topmanager!$A:$A,550) -> 0 | N16: =SUMIFS(topmanager!$D:$D,topmanager!$C:$C,rs_nova!$A16,topmanager!$A:$A,rs_nova!N$2) -> 0 | O16: =SUM(H16:N16) -> 0 | P16: =IFERROR(VLOOKUP($A16,total!$B$4:$AW$437,27,0),0) -> 0 | Q16: =IFERROR(VLOOKUP($A16,total!$B$4:$AW$437,21,0),0) -> 0 | R16: =IFERROR(VLOOKUP($A16,total!$B$4:$AW$437,25,0),0)+IFERROR(VLOOKUP($A16,total!$B$4:$AW$437,36,0),0) -> 0 | S16: =IFERROR(VLOOKUP(A16,gympass!$A$2:$F$148,6,0),0) -> 166.66667 | T16: =IFERROR(VLOOKUP($A16,total!$B$4:$AW$437,42,0),0) -> 66.666667 | U16: =IFERROR(VLOOKUP($A16,total!$B$4:$AW$437,32,0),0) -> 0 | V16: =IFERROR(VLOOKUP($A16,total!$B$4:$AW$437,28,0),0) -> 0 | W16: =IFERROR(VLOOKUP($A16,total!$B$4:$AX$437,49,0),0) -> 0 | Y16: =IFERROR(VLOOKUP(A16,#REF!,4,0),0) -> 0 | Z16: =IFERROR(VLOOKUP(B16,#REF!,8,0),0) -> 0 | AA16: =IFERROR(VLOOKUP($A16,total!$B$4:$AW$437,45,0),0) -> 0 | AB16: =IFERROR(VLOOKUP($A16,total!$B$4:$AW$437,48,0),0) -> 0 | AC16: =IFERROR(VLOOKUP($A16,total!$B$4:$AB$437,19,0),0) -> 0 | AD16: =IFERROR(VLOOKUP($A16,total!$B$4:$AB$437,10,0),0) -> 107.5845 | AE16: =IFERROR(VLOOKUP($A16,total!$B$4:$AB$437,13,0),0)-SUMIFS(topmanager!$D:$D,topmanager!$C:$C,rs_nova!$A20,topmanager!$A:$A,856) -> 470 | AF16: =IFERROR(VLOOKUP($A16,total!$B$4:$AB$437,16,0),0) -> 6.7563387 | AG16: =IFERROR(VLOOKUP($A16,total!$B$4:$AB$437,7,0),0) -> 0 | AH16: =IFERROR(VLOOKUP($A16,total!$B$4:$AD$437,29,0),0) -> 275 | AI16: =IFERROR(VLOOKUP(A16,total!$B$4:$AN$437,39,0),0) -> - | AJ16: =SUM(P16:AI16) -> 1092.6742 | AK16: =AK$5*($BN16-BG16) -> 0 | AL16: =AL$5*($BN16+BJ16+BK16+BL16+BM16) -> 0 | AM16: =IF(F16="NÃO",0,AM$5*$BN16) -> 0 | AN16: =IF(AND($A16>1000,$A16<=1999),0,AN$5*$G16) -> 352.30236 | AO16: =IF(AND($A16>1000,$A16<=1999),0,AO$5*$G16) -> 169.1728 | AP16: =IF(AND($A16>1000,$A16<=1999),0,AP$5*$G16) -> 148.0262 | AQ16: =IFERROR(VLOOKUP(TEXT($A16,"000000"),[6]Página1!$A$8:$S$801,13,FALSE),0) -> 0 | AR16: =IFERROR(VLOOKUP(TEXT($A16,"000000"),[6]Página1!$A$8:$S$801,16,FALSE),0) -> 0 | AS16: =IFERROR(VLOOKUP(TEXT($A16,"000000"),[6]Página1!$A$8:$S$801,19,FALSE),0) -> 0 | AT16: =IFERROR(VLOOKUP(TEXT($A16,"000000"),[7]Página1!$A$8:$R$814,12,FALSE),0) -> 0 | AU16: =IFERROR(VLOOKUP(TEXT($A16,"000000"),[7]Página1!$A$8:$R$814,15,FALSE),0) -> 0 | AV16: =IFERROR(VLOOKUP(TEXT($A16,"000000"),[7]Página1!$A$8:$R$814,18,FALSE),0) -> 0 | AX16: =SUM(AK16:AW16) -> 669.50136 | AY16: =AN16+AO16+AP16 -> 669.50136 | AZ16: =AX16+AJ16+O16+G16-AY16 -> 5321.9942 | BA16: =AX16+AJ16+O16+G16 -> 5991.4955 | BB16: =($G16)/$BB$3 -> 26.43325 | BC16: =$AX16/$BB$3 -> 4.1843835 | BD16: =$AJ16/$BB$3 -> 6.8292136 | BE16: =IFERROR(VLOOKUP(A16,salario!A$2:P$91,11,FALSE),0) -> 4229.32 | BF16: =SUMIFS(topmanager!$D:$D,topmanager!$C:$C,rs_nova!$A16,topmanager!$A:$A,rs_nova!BF$2) -> 0 | BG16: =SUMIFS(topmanager!$D:$D,topmanager!$C:$C,rs_nova!$A16,topmanager!$A:$A,rs_nova!BG$2) -> 0 | BH16: =SUMIFS(topmanager!$D:$D,topmanager!$C:$C,rs_nova!$A16,topmanager!$A:$A,rs_nova!BH$2) -> 0 | BI16: =SUMIFS(topmanager!$D:$D,topmanager!$C:$C,rs_nova!$A16,topmanager!$A:$A,rs_nova!BI$2) -> 0 | BJ16: =SUMIFS(topmanager!$D:$D,topmanager!$C:$C,rs_nova!$A16,topmanager!$A:$A,rs_nova!BJ$2)+SUMIFS(topmanager!$D:$D,topmanager!$C:$C,rs_nova!$A16,topmanager!$A:$A,rs_nova!BJ$2+1) -> 0 | BK16: =IFERROR(VLOOKUP(A16,[8]ferias!$C$4:$G$100,5,FALSE),0) -> 0 | BL16: =SUMIFS(topmanager!$D:$D,topmanager!$C:$C,rs_nova!$A16,topmanager!$A:$A,rs_nova!BL$2) -> 0 | BM16: =SUMIFS(topmanager!$D:$D,topmanager!$C:$C,rs_nova!$A16,topmanager!$A:$A,rs_nova!BM$2)+SUMIFS(topmanager!$D:$D,topmanager!$C:$C,rs_nova!$A20,topmanager!$A:$A,151) -> 0 | BN16: =BF16+BG16+BH16+BI16+P16+O16+W16 -> 0
A17: =total!B13 -> 10 | B17: =IFERROR(IF(E17="",IF(D17<=B$2,30,31-DAY(D17)),IF(E17<B$2,0,IF(D17>=B$2,DAY(E17)-DAY(D17),DAY(E17)))),0) -> 30 | C17: =total!D13 -> Colaborador 10 | D17: =IFERROR(VLOOKUP(A17,salario!A$3:J$32,10,FALSE),"") -> 46023 | E17: =IFERROR(IF(VLOOKUP(A17,salario!A$3:O$32,15,FALSE)="","",VLOOKUP(A17,salario!A$3:O$32,15,FALSE)),"") | F17: =IFERROR(VLOOKUP(A17,[5]base_pessoal!$B$2:$P$1504,13,FALSE),"") | G17: =IFERROR(VLOOKUP(A17,salario!A$2:P$91,11,FALSE),0)*B17/30 -> 2404.84 | H17: =SUMIFS(topmanager!$D:$D,topmanager!$C:$C,rs_nova!$A17,topmanager!$A:$A,rs_nova!H$2)+SUMIFS(topmanager!$D:$D,topmanager!$C:$C,rs_nova!$A17,topmanager!$A:$A,63) -> 0 | I17: =-SUMIFS(topmanager!$D:$D,topmanager!$C:$C,rs_nova!$A17,topmanager!$A:$A,rs_nova!I$2) -> 0 | J17: =SUMIFS(topmanager!$D:$D,topmanager!$C:$C,rs_nova!$A17,topmanager!$A:$A,rs_nova!J$2) -> 0 | K17: =SUMIFS(topmanager!$D:$D,topmanager!$C:$C,rs_nova!$A17,topmanager!$A:$A,rs_nova!K$2)+SUMIFS(topmanager!$D:$D,topmanager!$C:$C,rs_nova!$A17,topmanager!$A:$A,911) -> 0 | L17: =SUMIFS(topmanager!$D:$D,topmanager!$C:$C,rs_nova!$A17,topmanager!$A:$A,rs_nova!L$2) -> 0 | M17: =SUMIFS(topmanager!$D:$D,topmanager!$C:$C,rs_nova!$A17,topmanager!$A:$A,rs_nova!M$2)+SUMIFS(topmanager!$D:$D,topmanager!$C:$C,rs_nova!$A17,topmanager!$A:$A,908)+SUMIFS(topmanager!$D:$D,topmanager!$C:$C,rs_nova!$A17,topmanager!$A:$A,550) -> 0 | N17: =SUMIFS(topmanager!$D:$D,topmanager!$C:$C,rs_nova!$A17,topmanager!$A:$A,rs_nova!N$2) -> 0 | O17: =SUM(H17:N17) -> 0 | P17: =IFERROR(VLOOKUP($A17,total!$B$4:$AW$437,27,0),0) -> 0 | Q17: =IFERROR(VLOOKUP($A17,total!$B$4:$AW$437,21,0),0) -> 0 | R17: =IFERROR(VLOOKUP($A17,total!$B$4:$AW$437,25,0),0)+IFERROR(VLOOKUP($A17,total!$B$4:$AW$437,36,0),0) -> 0 | S17: =IFERROR(VLOOKUP(A17,gympass!$A$2:$F$148,6,0),0) -> 166.66667 | T17: =IFERROR(VLOOKUP($A17,total!$B$4:$AW$437,42,0),0) -> 66.666667 | U17: =IFERROR(VLOOKUP($A17,total!$B$4:$AW$437,32,0),0) -> 0 | V17: =IFERROR(VLOOKUP($A17,total!$B$4:$AW$437,28,0),0) -> 0 | W17: =IFERROR(VLOOKUP($A17,total!$B$4:$AX$437,49,0),0) -> 0 | Y17: =IFERROR(VLOOKUP(A17,#REF!,4,0),0) -> 0 | Z17: =IFERROR(VLOOKUP(B17,#REF!,8,0),0) -> 0 | AA17: =IFERROR(VLOOKUP($A17,total!$B$4:$AW$437,45,0),0) -> 0 | AB17: =IFERROR(VLOOKUP($A17,total!$B$4:$AW$437,48,0),0) -> 0 | AC17: =IFERROR(VLOOKUP($A17,total!$B$4:$AB$437,19,0),0) -> 0 | AD17: =IFERROR(VLOOKUP($A17,total!$B$4:$AB$437,10,0),0) -> 117.7101 | AE17: =IFERROR(VLOOKUP($A17,total!$B$4:$AB$437,13,0),0)-SUMIFS(topmanager!$D:$D,topmanager!$C:$C,rs_nova!$A21,topmanager!$A:$A,856) -> 490 | AF17: =IFERROR(VLOOKUP($A17,total!$B$4:$AB$437,16,0),0) -> 3.8417319 | AG17: =IFERROR(VLOOKUP($A17,total!$B$4:$AB$437,7,0),0) -> 0 | AH17: =IFERROR(VLOOKUP($A17,total!$B$4:$AD$437,29,0),0) -> 275 | AI17: =IFERROR(VLOOKUP(A17,total!$B$4:$AN$437,39,0),0) -> - | AJ17: =SUM(P17:AI17) -> 1119.8852 | AK17: =AK$5*($BN17-BG17) -> 0 | AL17: =AL$5*($BN17+BJ17+BK17+BL17+BM17) -> 0 | AM17: =IF(F17="NÃO",0,AM$5*$BN17) -> 0 | AN17: =IF(AND($A17>1000,$A17<=1999),0,AN$5*$G17) -> 200.32317 | AO17: =IF(AND($A17>1000,$A17<=1999),0,AO$5*$G17) -> 96.1936 | AP17: =IF(AND($A17>1000,$A17<=1999),0,AP$5*$G17) -> 84.1694 | AQ17: =IFERROR(VLOOKUP(TEXT($A17,"000000"),[6]Página1!$A$8:$S$801,13,FALSE),0) -> 0 | AR17: =IFERROR(VLOOKUP(TEXT($A17,"000000"),[6]Página1!$A$8:$S$801,16,FALSE),0) -> 0 | AS17: =IFERROR(VLOOKUP(TEXT($A17,"000000"),[6]Página1!$A$8:$S$801,19,FALSE),0) -> 0 | AT17: =IFERROR(VLOOKUP(TEXT($A17,"000000"),[7]Página1!$A$8:$R$814,12,FALSE),0) -> 0 | AU17: =IFERROR(VLOOKUP(TEXT($A17,"000000"),[7]Página1!$A$8:$R$814,15,FALSE),0) -> 0 | AV17: =IFERROR(VLOOKUP(TEXT($A17,"000000"),[7]Página1!$A$8:$R$814,18,FALSE),0) -> 0 | AX17: =SUM(AK17:AW17) -> 380.68617 | AY17: =AN17+AO17+AP17 -> 380.68617 | AZ17: =AX17+AJ17+O17+G17-AY17 -> 3524.7252 | BA17: =AX17+AJ17+O17+G17 -> 3905.4113 | BB17: =($G17)/$BB$3 -> 15.03025 | BC17: =$AX17/$BB$3 -> 2.3792886 | BD17: =$AJ17/$BB$3 -> 6.9992823 | BE17: =IFERROR(VLOOKUP(A17,salario!A$2:P$91,11,FALSE),0) -> 2404.84 | BF17: =SUMIFS(topmanager!$D:$D,topmanager!$C:$C,rs_nova!$A17,topmanager!$A:$A,rs_nova!BF$2) -> 0 | BG17: =SUMIFS(topmanager!$D:$D,topmanager!$C:$C,rs_nova!$A17,topmanager!$A:$A,rs_nova!BG$2) -> 0 | BH17: =SUMIFS(topmanager!$D:$D,topmanager!$C:$C,rs_nova!$A17,topmanager!$A:$A,rs_nova!BH$2) -> 0 | BI17: =SUMIFS(topmanager!$D:$D,topmanager!$C:$C,rs_nova!$A17,topmanager!$A:$A,rs_nova!BI$2) -> 0 | BJ17: =SUMIFS(topmanager!$D:$D,topmanager!$C:$C,rs_nova!$A17,topmanager!$A:$A,rs_nova!BJ$2)+SUMIFS(topmanager!$D:$D,topmanager!$C:$C,rs_nova!$A17,topmanager!$A:$A,rs_nova!BJ$2+1) -> 0 | BK17: =IFERROR(VLOOKUP(A17,[8]ferias!$C$4:$G$100,5,FALSE),0) -> 0 | BL17: =SUMIFS(topmanager!$D:$D,topmanager!$C:$C,rs_nova!$A17,topmanager!$A:$A,rs_nova!BL$2) -> 0 | BM17: =SUMIFS(topmanager!$D:$D,topmanager!$C:$C,rs_nova!$A17,topmanager!$A:$A,rs_nova!BM$2)+SUMIFS(topmanager!$D:$D,topmanager!$C:$C,rs_nova!$A21,topmanager!$A:$A,151) -> 0 | BN17: =BF17+BG17+BH17+BI17+P17+O17+W17 -> 0
A18: =total!B14 -> 11 | B18: =IFERROR(IF(E18="",IF(D18<=B$2,30,31-DAY(D18)),IF(E18<B$2,0,IF(D18>=B$2,DAY(E18)-DAY(D18),DAY(E18)))),0) -> 30 | C18: =total!D14 -> Colaborador 11 | D18: =IFERROR(VLOOKUP(A18,salario!A$3:J$32,10,FALSE),"") -> 46023 | E18: =IFERROR(IF(VLOOKUP(A18,salario!A$3:O$32,15,FALSE)="","",VLOOKUP(A18,salario!A$3:O$32,15,FALSE)),"") | F18: =IFERROR(VLOOKUP(A18,[5]base_pessoal!$B$2:$P$1504,13,FALSE),"") | G18: =IFERROR(VLOOKUP(A18,salario!A$2:P$91,11,FALSE),0)*B18/30 -> 2335.03 | H18: =SUMIFS(topmanager!$D:$D,topmanager!$C:$C,rs_nova!$A18,topmanager!$A:$A,rs_nova!H$2)+SUMIFS(topmanager!$D:$D,topmanager!$C:$C,rs_nova!$A18,topmanager!$A:$A,63) -> 0 | I18: =-SUMIFS(topmanager!$D:$D,topmanager!$C:$C,rs_nova!$A18,topmanager!$A:$A,rs_nova!I$2) -> 0 | J18: =SUMIFS(topmanager!$D:$D,topmanager!$C:$C,rs_nova!$A18,topmanager!$A:$A,rs_nova!J$2) -> 0 | K18: =SUMIFS(topmanager!$D:$D,topmanager!$C:$C,rs_nova!$A18,topmanager!$A:$A,rs_nova!K$2)+SUMIFS(topmanager!$D:$D,topmanager!$C:$C,rs_nova!$A18,topmanager!$A:$A,911) -> 0 | L18: =SUMIFS(topmanager!$D:$D,topmanager!$C:$C,rs_nova!$A18,topmanager!$A:$A,rs_nova!L$2) -> 0 | M18: =SUMIFS(topmanager!$D:$D,topmanager!$C:$C,rs_nova!$A18,topmanager!$A:$A,rs_nova!M$2)+SUMIFS(topmanager!$D:$D,topmanager!$C:$C,rs_nova!$A18,topmanager!$A:$A,908)+SUMIFS(topmanager!$D:$D,topmanager!$C:$C,rs_nova!$A18,topmanager!$A:$A,550) -> 0 | N18: =SUMIFS(topmanager!$D:$D,topmanager!$C:$C,rs_nova!$A18,topmanager!$A:$A,rs_nova!N$2) -> 0 | O18: =SUM(H18:N18) -> 0 | P18: =IFERROR(VLOOKUP($A18,total!$B$4:$AW$437,27,0),0) -> 0 | Q18: =IFERROR(VLOOKUP($A18,total!$B$4:$AW$437,21,0),0) -> 0 | R18: =IFERROR(VLOOKUP($A18,total!$B$4:$AW$437,25,0),0)+IFERROR(VLOOKUP($A18,total!$B$4:$AW$437,36,0),0) -> 0 | S18: =IFERROR(VLOOKUP(A18,gympass!$A$2:$F$148,6,0),0) -> 166.66667 | T18: =IFERROR(VLOOKUP($A18,total!$B$4:$AW$437,42,0),0) -> 66.666667 | U18: =IFERROR(VLOOKUP($A18,total!$B$4:$AW$437,32,0),0) -> 0 | V18: =IFERROR(VLOOKUP($A18,total!$B$4:$AW$437,28,0),0) -> 0 | W18: =IFERROR(VLOOKUP($A18,total!$B$4:$AX$437,49,0),0) -> 0 | Y18: =IFERROR(VLOOKUP(A18,#REF!,4,0),0) -> 0 | Z18: =IFERROR(VLOOKUP(B18,#REF!,8,0),0) -> 0 | AA18: =IFERROR(VLOOKUP($A18,total!$B$4:$AW$437,45,0),0) -> 0 | AB18: =IFERROR(VLOOKUP($A18,total!$B$4:$AW$437,48,0),0) -> 0 | AC18: =IFERROR(VLOOKUP($A18,total!$B$4:$AB$437,19,0),0) -> 0 | AD18: =IFERROR(VLOOKUP($A18,total!$B$4:$AB$437,10,0),0) -> 117.7101 | AE18: =IFERROR(VLOOKUP($A18,total!$B$4:$AB$437,13,0),0)-SUMIFS(topmanager!$D:$D,topmanager!$C:$C,rs_nova!$A22,topmanager!$A:$A,856) -> 490 | AF18: =IFERROR(VLOOKUP($A18,total!$B$4:$AB$437,16,0),0) -> 3.7302104 | AG18: =IFERROR(VLOOKUP($A18,total!$B$4:$AB$437,7,0),0) -> 0 | AH18: =IFERROR(VLOOKUP($A18,total!$B$4:$AD$437,29,0),0) -> 275 | AI18: =IFERROR(VLOOKUP(A18,total!$B$4:$AN$437,39,0),0) -> - | AJ18: =SUM(P18:AI18) -> 1119.7736 | AK18: =AK$5*($BN18-BG18) -> 0 | AL18: =AL$5*($BN18+BJ18+BK18+BL18+BM18) -> 0 | AM18: =IF(F18="NÃO",0,AM$5*$BN18) -> 0 | AN18: =IF(AND($A18>1000,$A18<=1999),0,AN$5*$G18) -> 194.508 | AO18: =IF(AND($A18>1000,$A18<=1999),0,AO$5*$G18) -> 93.4012 | AP18: =IF(AND($A18>1000,$A18<=1999),0,AP$5*$G18) -> 81.72605 | AQ18: =IFERROR(VLOOKUP(TEXT($A18,"000000"),[6]Página1!$A$8:$S$801,13,FALSE),0) -> 0 | AR18: =IFERROR(VLOOKUP(TEXT($A18,"000000"),[6]Página1!$A$8:$S$801,16,FALSE),0) -> 0 | AS18: =IFERROR(VLOOKUP(TEXT($A18,"000000"),[6]Página1!$A$8:$S$801,19,FALSE),0) -> 0 | AT18: =IFERROR(VLOOKUP(TEXT($A18,"000000"),[7]Página1!$A$8:$R$814,12,FALSE),0) -> 0 | AU18: =IFERROR(VLOOKUP(TEXT($A18,"000000"),[7]Página1!$A$8:$R$814,15,FALSE),0) -> 0 | AV18: =IFERROR(VLOOKUP(TEXT($A18,"000000"),[7]Página1!$A$8:$R$814,18,FALSE),0) -> 0 | AX18: =SUM(AK18:AW18) -> 369.63525 | AY18: =AN18+AO18+AP18 -> 369.63525 | AZ18: =AX18+AJ18+O18+G18-AY18 -> 3454.8036 | BA18: =AX18+AJ18+O18+G18 -> 3824.4389 | BB18: =($G18)/$BB$3 -> 14.593938 | BC18: =$AX18/$BB$3 -> 2.3102203 | BD18: =$AJ18/$BB$3 -> 6.9985853 | BE18: =IFERROR(VLOOKUP(A18,salario!A$2:P$91,11,FALSE),0) -> 2335.03 | BF18: =SUMIFS(topmanager!$D:$D,topmanager!$C:$C,rs_nova!$A18,topmanager!$A:$A,rs_nova!BF$2) -> 0 | BG18: =SUMIFS(topmanager!$D:$D,topmanager!$C:$C,rs_nova!$A18,topmanager!$A:$A,rs_nova!BG$2) -> 0 | BH18: =SUMIFS(topmanager!$D:$D,topmanager!$C:$C,rs_nova!$A18,topmanager!$A:$A,rs_nova!BH$2) -> 0 | BI18: =SUMIFS(topmanager!$D:$D,topmanager!$C:$C,rs_nova!$A18,topmanager!$A:$A,rs_nova!BI$2) -> 0 | BJ18: =SUMIFS(topmanager!$D:$D,topmanager!$C:$C,rs_nova!$A18,topmanager!$A:$A,rs_nova!BJ$2)+SUMIFS(topmanager!$D:$D,topmanager!$C:$C,rs_nova!$A18,topmanager!$A:$A,rs_nova!BJ$2+1) -> 0 | BK18: =IFERROR(VLOOKUP(A18,[8]ferias!$C$4:$G$100,5,FALSE),0) -> 0 | BL18: =SUMIFS(topmanager!$D:$D,topmanager!$C:$C,rs_nova!$A18,topmanager!$A:$A,rs_nova!BL$2) -> 0 | BM18: =SUMIFS(topmanager!$D:$D,topmanager!$C:$C,rs_nova!$A18,topmanager!$A:$A,rs_nova!BM$2)+SUMIFS(topmanager!$D:$D,topmanager!$C:$C,rs_nova!$A22,topmanager!$A:$A,151) -> 0 | BN18: =BF18+BG18+BH18+BI18+P18+O18+W18 -> 0
A19: =total!B15 -> 12 | B19: =IFERROR(IF(E19="",IF(D19<=B$2,30,31-DAY(D19)),IF(E19<B$2,0,IF(D19>=B$2,DAY(E19)-DAY(D19),DAY(E19)))),0) -> 30 | C19: =total!D15 -> Colaborador 12 | D19: =IFERROR(VLOOKUP(A19,salario!A$3:J$32,10,FALSE),"") -> 46023 | E19: =IFERROR(IF(VLOOKUP(A19,salario!A$3:O$32,15,FALSE)="","",VLOOKUP(A19,salario!A$3:O$32,15,FALSE)),"") | F19: =IFERROR(VLOOKUP(A19,[5]base_pessoal!$B$2:$P$1504,13,FALSE),"") | G19: =IFERROR(VLOOKUP(A19,salario!A$2:P$91,11,FALSE),0)*B19/30 -> 3290.79 | H19: =SUMIFS(topmanager!$D:$D,topmanager!$C:$C,rs_nova!$A19,topmanager!$A:$A,rs_nova!H$2)+SUMIFS(topmanager!$D:$D,topmanager!$C:$C,rs_nova!$A19,topmanager!$A:$A,63) -> 0 | I19: =-SUMIFS(topmanager!$D:$D,topmanager!$C:$C,rs_nova!$A19,topmanager!$A:$A,rs_nova!I$2) -> 0 | J19: =SUMIFS(topmanager!$D:$D,topmanager!$C:$C,rs_nova!$A19,topmanager!$A:$A,rs_nova!J$2) -> 0 | K19: =SUMIFS(topmanager!$D:$D,topmanager!$C:$C,rs_nova!$A19,topmanager!$A:$A,rs_nova!K$2)+SUMIFS(topmanager!$D:$D,topmanager!$C:$C,rs_nova!$A19,topmanager!$A:$A,911) -> 0 | L19: =SUMIFS(topmanager!$D:$D,topmanager!$C:$C,rs_nova!$A19,topmanager!$A:$A,rs_nova!L$2) -> 0 | M19: =SUMIFS(topmanager!$D:$D,topmanager!$C:$C,rs_nova!$A19,topmanager!$A:$A,rs_nova!M$2)+SUMIFS(topmanager!$D:$D,topmanager!$C:$C,rs_nova!$A19,topmanager!$A:$A,908)+SUMIFS(topmanager!$D:$D,topmanager!$C:$C,rs_nova!$A19,topmanager!$A:$A,550) -> 0 | N19: =SUMIFS(topmanager!$D:$D,topmanager!$C:$C,rs_nova!$A19,topmanager!$A:$A,rs_nova!N$2) -> 0 | O19: =SUM(H19:N19) -> 0 | P19: =IFERROR(VLOOKUP($A19,total!$B$4:$AW$437,27,0),0) -> 0 | Q19: =IFERROR(VLOOKUP($A19,total!$B$4:$AW$437,21,0),0) -> 0 | R19: =IFERROR(VLOOKUP($A19,total!$B$4:$AW$437,25,0),0)+IFERROR(VLOOKUP($A19,total!$B$4:$AW$437,36,0),0) -> 0 | S19: =IFERROR(VLOOKUP(A19,gympass!$A$2:$F$148,6,0),0) -> 166.66667 | T19: =IFERROR(VLOOKUP($A19,total!$B$4:$AW$437,42,0),0) -> 66.666667 | U19: =IFERROR(VLOOKUP($A19,total!$B$4:$AW$437,32,0),0) -> 0 | V19: =IFERROR(VLOOKUP($A19,total!$B$4:$AW$437,28,0),0) -> 0 | W19: =IFERROR(VLOOKUP($A19,total!$B$4:$AX$437,49,0),0) -> 0 | Y19: =IFERROR(VLOOKUP(A19,#REF!,4,0),0) -> 0 | Z19: =IFERROR(VLOOKUP(B19,#REF!,8,0),0) -> 0 | AA19: =IFERROR(VLOOKUP($A19,total!$B$4:$AW$437,45,0),0) -> 0 | AB19: =IFERROR(VLOOKUP($A19,total!$B$4:$AW$437,48,0),0) -> 0 | AC19: =IFERROR(VLOOKUP($A19,total!$B$4:$AB$437,19,0),0) -> 0 | AD19: =IFERROR(VLOOKUP($A19,total!$B$4:$AB$437,10,0),0) -> 39.2367 | AE19: =IFERROR(VLOOKUP($A19,total!$B$4:$AB$437,13,0),0)-SUMIFS(topmanager!$D:$D,topmanager!$C:$C,rs_nova!$A23,topmanager!$A:$A,856) -> 490 | AF19: =IFERROR(VLOOKUP($A19,total!$B$4:$AB$437,16,0),0) -> 5.257037 | AG19: =IFERROR(VLOOKUP($A19,total!$B$4:$AB$437,7,0),0) -> 0 | AH19: =IFERROR(VLOOKUP($A19,total!$B$4:$AD$437,29,0),0) -> 275 | AI19: =IFERROR(VLOOKUP(A19,total!$B$4:$AN$437,39,0),0) -> - | AJ19: =SUM(P19:AI19) -> 1042.8271 | AK19: =AK$5*($BN19-BG19) -> 0 | AL19: =AL$5*($BN19+BJ19+BK19+BL19+BM19) -> 0 | AM19: =IF(F19="NÃO",0,AM$5*$BN19) -> 0 | AN19: =IF(AND($A19>1000,$A19<=1999),0,AN$5*$G19) -> 274.12281 | AO19: =IF(AND($A19>1000,$A19<=1999),0,AO$5*$G19) -> 131.6316 | AP19: =IF(AND($A19>1000,$A19<=1999),0,AP$5*$G19) -> 115.17765 | AQ19: =IFERROR(VLOOKUP(TEXT($A19,"000000"),[6]Página1!$A$8:$S$801,13,FALSE),0) -> 0 | AR19: =IFERROR(VLOOKUP(TEXT($A19,"000000"),[6]Página1!$A$8:$S$801,16,FALSE),0) -> 0 | AS19: =IFERROR(VLOOKUP(TEXT($A19,"000000"),[6]Página1!$A$8:$S$801,19,FALSE),0) -> 0 | AT19: =IFERROR(VLOOKUP(TEXT($A19,"000000"),[7]Página1!$A$8:$R$814,12,FALSE),0) -> 0 | AU19: =IFERROR(VLOOKUP(TEXT($A19,"000000"),[7]Página1!$A$8:$R$814,15,FALSE),0) -> 0 | AV19: =IFERROR(VLOOKUP(TEXT($A19,"000000"),[7]Página1!$A$8:$R$814,18,FALSE),0) -> 0 | AX19: =SUM(AK19:AW19) -> 520.93206 | AY19: =AN19+AO19+AP19 -> 520.93206 | AZ19: =AX19+AJ19+O19+G19-AY19 -> 4333.6171 | BA19: =AX19+AJ19+O19+G19 -> 4854.5491 | BB19: =($G19)/$BB$3 -> 20.567438 | BC19: =$AX19/$BB$3 -> 3.2558254 | BD19: =$AJ19/$BB$3 -> 6.5176692 | BE19: =IFERROR(VLOOKUP(A19,salario!A$2:P$91,11,FALSE),0) -> 3290.79 | BF19: =SUMIFS(topmanager!$D:$D,topmanager!$C:$C,rs_nova!$A19,topmanager!$A:$A,rs_nova!BF$2) -> 0 | BG19: =SUMIFS(topmanager!$D:$D,topmanager!$C:$C,rs_nova!$A19,topmanager!$A:$A,rs_nova!BG$2) -> 0 | BH19: =SUMIFS(topmanager!$D:$D,topmanager!$C:$C,rs_nova!$A19,topmanager!$A:$A,rs_nova!BH$2) -> 0 | BI19: =SUMIFS(topmanager!$D:$D,topmanager!$C:$C,rs_nova!$A19,topmanager!$A:$A,rs_nova!BI$2) -> 0 | BJ19: =SUMIFS(topmanager!$D:$D,topmanager!$C:$C,rs_nova!$A19,topmanager!$A:$A,rs_nova!BJ$2)+SUMIFS(topmanager!$D:$D,topmanager!$C:$C,rs_nova!$A19,topmanager!$A:$A,rs_nova!BJ$2+1) -> 0 | BK19: =IFERROR(VLOOKUP(A19,[8]ferias!$C$4:$G$100,5,FALSE),0) -> 0 | BL19: =SUMIFS(topmanager!$D:$D,topmanager!$C:$C,rs_nova!$A19,topmanager!$A:$A,rs_nova!BL$2) -> 0 | BM19: =SUMIFS(topmanager!$D:$D,topmanager!$C:$C,rs_nova!$A19,topmanager!$A:$A,rs_nova!BM$2)+SUMIFS(topmanager!$D:$D,topmanager!$C:$C,rs_nova!$A23,topmanager!$A:$A,151) -> 0 | BN19: =BF19+BG19+BH19+BI19+P19+O19+W19 -> 0
A20: =total!B16 -> 13 | B20: =IFERROR(IF(E20="",IF(D20<=B$2,30,31-DAY(D20)),IF(E20<B$2,0,IF(D20>=B$2,DAY(E20)-DAY(D20),DAY(E20)))),0) -> 30 | C20: =total!D16 -> Colaborador 13 | D20: =IFERROR(VLOOKUP(A20,salario!A$3:J$32,10,FALSE),"") -> 46023 | E20: =IFERROR(IF(VLOOKUP(A20,salario!A$3:O$32,15,FALSE)="","",VLOOKUP(A20,salario!A$3:O$32,15,FALSE)),"") | F20: =IFERROR(VLOOKUP(A20,[5]base_pessoal!$B$2:$P$1504,13,FALSE),"") | G20: =IFERROR(VLOOKUP(A20,salario!A$2:P$91,11,FALSE),0)*B20/30 -> 1102.16 | H20: =SUMIFS(topmanager!$D:$D,topmanager!$C:$C,rs_nova!$A20,topmanager!$A:$A,rs_nova!H$2)+SUMIFS(topmanager!$D:$D,topmanager!$C:$C,rs_nova!$A20,topmanager!$A:$A,63) -> 0 | I20: =-SUMIFS(topmanager!$D:$D,topmanager!$C:$C,rs_nova!$A20,topmanager!$A:$A,rs_nova!I$2) -> 0 | J20: =SUMIFS(topmanager!$D:$D,topmanager!$C:$C,rs_nova!$A20,topmanager!$A:$A,rs_nova!J$2) -> 0 | K20: =SUMIFS(topmanager!$D:$D,topmanager!$C:$C,rs_nova!$A20,topmanager!$A:$A,rs_nova!K$2)+SUMIFS(topmanager!$D:$D,topmanager!$C:$C,rs_nova!$A20,topmanager!$A:$A,911) -> 0 | L20: =SUMIFS(topmanager!$D:$D,topmanager!$C:$C,rs_nova!$A20,topmanager!$A:$A,rs_nova!L$2) -> 0 | M20: =SUMIFS(topmanager!$D:$D,topmanager!$C:$C,rs_nova!$A20,topmanager!$A:$A,rs_nova!M$2)+SUMIFS(topmanager!$D:$D,topmanager!$C:$C,rs_nova!$A20,topmanager!$A:$A,908)+SUMIFS(topmanager!$D:$D,topmanager!$C:$C,rs_nova!$A20,topmanager!$A:$A,550) -> 0 | N20: =SUMIFS(topmanager!$D:$D,topmanager!$C:$C,rs_nova!$A20,topmanager!$A:$A,rs_nova!N$2) -> 0 | O20: =SUM(H20:N20) -> 0 | P20: =IFERROR(VLOOKUP($A20,total!$B$4:$AW$437,27,0),0) -> 0 | Q20: =IFERROR(VLOOKUP($A20,total!$B$4:$AW$437,21,0),0) -> 0 | R20: =IFERROR(VLOOKUP($A20,total!$B$4:$AW$437,25,0),0)+IFERROR(VLOOKUP($A20,total!$B$4:$AW$437,36,0),0) -> 0 | S20: =IFERROR(VLOOKUP(A20,gympass!$A$2:$F$148,6,0),0) -> 166.66667 | T20: =IFERROR(VLOOKUP($A20,total!$B$4:$AW$437,42,0),0) -> 66.666667 | U20: =IFERROR(VLOOKUP($A20,total!$B$4:$AW$437,32,0),0) -> 0 | V20: =IFERROR(VLOOKUP($A20,total!$B$4:$AW$437,28,0),0) -> 0 | W20: =IFERROR(VLOOKUP($A20,total!$B$4:$AX$437,49,0),0) -> 0 | Y20: =IFERROR(VLOOKUP(A20,#REF!,4,0),0) -> 0 | Z20: =IFERROR(VLOOKUP(B20,#REF!,8,0),0) -> 0 | AA20: =IFERROR(VLOOKUP($A20,total!$B$4:$AW$437,45,0),0) -> 0 | AB20: =IFERROR(VLOOKUP($A20,total!$B$4:$AW$437,48,0),0) -> 0 | AC20: =IFERROR(VLOOKUP($A20,total!$B$4:$AB$437,19,0),0) -> 0 | AD20: =IFERROR(VLOOKUP($A20,total!$B$4:$AB$437,10,0),0) -> 196.1835 | AE20: =IFERROR(VLOOKUP($A20,total!$B$4:$AB$437,13,0),0)-SUMIFS(topmanager!$D:$D,topmanager!$C:$C,rs_nova!$A24,topmanager!$A:$A,856) -> 490 | AF20: =IFERROR(VLOOKUP($A20,total!$B$4:$AB$437,16,0),0) -> 1.7607006 | AG20: =total!AJ16 -> 0 | AH20: =IFERROR(VLOOKUP($A20,total!$B$4:$AD$437,29,0),0) -> 275 | AI20: =IFERROR(VLOOKUP(A20,total!$B$4:$AN$437,39,0),0) -> 100 | AJ20: =SUM(P20:AI20) -> 1296.2775 | AK20: =AK$5*($BN20-BG20) -> 0 | AL20: =AL$5*($BN20+BJ20+BK20+BL20+BM20) -> 0 | AM20: =IF(F20="NÃO",0,AM$5*$BN20) -> 0 | AN20: =IF(AND($A20>1000,$A20<=1999),0,AN$5*$G20) -> 91.809928 | AO20: =IF(AND($A20>1000,$A20<=1999),0,AO$5*$G20) -> 44.0864 | AP20: =IF(AND($A20>1000,$A20<=1999),0,AP$5*$G20) -> 38.5756 | AQ20: =IFERROR(VLOOKUP(TEXT($A20,"000000"),[6]Página1!$A$8:$S$801,13,FALSE),0) -> 0 | AR20: =IFERROR(VLOOKUP(TEXT($A20,"000000"),[6]Página1!$A$8:$S$801,16,FALSE),0) -> 0 | AS20: =IFERROR(VLOOKUP(TEXT($A20,"000000"),[6]Página1!$A$8:$S$801,19,FALSE),0) -> 0 | AT20: =IFERROR(VLOOKUP(TEXT($A20,"000000"),[7]Página1!$A$8:$R$814,12,FALSE),0) -> 0 | AU20: =IFERROR(VLOOKUP(TEXT($A20,"000000"),[7]Página1!$A$8:$R$814,15,FALSE),0) -> 0 | AV20: =IFERROR(VLOOKUP(TEXT($A20,"000000"),[7]Página1!$A$8:$R$814,18,FALSE),0) -> 0 | AX20: =SUM(AK20:AW20) -> 174.47193 | AY20: =AN20+AO20+AP20 -> 174.47193 | AZ20: =AX20+AJ20+O20+G20-AY20 -> 2398.4375 | BA20: =AX20+AJ20+O20+G20 -> 2572.9095 | BB20: =($G20)/$BB$3 -> 6.8885 | BC20: =$AX20/$BB$3 -> 1.0904496 | BD20: =$AJ20/$BB$3 -> 8.1017346 | BE20: =IFERROR(VLOOKUP(A20,salario!A$2:P$91,11,FALSE),0) -> 1102.16 | BF20: =SUMIFS(topmanager!$D:$D,topmanager!$C:$C,rs_nova!$A20,topmanager!$A:$A,rs_nova!BF$2) -> 0 | BG20: =SUMIFS(topmanager!$D:$D,topmanager!$C:$C,rs_nova!$A20,topmanager!$A:$A,rs_nova!BG$2) -> 0 | BH20: =SUMIFS(topmanager!$D:$D,topmanager!$C:$C,rs_nova!$A20,topmanager!$A:$A,rs_nova!BH$2) -> 0 | BI20: =SUMIFS(topmanager!$D:$D,topmanager!$C:$C,rs_nova!$A20,topmanager!$A:$A,rs_nova!BI$2) -> 0 | BJ20: =SUMIFS(topmanager!$D:$D,topmanager!$C:$C,rs_nova!$A20,topmanager!$A:$A,rs_nova!BJ$2)+SUMIFS(topmanager!$D:$D,topmanager!$C:$C,rs_nova!$A20,topmanager!$A:$A,rs_nova!BJ$2+1) -> 0 | BK20: =IFERROR(VLOOKUP(A20,[8]ferias!$C$4:$G$100,5,FALSE),0) -> 0 | BL20: =SUMIFS(topmanager!$D:$D,topmanager!$C:$C,rs_nova!$A20,topmanager!$A:$A,rs_nova!BL$2) -> 0 | BM20: =SUMIFS(topmanager!$D:$D,topmanager!$C:$C,rs_nova!$A20,topmanager!$A:$A,rs_nova!BM$2)+SUMIFS(topmanager!$D:$D,topmanager!$C:$C,rs_nova!$A24,topmanager!$A:$A,151) -> 0 | BN20: =BF20+BG20+BH20+BI20+P20+O20+W20 -> 0
A21: =total!B17 -> 14 | B21: =IFERROR(IF(E21="",IF(D21<=B$2,30,31-DAY(D21)),IF(E21<B$2,0,IF(D21>=B$2,DAY(E21)-DAY(D21),DAY(E21)))),0) -> 30 | C21: =total!D17 -> Colaborador 14 | D21: =IFERROR(VLOOKUP(A21,salario!A$3:J$32,10,FALSE),"") -> 46023 | E21: =IFERROR(IF(VLOOKUP(A21,salario!A$3:O$32,15,FALSE)="","",VLOOKUP(A21,salario!A$3:O$32,15,FALSE)),"") | F21: =IFERROR(VLOOKUP(A21,[5]base_pessoal!$B$2:$P$1504,13,FALSE),"") | G21: =IFERROR(VLOOKUP(A21,salario!A$2:P$91,11,FALSE),0)*B21/30 -> 5617.18 | H21: =SUMIFS(topmanager!$D:$D,topmanager!$C:$C,rs_nova!$A21,topmanager!$A:$A,rs_nova!H$2)+SUMIFS(topmanager!$D:$D,topmanager!$C:$C,rs_nova!$A21,topmanager!$A:$A,63) -> 0 | I21: =-SUMIFS(topmanager!$D:$D,topmanager!$C:$C,rs_nova!$A21,topmanager!$A:$A,rs_nova!I$2) -> 0 | J21: =SUMIFS(topmanager!$D:$D,topmanager!$C:$C,rs_nova!$A21,topmanager!$A:$A,rs_nova!J$2) -> 0 | K21: =SUMIFS(topmanager!$D:$D,topmanager!$C:$C,rs_nova!$A21,topmanager!$A:$A,rs_nova!K$2)+SUMIFS(topmanager!$D:$D,topmanager!$C:$C,rs_nova!$A21,topmanager!$A:$A,911) -> 0 | L21: =SUMIFS(topmanager!$D:$D,topmanager!$C:$C,rs_nova!$A21,topmanager!$A:$A,rs_nova!L$2) -> 0 | M21: =SUMIFS(topmanager!$D:$D,topmanager!$C:$C,rs_nova!$A21,topmanager!$A:$A,rs_nova!M$2)+SUMIFS(topmanager!$D:$D,topmanager!$C:$C,rs_nova!$A21,topmanager!$A:$A,908)+SUMIFS(topmanager!$D:$D,topmanager!$C:$C,rs_nova!$A21,topmanager!$A:$A,550) -> 0 | N21: =SUMIFS(topmanager!$D:$D,topmanager!$C:$C,rs_nova!$A21,topmanager!$A:$A,rs_nova!N$2) -> 0 | O21: =SUM(H21:N21) -> 0 | P21: =IFERROR(VLOOKUP($A21,total!$B$4:$AW$437,27,0),0) -> 0 | Q21: =IFERROR(VLOOKUP($A21,total!$B$4:$AW$437,21,0),0) -> 0 | R21: =IFERROR(VLOOKUP($A21,total!$B$4:$AW$437,25,0),0)+IFERROR(VLOOKUP($A21,total!$B$4:$AW$437,36,0),0) -> 0 | S21: =IFERROR(VLOOKUP(A21,gympass!$A$2:$F$148,6,0),0) -> 166.66667 | T21: =IFERROR(VLOOKUP($A21,total!$B$4:$AW$437,42,0),0) -> 66.666667 | U21: =IFERROR(VLOOKUP($A21,total!$B$4:$AW$437,32,0),0) -> 0 | V21: =IFERROR(VLOOKUP($A21,total!$B$4:$AW$437,28,0),0) -> 0 | W21: =IFERROR(VLOOKUP($A21,total!$B$4:$AX$437,49,0),0) -> 0 | Y21: =IFERROR(VLOOKUP(A21,#REF!,4,0),0) -> 0 | Z21: =IFERROR(VLOOKUP(B21,#REF!,8,0),0) -> 0 | AA21: =IFERROR(VLOOKUP($A21,total!$B$4:$AW$437,45,0),0) -> 0 | AB21: =IFERROR(VLOOKUP($A21,total!$B$4:$AW$437,48,0),0) -> 0 | AC21: =IFERROR(VLOOKUP($A21,total!$B$4:$AB$437,19,0),0) -> 0 | AD21: =IFERROR(VLOOKUP($A21,total!$B$4:$AB$437,10,0),0) -> 179.3075 | AE21: =IFERROR(VLOOKUP($A21,total!$B$4:$AB$437,13,0),0)-SUMIFS(topmanager!$D:$D,topmanager!$C:$C,rs_nova!$A25,topmanager!$A:$A,856) -> 517 | AF21: =IFERROR(VLOOKUP($A21,total!$B$4:$AB$437,16,0),0) -> 8.9734451 | AG21: =IFERROR(VLOOKUP($A21,total!$B$4:$AB$437,7,0),0) -> 0 | AH21: =IFERROR(VLOOKUP($A21,total!$B$4:$AD$437,29,0),0) -> 275 | AI21: =IFERROR(VLOOKUP(A21,total!$B$4:$AN$437,39,0),0) -> 100 | AJ21: =SUM(P21:AI21) -> 1313.6143 | AK21: =AK$5*($BN21-BG21) -> 0 | AL21: =AL$5*($BN21+BJ21+BK21+BL21+BM21) -> 0 | AM21: =IF(F21="NÃO",0,AM$5*$BN21) -> 0 | AN21: =IF(AND($A21>1000,$A21<=1999),0,AN$5*$G21) -> 467.91109 | AO21: =IF(AND($A21>1000,$A21<=1999),0,AO$5*$G21) -> 224.6872 | AP21: =IF(AND($A21>1000,$A21<=1999),0,AP$5*$G21) -> 196.6013 | AQ21: =IFERROR(VLOOKUP(TEXT($A21,"000000"),[6]Página1!$A$8:$S$801,13,FALSE),0) -> 0 | AR21: =IFERROR(VLOOKUP(TEXT($A21,"000000"),[6]Página1!$A$8:$S$801,16,FALSE),0) -> 0 | AS21: =IFERROR(VLOOKUP(TEXT($A21,"000000"),[6]Página1!$A$8:$S$801,19,FALSE),0) -> 0 | AT21: =IFERROR(VLOOKUP(TEXT($A21,"000000"),[7]Página1!$A$8:$R$814,12,FALSE),0) -> 0 | AU21: =IFERROR(VLOOKUP(TEXT($A21,"000000"),[7]Página1!$A$8:$R$814,15,FALSE),0) -> 0 | AV21: =IFERROR(VLOOKUP(TEXT($A21,"000000"),[7]Página1!$A$8:$R$814,18,FALSE),0) -> 0 | AX21: =SUM(AK21:AW21) -> 889.19959 | AY21: =AN21+AO21+AP21 -> 889.19959 | AZ21: =AX21+AJ21+O21+G21-AY21 -> 6930.7943 | BA21: =AX21+AJ21+O21+G21 -> 7819.9939 | BB21: =($G21)/$BB$3 -> 35.107375 | BC21: =$AX21/$BB$3 -> 5.5574975 | BD21: =$AJ21/$BB$3 -> 8.2100892 | BE21: =IFERROR(VLOOKUP(A21,salario!A$2:P$91,11,FALSE),0) -> 5617.18 | BF21: =SUMIFS(topmanager!$D:$D,topmanager!$C:$C,rs_nova!$A21,topmanager!$A:$A,rs_nova!BF$2) -> 0 | BG21: =SUMIFS(topmanager!$D:$D,topmanager!$C:$C,rs_nova!$A21,topmanager!$A:$A,rs_nova!BG$2) -> 0 | BH21: =SUMIFS(topmanager!$D:$D,topmanager!$C:$C,rs_nova!$A21,topmanager!$A:$A,rs_nova!BH$2) -> 0 | BI21: =SUMIFS(topmanager!$D:$D,topmanager!$C:$C,rs_nova!$A21,topmanager!$A:$A,rs_nova!BI$2) -> 0 | BJ21: =SUMIFS(topmanager!$D:$D,topmanager!$C:$C,rs_nova!$A21,topmanager!$A:$A,rs_nova!BJ$2)+SUMIFS(topmanager!$D:$D,topmanager!$C:$C,rs_nova!$A21,topmanager!$A:$A,rs_nova!BJ$2+1) -> 0 | BK21: =IFERROR(VLOOKUP(A21,[8]ferias!$C$4:$G$100,5,FALSE),0) -> 0 | BL21: =SUMIFS(topmanager!$D:$D,topmanager!$C:$C,rs_nova!$A21,topmanager!$A:$A,rs_nova!BL$2) -> 0 | BM21: =SUMIFS(topmanager!$D:$D,topmanager!$C:$C,rs_nova!$A21,topmanager!$A:$A,rs_nova!BM$2)+SUMIFS(topmanager!$D:$D,topmanager!$C:$C,rs_nova!$A25,topmanager!$A:$A,151) -> 0 | BN21: =BF21+BG21+BH21+BI21+P21+O21+W21 -> 0
A22: =total!B18 -> 15 | B22: =IFERROR(IF(E22="",IF(D22<=B$2,30,31-DAY(D22)),IF(E22<B$2,0,IF(D22>=B$2,DAY(E22)-DAY(D22),DAY(E22)))),0) -> 30 | C22: =total!D18 -> Colaborador 15 | D22: =IFERROR(VLOOKUP(A22,salario!A$3:J$32,10,FALSE),"") -> 46023 | E22: =IFERROR(IF(VLOOKUP(A22,salario!A$3:O$32,15,FALSE)="","",VLOOKUP(A22,salario!A$3:O$32,15,FALSE)),"") | F22: =IFERROR(VLOOKUP(A22,[5]base_pessoal!$B$2:$P$1504,13,FALSE),"") | G22: =IFERROR(VLOOKUP(A22,salario!A$2:P$91,11,FALSE),0)*B22/30 -> 5591.86 | H22: =SUMIFS(topmanager!$D:$D,topmanager!$C:$C,rs_nova!$A22,topmanager!$A:$A,rs_nova!H$2)+SUMIFS(topmanager!$D:$D,topmanager!$C:$C,rs_nova!$A22,topmanager!$A:$A,63) -> 0 | I22: =-SUMIFS(topmanager!$D:$D,topmanager!$C:$C,rs_nova!$A22,topmanager!$A:$A,rs_nova!I$2) -> 0 | J22: =SUMIFS(topmanager!$D:$D,topmanager!$C:$C,rs_nova!$A22,topmanager!$A:$A,rs_nova!J$2) -> 0 | K22: =SUMIFS(topmanager!$D:$D,topmanager!$C:$C,rs_nova!$A22,topmanager!$A:$A,rs_nova!K$2)+SUMIFS(topmanager!$D:$D,topmanager!$C:$C,rs_nova!$A22,topmanager!$A:$A,911) -> 0 | L22: =SUMIFS(topmanager!$D:$D,topmanager!$C:$C,rs_nova!$A22,topmanager!$A:$A,rs_nova!L$2) -> 0 | M22: =SUMIFS(topmanager!$D:$D,topmanager!$C:$C,rs_nova!$A22,topmanager!$A:$A,rs_nova!M$2)+SUMIFS(topmanager!$D:$D,topmanager!$C:$C,rs_nova!$A22,topmanager!$A:$A,908)+SUMIFS(topmanager!$D:$D,topmanager!$C:$C,rs_nova!$A22,topmanager!$A:$A,550) -> 0 | N22: =SUMIFS(topmanager!$D:$D,topmanager!$C:$C,rs_nova!$A22,topmanager!$A:$A,rs_nova!N$2) -> 0 | O22: =SUM(H22:N22) -> 0 | P22: =IFERROR(VLOOKUP($A22,total!$B$4:$AW$437,27,0),0) -> 0 | Q22: =IFERROR(VLOOKUP($A22,total!$B$4:$AW$437,21,0),0) -> 0 | R22: =IFERROR(VLOOKUP($A22,total!$B$4:$AW$437,25,0),0)+IFERROR(VLOOKUP($A22,total!$B$4:$AW$437,36,0),0) -> 0 | S22: =IFERROR(VLOOKUP(A22,gympass!$A$2:$F$148,6,0),0) -> 166.66667 | T22: =IFERROR(VLOOKUP($A22,total!$B$4:$AW$437,42,0),0) -> 66.666667 | U22: =IFERROR(VLOOKUP($A22,total!$B$4:$AW$437,32,0),0) -> 0 | V22: =IFERROR(VLOOKUP($A22,total!$B$4:$AW$437,28,0),0) -> 0 | W22: =IFERROR(VLOOKUP($A22,total!$B$4:$AX$437,49,0),0) -> 0 | Y22: =IFERROR(VLOOKUP(A22,#REF!,4,0),0) -> 0 | Z22: =IFERROR(VLOOKUP(B22,#REF!,8,0),0) -> 0 | AA22: =IFERROR(VLOOKUP($A22,total!$B$4:$AW$437,45,0),0) -> 0 | AB22: =IFERROR(VLOOKUP($A22,total!$B$4:$AW$437,48,0),0) -> 0 | AC22: =IFERROR(VLOOKUP($A22,total!$B$4:$AB$437,19,0),0) -> 0 | AD22: =IFERROR(VLOOKUP($A22,total!$B$4:$AB$437,10,0),0) -> 35.8615 | AE22: =IFERROR(VLOOKUP($A22,total!$B$4:$AB$437,13,0),0)-SUMIFS(topmanager!$D:$D,topmanager!$C:$C,rs_nova!$A26,topmanager!$A:$A,856) -> 470 | AF22: =IFERROR(VLOOKUP($A22,total!$B$4:$AB$437,16,0),0) -> 8.9329963 | AG22: =IFERROR(VLOOKUP($A22,total!$B$4:$AB$437,7,0),0) -> 0 | AH22: =IFERROR(VLOOKUP($A22,total!$B$4:$AD$437,29,0),0) -> 275 | AI22: =IFERROR(VLOOKUP(A22,total!$B$4:$AN$437,39,0),0) -> 100 | AJ22: =SUM(P22:AI22) -> 1123.1278 | AK22: =AK$5*($BN22-BG22) -> 0 | AL22: =AL$5*($BN22+BJ22+BK22+BL22+BM22) -> 0 | AM22: =IF(F22="NÃO",0,AM$5*$BN22) -> 0 | AN22: =IF(AND($A22>1000,$A22<=1999),0,AN$5*$G22) -> 465.80194 | AO22: =IF(AND($A22>1000,$A22<=1999),0,AO$5*$G22) -> 223.6744 | AP22: =IF(AND($A22>1000,$A22<=1999),0,AP$5*$G22) -> 195.7151 | AQ22: =IFERROR(VLOOKUP(TEXT($A22,"000000"),[6]Página1!$A$8:$S$801,13,FALSE),0) -> 0 | AR22: =IFERROR(VLOOKUP(TEXT($A22,"000000"),[6]Página1!$A$8:$S$801,16,FALSE),0) -> 0 | AS22: =IFERROR(VLOOKUP(TEXT($A22,"000000"),[6]Página1!$A$8:$S$801,19,FALSE),0) -> 0 | AT22: =IFERROR(VLOOKUP(TEXT($A22,"000000"),[7]Página1!$A$8:$R$814,12,FALSE),0) -> 0 | AU22: =IFERROR(VLOOKUP(TEXT($A22,"000000"),[7]Página1!$A$8:$R$814,15,FALSE),0) -> 0 | AV22: =IFERROR(VLOOKUP(TEXT($A22,"000000"),[7]Página1!$A$8:$R$814,18,FALSE),0) -> 0 | AX22: =SUM(AK22:AW22) -> 885.19144 | AY22: =AN22+AO22+AP22 -> 885.19144 | AZ22: =AX22+AJ22+O22+G22-AY22 -> 6714.9878 | BA22: =AX22+AJ22+O22+G22 -> 7600.1793 | BB22: =($G22)/$BB$3 -> 34.949125 | BC22: =$AX22/$BB$3 -> 5.5324465 | BD22: =$AJ22/$BB$3 -> 7.0195489 | BE22: =IFERROR(VLOOKUP(A22,salario!A$2:P$91,11,FALSE),0) -> 5591.86 | BF22: =SUMIFS(topmanager!$D:$D,topmanager!$C:$C,rs_nova!$A22,topmanager!$A:$A,rs_nova!BF$2) -> 0 | BG22: =SUMIFS(topmanager!$D:$D,topmanager!$C:$C,rs_nova!$A22,topmanager!$A:$A,rs_nova!BG$2) -> 0 | BH22: =SUMIFS(topmanager!$D:$D,topmanager!$C:$C,rs_nova!$A22,topmanager!$A:$A,rs_nova!BH$2) -> 0 | BI22: =SUMIFS(topmanager!$D:$D,topmanager!$C:$C,rs_nova!$A22,topmanager!$A:$A,rs_nova!BI$2) -> 0 | BJ22: =SUMIFS(topmanager!$D:$D,topmanager!$C:$C,rs_nova!$A22,topmanager!$A:$A,rs_nova!BJ$2)+SUMIFS(topmanager!$D:$D,topmanager!$C:$C,rs_nova!$A22,topmanager!$A:$A,rs_nova!BJ$2+1) -> 0 | BK22: =IFERROR(VLOOKUP(A22,[8]ferias!$C$4:$G$100,5,FALSE),0) -> 0 | BL22: =SUMIFS(topmanager!$D:$D,topmanager!$C:$C,rs_nova!$A22,topmanager!$A:$A,rs_nova!BL$2) -> 0 | BM22: =SUMIFS(topmanager!$D:$D,topmanager!$C:$C,rs_nova!$A22,topmanager!$A:$A,rs_nova!BM$2)+SUMIFS(topmanager!$D:$D,topmanager!$C:$C,rs_nova!$A26,topmanager!$A:$A,151) -> 0 | BN22: =BF22+BG22+BH22+BI22+P22+O22+W22 -> 0
